Workbook

Sheet 2022-2026 IRS Updates
A1: 2022-2026 IRS Tax Code Updates
A2: Prepared: April 2026 | Sources: IRS Rev. Procs. 2021-45, 2022-38, 2023-34, 2024-40, 2025-32; SSA OASDI & Medicare; One Big Beautiful Bill Act (July 2025)
A3: Legend: | B3: Blue text = hardcoded inputs from official sources | E3: Yellow = unconfirmed - needs review
A5: Social Security Taxable Wages & Medicare Rates
A6: Tax Year | B6: SS Tax Rate | C6: Max Wage Base ($) | D6: Medicare Tax Rate | E6: Addl Medicare (>$200K)
A7: 2022 | B7: 0.062 | C7: 147000 | D7: 0.0145 | E7: 0.009
A8: 2023 | B8: 0.062 | C8: 160200 | D8: 0.0145 | E8: 0.009
A9: 2024 | B9: 0.062 | C9: 168600 | D9: 0.0145 | E9: 0.009
A10: 2025 | B10: 0.062 | C10: 176100 | D10: 0.0145 | E10: 0.009
A11: 2026 | B11: 0.062 | C11: 184500 | D11: 0.0145 | E11: 0.009
A13: Source: SSA Fact Sheet on 2022-2026 Social Security Changes; ssa.gov/OACT/COLA/cbb.html
A15: Standard Deduction by Filing Status
A16: Tax Year | B16: MFJ / QSS ($) | C16: Single ($) | D16: HoH ($) | E16: MFS ($)
A17: 2022 | B17: 25900 | C17: 12950 | D17: 19400 | E17: 12950
A18: 2023 | B18: 27700 | C18: 13850 | D18: 20800 | E18: 13850
A19: 2024 | B19: 29200 | C19: 14600 | D19: 21900 | E19: 14600
A20: 2025 | B20: 31500 | C20: 15750 | D20: 23625 | E20: 15750
A21: 2026 | B21: 32200 | C21: 16100 | D21: 24150 | E21: 16100
A23: Source: IRS Rev. Proc. 2021-45, 2022-38, 2023-34, 2024-40, 2025-32
A25: Alternative Minimum Tax (AMT)
A26: AMT Exemption
A27: Tax Year | B27: MFJ ($) | C27: Single / HoH ($) | D27: MFS ($)
A28: 2022 | B28: 118100 | C28: 75900 | D28: 59050
A29: 2023 | B29: 126500 | C29: 81300 | D29: 63250
A30: 2024 | B30: 133300 | C30: 85700 | D30: 66650
A31: 2025 | B31: 137000 | C31: 88100 | D31: 68500
A32: 2026 | B32: 140200 | C32: 90100 | D32: 70100
A34: AMT 26%/28% Breakpoint
A35: Tax Year | B35: MFJ / Single / HoH ($) | C35: MFS ($)
A36: 2022 | B36: 206100 | C36: 103050
A37: 2023 | B37: 220700 | C37: 110350
A38: 2024 | B38: 232600 | C38: 116300
A39: 2025 | B39: 239100 | C39: 119550
A40: 2026 | B40: 244500 | C40: 122250
A42: AMT Exemption Phase-out Threshold Start
A43: Tax Year | B43: MFJ ($) | C43: Single / HoH ($) | D43: MFS ($)
A44: 2022 | B44: 1079800 | C44: 539900 | D44: 539900
A45: 2023 | B45: 1156300 | C45: 578150 | D45: 578150
A46: 2024 | B46: 1218700 | C46: 609350 | D46: 609350
A47: 2025 | B47: 1252700 | C47: 626350 | D47: 626350
A48: 2026 | B48: 1000000 | C48: 500000 | D48: 500000
A50: Source: IRC Sec. 55; IRS Rev. Procs. 2021-45 through 2025-32; OBBBA of 2025 Sec. 70107
A52: Federal Income Tax Brackets (Upper Limit of Each Bracket)
A53: Married Filing Jointly
A54: Tax Year | B54: 10% | C54: 12% | D54: 22% | E54: 24% | F54: 32% | G54: 35% | H54: 37%
A55: 2022 | B55: 20550 | C55: 83550 | D55: 178150 | E55: 340100 | F55: 431900 | G55: 647850 | H55: above
A56: 2023 | B56: 22000 | C56: 89450 | D56: 190750 | E56: 364200 | F56: 462500 | G56: 693750 | H56: above
A57: 2024 | B57: 23200 | C57: 94300 | D57: 201050 | E57: 383900 | F57: 487450 | G57: 731200 | H57: above
A58: 2025 | B58: 23850 | C58: 96950 | D58: 206700 | E58: 394600 | F58: 501050 | G58: 751600 | H58: above
A59: 2026 | B59: 24800 | C59: 100800 | D59: 211400 | E59: 403550 | F59: 512450 | G59: 768700 | H59: above
A61: Single
A62: Tax Year | B62: 10% | C62: 12% | D62: 22% | E62: 24% | F62: 32% | G62: 35% | H62: 37%
A63: 2022 | B63: 10275 | C63: 41775 | D63: 89075 | E63: 170050 | F63: 215950 | G63: 539900 | H63: above
A64: 2023 | B64: 11000 | C64: 44725 | D64: 95375 | E64: 182100 | F64: 231250 | G64: 578125 | H64: above
A65: 2024 | B65: 11600 | C65: 47150 | D65: 100525 | E65: 191950 | F65: 243725 | G65: 609350 | H65: above
A66: 2025 | B66: 11925 | C66: 48475 | D66: 103350 | E66: 197300 | F66: 250525 | G66: 626350 | H66: above
A67: 2026 | B67: 12400 | C67: 50400 | D67: 105700 | E67: 201775 | F67: 256225 | G67: 640600 | H67: above
A69: Head of Household
A70: Tax Year | B70: 10% | C70: 12% | D70: 22% | E70: 24% | F70: 32% | G70: 35% | H70: 37%
A71: 2022 | B71: 14650 | C71: 55900 | D71: 89050 | E71: 170050 | F71: 215950 | G71: 539900 | H71: above
A72: 2023 | B72: 15700 | C72: 59850 | D72: 95350 | E72: 182100 | F72: 231250 | G72: 578100 | H72: above
A73: 2024 | B73: 16550 | C73: 63100 | D73: 100500 | E73: 191950 | F73: 243700 | G73: 609350 | H73: above
A74: 2025 | B74: 17000 | C74: 64850 | D74: 103350 | E74: 197300 | F74: 250500 | G74: 626350 | H74: above
A75: 2026 | B75: 17700 | C75: 67450 | D75: 105700 | E75: 201750 | F75: 256200 | G75: 640600 | H75: above
A77: Married Filing Separately
A78: Tax Year | B78: 10% | C78: 12% | D78: 22% | E78: 24% | F78: 32% | G78: 35% | H78: 37%
A79: 2022 | B79: 10275 | C79: 41775 | D79: 89075 | E79: 170050 | F79: 215950 | G79: 323925 | H79: above
A80: 2023 | B80: 11000 | C80: 44725 | D80: 95375 | E80: 182100 | F80: 231250 | G80: 346875 | H80: above
A81: 2024 | B81: 11600 | C81: 47150 | D81: 100525 | E81: 191950 | F81: 243725 | G81: 365600 | H81: above
A82: 2025 | B82: 11925 | C82: 48475 | D82: 103350 | E82: 197300 | F82: 250525 | G82: 375800 | H82: above
A83: 2026 | B83: 12400 | C83: 50400 | D83: 105700 | E83: 201775 | F83: 256225 | G83: 384350 | H83: above
A85: Trusts & Estates
A86: Tax Year | B86: 10% | C86: 24% | D86: 35% | E86: 37%
A87: 2022 | B87: 2750 | C87: 9850 | D87: 13450 | E87: above
A88: 2023 | B88: 2900 | C88: 10550 | D88: 14450 | E88: above
A89: 2024 | B89: 3100 | C89: 11150 | D89: 15200 | E89: above
A90: 2025 | B90: 3150 | C90: 11450 | D90: 15650 | E90: above
A91: 2026 | B91: 3300 | C91: 11700 | D91: 16000 | E91: above
A93: Source: IRC Sec. 1; IRS Rev. Procs. 2021-45, 2022-38, 2023-34, 2024-40, 2025-32. Rates made permanent by OBBBA (July 2025).
A95: Long-Term Capital Gains & Qualified Dividend Brackets
A96: Married Filing Jointly
A97: Tax Year | B97: 0% Bracket Top ($) | C97: 15% Bracket Top ($) | D97: 20% Applies Above ($)
A98: 2022 | B98: 83350 | C98: 517200 | D98: 517200
A99: 2023 | B99: 89250 | C99: 553850 | D99: 553850
A100: 2024 | B100: 94050 | C100: 583750 | D100: 583750
A101: 2025 | B101: 96700 | C101: 600050 | D101: 600050
A102: 2026 | B102: 98900 | C102: 613700 | D102: 613700
A104: Single
A105: Tax Year | B105: 0% Bracket Top ($) | C105: 15% Bracket Top ($) | D105: 20% Applies Above ($)
A106: 2022 | B106: 41675 | C106: 459750 | D106: 459750
A107: 2023 | B107: 44625 | C107: 492300 | D107: 492300
A108: 2024 | B108: 47025 | C108: 518900 | D108: 518900
A109: 2025 | B109: 48350 | C109: 533400 | D109: 533400
A110: 2026 | B110: 49450 | C110: 545500 | D110: 545500
A112: Head of Household
A113: Tax Year | B113: 0% Bracket Top ($) | C113: 15% Bracket Top ($) | D113: 20% Applies Above ($)
A114: 2022 | B114: 55800 | C114: 488500 | D114: 488500
A115: 2023 | B115: 59750 | C115: 523050 | D115: 523050
A116: 2024 | B116: 63000 | C116: 551350 | D116: 551350
A117: 2025 | B117: 64750 | C117: 566700 | D117: 566700
...

Sheet General
A1: Revision History
A3: 44119 | B3: V2021.0 | C3: New version for the 2021 tax year.
A6: IRC 7520 Rate
A7: Historic IRC 7520 Rates | B7: Dec | C7: Nov | D7: Oct | E7: Sep | F7: Aug | G7: Jul | H7: Jun | I7: May | J7: Apr | K7: Mar | L7: Feb | M7: Jan
A8: For 2020 | B8: 0.006 | C8: 0.004 | D8: 0.004 | E8: 0.004 | F8: 0.004 | G8: 0.006 | H8: 0.006 | I8: 0.008 | J8: 0.012 | K8: 0.018 | L8: 0.022 | M8: 0.02
A9: For 2019 | B9: 0.02 | C9: 0.02 | D9: 0.018 | E9: 0.022 | F9: 0.022 | G9: 0.026 | H9: 0.028 | I9: 0.028 | J9: 0.03 | K9: 0.032 | L9: 0.032 | M9: 0.034
A10: For 2018 | B10: 0.036 | C10: 0.036 | D10: 0.034 | E10: 0.034 | F10: 0.034 | G10: 0.034 | H10: 0.034 | I10: 0.032 | J10: 0.032 | K10: 0.03 | L10: 0.028 | M10: 0.026
A11: For 2017 | B11: 0.026 | C11: 0.024 | D11: 0.022 | E11: 0.024 | F11: 0.024 | G11: 0.022 | H11: 0.024 | I11: 0.024 | J11: 0.026 | K11: 0.024 | L11: 0.026 | M11: 0.024
A12: For 2016 | B12: 0.018 | C12: 0.016 | D12: 0.016 | E12: 0.014 | F12: 0.014 | G12: 0.018 | H12: 0.018 | I12: 0.018 | J12: 0.018 | K12: 0.018 | L12: 0.022 | M12: 0.022
A13: For 2015 | B13: 0.02 | C13: 0.02 | D13: 0.02 | E13: 0.022 | F13: 0.022 | G13: 0.022 | H13: 0.02 | I13: 0.018 | J13: 0.02 | K13: 0.018 | L13: 0.02 | M13: 0.022
A14: For 2014 | B14: 0.02 | C14: 0.022 | D14: 0.0222 | E14: 0.022 | F14: 0.022 | G14: 0.022 | H14: 0.022 | I14: 0.024 | J14: 0.022 | K14: 0.022 | L14: 0.022 | M14: 0.022
A15: For 2013 | B15: 0.02 | C15: 0.02 | D15: 0.024 | E15: 0.02 | F15: 0.02 | G15: 0.014 | H15: 0.012 | I15: 0.012 | J15: 0.014 | K15: 0.014 | L15: 0.012 | M15: 0.01
A16: For 2012 | B16: 0.012 | C16: 0.01 | D16: 0.012 | E16: 0.01 | F16: 0.01 | G16: 0.012 | H16: 0.012 | I16: 0.016 | J16: 0.014 | K16: 0.014 | L16: 0.014 | M16: 0.014
A17: For 2011 | B17: 0.016 | C17: 0.014 | D17: 0.014 | E17: 0.02 | F17: 0.022 | G17: 0.024 | H17: 0.028 | I17: 0.03 | J17: 0.03 | K17: 0.03 | L17: 0.028 | M17: 0.024
A18: For 2010 | B18: 0.018 | C18: 0.02 | D18: 0.02 | E18: 0.024 | F18: 0.026 | G18: 0.028 | H18: 0.032 | I18: 0.034 | J18: 0.032 | K18: 0.032 | L18: 0.034 | M18: 0.03
A19: For 2009 | B19: 0.032 | C19: 0.032 | D19: 0.032 | E19: 0.034 | F19: 0.034 | G19: 0.034 | H19: 0.028 | I19: 0.024 | J19: 0.026 | K19: 0.024 | L19: 0.02 | M19: 0.024
... A24: For 2004 | B24: 0.042 | C24: 0.042 | D24: 0.044 | E24: 0.048 | F24: 0.046 | G24: 0.05 | H24: 0.046 | I24: 0.038 | J24: 0.038 | K24: 0.04 | L24: 0.042 | M24: 0.042

Sheet Tax Values
A1: Income Tax Rates / Values
A2: NOTE: All values based upon "taxable year".
A3: These are IRS published values. The raw values that we use are under the tabs showing tax law extension.
A4: *** See "2022-2026 IRS Updates" sheet for complete updated 2022-2026 values from IRS Rev. Procs. 2021-45 through 2025-32 and OBBBA 2025 ***
A5: Social Security Taxable Wages
A6: Tax Year | B6: Soc Sec Tax Rate | C6: Max Wages | D6: Medicare Tax Rate
A7: =A8+1 -> 2022 | B7: 0.062 | C7: 147000 | D7: 0.0145
A8: =A9+1 -> 2021 | B8: 0.062 | C8: 142800 | D8: 0.0145
A9: =A10+1 -> 2020 | B9: 0.062 | C9: 137700 | D9: 0.0145
A10: =A11+1 -> 2019 | B10: 0.062 | C10: 132900 | D10: 0.0145
A11: =A12+1 -> 2018 | B11: 0.062 | C11: 130500 | D11: 0.0145
A12: =A13+1 -> 2017 | B12: 0.062 | C12: 127200 | D12: 0.0145
A13: =A14+1 -> 2016 | B13: 0.062 | C13: 118500 | D13: 0.0145 | E13: * no change from 2015
A14: =A15+1 -> 2015 | B14: 0.062 | C14: 118500 | D14: 0.0145
A15: =A16+1 -> 2014 | B15: 0.062 | C15: 117000 | D15: 0.0145
A16: =A17+1 -> 2013 | B16: 0.062 | C16: 113700 | D16: 0.0145 | E16: * returned to 6.2% per American Taxpayer Relief Act of 2012
A17: =A18+1 -> 2012 | B17: 0.042 | C17: 110100 | D17: 0.0145 | E17: * one year reduction only by Congress Dec '11
A18: =A19+1 -> 2011 | B18: 0.042 | C18: 106800 | D18: 0.0145 | E18: * one year reduction only by Congress Dec '10
A19: =A20+1 -> 2010 | B19: 0.062 | C19: 106800 | D19: 0.0145
A20: =A21+1 -> 2009 | B20: 0.062 | C20: 106800 | D20: 0.0145
A21: =A22+1 -> 2008 | B21: 0.062 | C21: 102000 | D21: 0.0145
A22: =A23+1 -> 2007 | B22: 0.062 | C22: 97500 | D22: 0.0145
A23: =A24+1 -> 2006 | B23: 0.062 | C23: 94200 | D23: 0.0145
A24: =A25+1 -> 2005 | B24: 0.062 | C24: 90000 | D24: 0.0145
A25: =A26+1 -> 2004 | B25: 0.062 | C25: 87900 | D25: 0.0145
A26: =A27+1 -> 2003 | B26: 0.062 | C26: 87000 | D26: 0.0145
A27: =A28+1 -> 2002 | B27: 0.062 | C27: 84900 | D27: 0.0145
A28: =A29+1 -> 2001 | B28: 0.062 | C28: 80400 | D28: 0.0145
A29: 2000 | B29: 0.062 | C29: 76200 | D29: 0.0145
A32: Standard Deduction | H32: Standard Deduction (for 2026 Sunset)
A33: Tax Year | B33: Joint * | C33: Single | D33: Joint vs. Single Ratio | E33: Head of Household | F33: Separate | H33: Tax Year | I33: Joint * | J33: Single | K33: Joint vs. Single Ratio | L33: Head of Household | M33: Separate
A34: =A35+1 -> 2022 | B34: ='Tax Value Calcs'!D21 -> 25800 | C34: ='Tax Value Calcs'!F21 -> 12900 | D34: =B34/C34 -> 2 | E34: ='Tax Value Calcs'!H21 -> 19400 | F34: ='Tax Value Calcs'!J21 -> 12900 | H34: =H35+1 -> 2022 | I34: ='Tax Value Calcs'!I33 -> 14000 | J34: ='Tax Value Calcs'!K33 -> 7000 | K34: =I34/J34 -> 2 | L34: ='Tax Value Calcs'!M33 -> 10250 | M34: ='Tax Value Calcs'!O33 -> 7000
A35: =A36+1 -> 2021 | B35: ='Tax Value Calcs'!D22 -> 25100 | C35: ='Tax Value Calcs'!F22 -> 12550 | D35: =B35/C35 -> 2 | E35: ='Tax Value Calcs'!H22 -> 18800 | F35: ='Tax Value Calcs'!J22 -> 12550 | H35: =H36+1 -> 2021 | I35: ='Tax Value Calcs'!I34 -> 13600 | J35: ='Tax Value Calcs'!K34 -> 6800 | K35: =I35/J35 -> 2 | L35: ='Tax Value Calcs'!M34 -> 9950 | M35: ='Tax Value Calcs'!O34 -> 6800
A36: =A37+1 -> 2020 | B36: ='Tax Value Calcs'!D23 -> 24800 | C36: ='Tax Value Calcs'!F23 -> 12400 | D36: =B36/C36 -> 2 | E36: ='Tax Value Calcs'!H23 -> 18600 | F36: ='Tax Value Calcs'!J23 -> 12400 | H36: =H37+1 -> 2020 | I36: ='Tax Value Calcs'!I35 -> 13400 | J36: ='Tax Value Calcs'!K35 -> 6700 | K36: =I36/J36 -> 2 | L36: ='Tax Value Calcs'!M35 -> 9850 | M36: ='Tax Value Calcs'!O35 -> 6700
A37: =A38+1 -> 2019 | B37: ='Tax Value Calcs'!D24 -> 24400 | C37: ='Tax Value Calcs'!F24 -> 12200 | D37: =B37/C37 -> 2 | E37: ='Tax Value Calcs'!H24 -> 18350 | F37: ='Tax Value Calcs'!J24 -> 12200 | H37: =H38+1 -> 2019 | I37: ='Tax Value Calcs'!I36 -> 13200 | J37: ='Tax Value Calcs'!K36 -> 6600 | K37: =I37/J37 -> 2 | L37: ='Tax Value Calcs'!M36 -> 9700 | M37: ='Tax Value Calcs'!O36 -> 6600
A38: =A39+1 -> 2018 | B38: ='Tax Value Calcs'!D25 -> 24000 | C38: ='Tax Value Calcs'!F25 -> 12000 | D38: =B38/C38 -> 2 | E38: ='Tax Value Calcs'!M37 -> 9500 | F38: ='Tax Value Calcs'!O37 -> 6450 | H38: =H39+1 -> 2018 | I38: ='Tax Value Calcs'!I37 -> 12900 | J38: ='Tax Value Calcs'!K37 -> 6450 | K38: =I38/J38 -> 2 | L38: ='Tax Value Calcs'!M37 -> 9500 | M38: ='Tax Value Calcs'!O37 -> 6450
A39: =A40+1 -> 2017 | B39: ='Tax Value Calcs'!I38 -> 12700 | C39: ='Tax Value Calcs'!K38 -> 6350 | D39: =B39/C39 -> 2 | E39: ='Tax Value Calcs'!M38 -> 9350 | F39: ='Tax Value Calcs'!O38 -> 6350 | H39: 2017 | I39: ='Tax Value Calcs'!I38 -> 12700 | J39: ='Tax Value Calcs'!K38 -> 6350 | K39: =I39/J39 -> 2 | L39: ='Tax Value Calcs'!M38 -> 9350 | M39: ='Tax Value Calcs'!O38 -> 6350
A40: =A41+1 -> 2016 | B40: ='Tax Value Calcs'!I39 -> 12600 | C40: ='Tax Value Calcs'!K39 -> 6300 | D40: =B40/C40 -> 2 | E40: ='Tax Value Calcs'!M39 -> 9300 | F40: ='Tax Value Calcs'!O39 -> 6300
A41: =A42+1 -> 2015 | B41: ='Tax Value Calcs'!I40 -> 12600 | C41: ='Tax Value Calcs'!K40 -> 6300 | D41: =B41/C41 -> 2 | E41: ='Tax Value Calcs'!M40 -> 9250 | F41: ='Tax Value Calcs'!O40 -> 6300
A42: =A43+1 -> 2014 | B42: ='Tax Value Calcs'!I41 -> 12400 | C42: ='Tax Value Calcs'!K41 -> 6200 | D42: =B42/C42 -> 2 | E42: ='Tax Value Calcs'!M41 -> 9100 | F42: ='Tax Value Calcs'!O41 -> 6200
A43: =A44+1 -> 2013 | B43: ='Tax Value Calcs'!I42 -> 12200 | C43: ='Tax Value Calcs'!K42 -> 6100 | D43: =B43/C43 -> 2 | E43: ='Tax Value Calcs'!M42 -> 8950 | F43: ='Tax Value Calcs'!O42 -> 6100
A44: =A45+1 -> 2012 | B44: ='Tax Value Calcs'!I43 -> 11900 | C44: ='Tax Value Calcs'!K43 -> 5950 | D44: =B44/C44 -> 2 | E44: ='Tax Value Calcs'!M43 -> 8700 | F44: ='Tax Value Calcs'!O43 -> 5950
A45: =A46+1 -> 2011 | B45: ='Tax Value Calcs'!I44 -> 11600 | C45: ='Tax Value Calcs'!K44 -> 5800 | D45: =B45/C45 -> 2 | E45: ='Tax Value Calcs'!M44 -> 8500 | F45: ='Tax Value Calcs'!O44 -> 5800
A46: =A47+1 -> 2010 | B46: ='Tax Value Calcs'!I45 -> 11400 | C46: ='Tax Value Calcs'!K45 -> 5700 | D46: =B46/C46 -> 2 | E46: ='Tax Value Calcs'!M45 -> 8400 | F46: ='Tax Value Calcs'!O45 -> 5700
A47: =A48+1 -> 2009 | B47: ='Tax Value Calcs'!I46 -> 11400 | C47: ='Tax Value Calcs'!K46 -> 5700 | D47: =B47/C47 -> 2 | E47: ='Tax Value Calcs'!M46 -> 8350 | F47: ='Tax Value Calcs'!O46 -> 5700
A48: =A49+1 -> 2008 | B48: ='Tax Value Calcs'!I47 -> 10900 | C48: ='Tax Value Calcs'!K47 -> 5450 | D48: =B48/C48 -> 2 | E48: ='Tax Value Calcs'!M47 -> 8000 | F48: ='Tax Value Calcs'!O47 -> 5450
A49: =A50+1 -> 2007 | B49: ='Tax Value Calcs'!I48 -> 10700 | C49: ='Tax Value Calcs'!K48 -> 5350 | D49: =B49/C49 -> 2 | E49: ='Tax Value Calcs'!M48 -> 7850 | F49: ='Tax Value Calcs'!O48 -> 5350
A50: =A51+1 -> 2006 | B50: ='Tax Value Calcs'!I49 -> 10300 | C50: ='Tax Value Calcs'!K49 -> 5150 | D50: =B50/C50 -> 2 | E50: ='Tax Value Calcs'!M49 -> 7550 | F50: ='Tax Value Calcs'!O49 -> 5150
A51: =A52+1 -> 2005 | B51: ='Tax Value Calcs'!I50 -> 10000 | C51: ='Tax Value Calcs'!K50 -> 5000 | D51: =B51/C51 -> 2 | E51: ='Tax Value Calcs'!M50 -> 7300 | F51: ='Tax Value Calcs'!O50 -> 5000
A52: =A53+1 -> 2004 | B52: ='Tax Value Calcs'!I51 -> 9700 | C52: ='Tax Value Calcs'!K51 -> 4850 | D52: =B52/C52 -> 2 | E52: ='Tax Value Calcs'!M51 -> 7150 | F52: ='Tax Value Calcs'!O51 -> 4850
A53: =A54+1 -> 2003 | B53: ='Tax Value Calcs'!I52 -> 9500 | C53: ='Tax Value Calcs'!K52 -> 4750 | D53: 2 | E53: ='Tax Value Calcs'!M52 -> 7000 | F53: ='Tax Value Calcs'!O52 -> 4750
A54: =A55+1 -> 2002 | B54: ='Tax Value Calcs'!I53 -> 7850 | C54: ='Tax Value Calcs'!K53 -> 4700 | D54: =B54/C54 -> 1.6702128 | E54: ='Tax Value Calcs'!M53 -> 6900 | F54: ='Tax Value Calcs'!O53 -> 4700
A55: =A56+1 -> 2001 | B55: ='Tax Value Calcs'!I54 -> 7600 | C55: ='Tax Value Calcs'!K54 -> 4550 | D55: =B55/C55 -> 1.6703297 | E55: ='Tax Value Calcs'!M54 -> 6650 | F55: ='Tax Value Calcs'!O54 -> 4550
A56: 2000 | B56: ='Tax Value Calcs'!I55 -> 7350 | C56: ='Tax Value Calcs'!K55 -> 4400 | D56: =B56/C56 -> 1.6704545 | E56: ='Tax Value Calcs'!M55 -> 6450 | F56: ='Tax Value Calcs'!O55 -> 4400
A57: * Joint value calculated as 2X rounded value for single
A59: Personal Exemption (2026 Sunset)
A60: Year | B60: Joint | C60: Single
A61: =A62+1 -> 2022 | B61: =C61*2 -> 8900 | C61: ='Tax Value Calcs'!D73 -> 4450
A62: =A63+1 -> 2021 | B62: =C62*2 -> 8700 | C62: ='Tax Value Calcs'!D74 -> 4350
A63: =A64+1 -> 2020 | B63: =C63*2 -> 8600 | C63: ='Tax Value Calcs'!D75 -> 4300
A64: =A65+1 -> 2019 | B64: =C64*2 -> 8400 | C64: ='Tax Value Calcs'!D76 -> 4200
A65: =A66+1 -> 2018 | B65: =C65*2 -> 8300 | C65: ='Tax Value Calcs'!D77 -> 4150
A66: =A67+1 -> 2017 | B66: =C66*2 -> 8100 | C66: ='Tax Value Calcs'!D78 -> 4050
A67: =A68+1 -> 2016 | B67: =C67*2 -> 8100 | C67: ='Tax Value Calcs'!D79 -> 4050
A68: =A69+1 -> 2015 | B68: =C68*2 -> 8000 | C68: ='Tax Value Calcs'!D80 -> 4000
A69: =A70+1 -> 2014 | B69: =C69*2 -> 7900 | C69: ='Tax Value Calcs'!D81 -> 3950
A70: =A71+1 -> 2013 | B70: =C70*2 -> 7800 | C70: ='Tax Value Calcs'!D82 -> 3900
A71: =A72+1 -> 2012 | B71: =C71*2 -> 7600 | C71: 3800
A72: =A73+1 -> 2011 | B72: =C72*2 -> 7400 | C72: 3700
A73: =A74+1 -> 2010 | B73: 7300 | C73: 3650
A74: =A75+1 -> 2009 | B74: 7300 | C74: 3650
A75: =A76+1 -> 2008 | B75: 7000 | C75: 3500
A76: =A77+1 -> 2007 | B76: 6800 | C76: 3400
A77: =A78+1 -> 2006 | B77: 6600 | C77: 3300
A78: =A79+1 -> 2005 | B78: 6400 | C78: 3200
A79: =A80+1 -> 2004 | B79: 6200 | C79: 3100
A80: =A81+1 -> 2003 | B80: 6100 | C80: 3050
A81: =A82+1 -> 2002 | B81: 6000 | C81: 3000
A82: =A83+1 -> 2001 | B82: 5800 | C82: 2900
A83: 2000 | B83: 5600 | C83: 2800
A85: Personal Exemption Phase Out (for 2026 Sunset)
B86: Joint | C86: Single | D86: Head of Household | E86: Separate | F86: Phase Out Percent
A87: =A88+1 -> 2022 | B87: ='Tax Value Calcs'!D111 -> 344050 | C87: ='Tax Value Calcs'!F111 -> 286700 | D87: ='Tax Value Calcs'!H111 -> 315350 | E87: ='Tax Value Calcs'!J111 -> 172025 | F87: 1
A88: =A89+1 -> 2021 | B88: ='Tax Value Calcs'!D112 -> 334000 | C88: ='Tax Value Calcs'!F112 -> 278350 | D88: ='Tax Value Calcs'!H112 -> 306200 | E88: ='Tax Value Calcs'!J112 -> 167000 | F88: 1
A89: =A90+1 -> 2020 | B89: ='Tax Value Calcs'!D113 -> 330350 | C89: ='Tax Value Calcs'!F113 -> 275300 | D89: ='Tax Value Calcs'!H113 -> 302850 | E89: ='Tax Value Calcs'!J113 -> 165175 | F89: 1
A90: =A91+1 -> 2019 | B90: ='Tax Value Calcs'!D114 -> 325300 | C90: ='Tax Value Calcs'!F114 -> 271100 | D90: ='Tax Value Calcs'!H114 -> 298200 | E90: ='Tax Value Calcs'!J114 -> 162650 | F90: 1
A91: =A92+1 -> 2018 | B91: ='Tax Value Calcs'!D115 -> 318950 | C91: ='Tax Value Calcs'!F115 -> 265800 | D91: ='Tax Value Calcs'!H115 -> 292400 | E91: ='Tax Value Calcs'!J115 -> 159475 | F91: 1
A92: =A93+1 -> 2017 | B92: ='Tax Value Calcs'!D116 -> 313800 | C92: ='Tax Value Calcs'!F116 -> 261500 | D92: ='Tax Value Calcs'!H116 -> 287650 | E92: ='Tax Value Calcs'!J116 -> 156900 | F92: 1
A93: =A94+1 -> 2016 | B93: ='Tax Value Calcs'!D117 -> 311300 | C93: ='Tax Value Calcs'!F117 -> 259400 | D93: ='Tax Value Calcs'!H117 -> 285350 | E93: ='Tax Value Calcs'!J117 -> 155650 | F93: 1
A94: =A95+1 -> 2015 | B94: ='Tax Value Calcs'!D118 -> 309900 | C94: ='Tax Value Calcs'!F118 -> 258250 | D94: ='Tax Value Calcs'!H118 -> 284050 | E94: ='Tax Value Calcs'!J118 -> 154950 | F94: 1
A95: =A96+1 -> 2014 | B95: ='Tax Value Calcs'!D119 -> 305050 | C95: ='Tax Value Calcs'!F119 -> 254200 | D95: ='Tax Value Calcs'!H119 -> 279650 | E95: ='Tax Value Calcs'!J119 -> 152525 | F95: 1
A96: 2013 | B96: ='Tax Value Calcs'!D120 -> 300000 | C96: ='Tax Value Calcs'!F120 -> 250000 | D96: ='Tax Value Calcs'!H120 -> 275000 | E96: ='Tax Value Calcs'!J120 -> 150000 | F96: 1
A98: Itemized Deduction Phase Out (for 2026 Sunset)
B99: Joint | C99: Single | D99: Head of Household | E99: Separate | F99: Phase Out Percentage
A100: =A101+1 -> 2022 | B100: ='Tax Value Calcs'!D125 -> 344050 | C100: ='Tax Value Calcs'!F125 -> 286700 | D100: ='Tax Value Calcs'!H125 -> 315350 | E100: ='Tax Value Calcs'!J125 -> 172025 | F100: 1
A101: =A102+1 -> 2021 | B101: ='Tax Value Calcs'!D126 -> 334000 | C101: ='Tax Value Calcs'!F126 -> 278350 | D101: ='Tax Value Calcs'!H126 -> 306200 | E101: ='Tax Value Calcs'!J126 -> 167000 | F101: 1
A102: =A103+1 -> 2020 | B102: ='Tax Value Calcs'!D127 -> 330350 | C102: ='Tax Value Calcs'!F127 -> 275300 | D102: ='Tax Value Calcs'!H127 -> 302850 | E102: ='Tax Value Calcs'!J127 -> 165175 | F102: 1
A103: =A104+1 -> 2019 | B103: ='Tax Value Calcs'!D128 -> 325300 | C103: ='Tax Value Calcs'!F128 -> 271100 | D103: ='Tax Value Calcs'!H128 -> 298200 | E103: ='Tax Value Calcs'!J128 -> 162650 | F103: 1
A104: =A105+1 -> 2018 | B104: ='Tax Value Calcs'!D129 -> 318950 | C104: ='Tax Value Calcs'!F129 -> 265800 | D104: ='Tax Value Calcs'!H129 -> 292400 | E104: ='Tax Value Calcs'!J129 -> 159475 | F104: 1
A105: =A106+1 -> 2017 | B105: ='Tax Value Calcs'!D130 -> 313800 | C105: ='Tax Value Calcs'!F130 -> 261500 | D105: ='Tax Value Calcs'!H130 -> 287650 | E105: ='Tax Value Calcs'!J130 -> 156900 | F105: 1
...

Sheet Tax Value Calcs
A1: CPI Indexing Calculations for Income Tax Values
A2: These calculations are used to index IRS base numbers from the internal revenue code to future years.
A4: Color Coding:
A5: Green | B5: Base value that is indexed to get subsequent year values.
A6: Red | B6: Future values based upon a CPI value (3% in the examples) picked out of the air.
A9: Cumulative CPI for TCJA Sunset (for 2026 Sunset)
A10: Year | B10: Cumulative CPI
A11: =A12+1 -> 2022 | B11: ='CPI-U & C-CPI-U Calcs'!G14 -> 1.096417
A12: =A13+1 -> 2021 | B12: ='CPI-U & C-CPI-U Calcs'!G15 -> 1.0644825
A13: =A14+1 -> 2020 | B13: ='CPI-U & C-CPI-U Calcs'!G16 -> 1.0528385
A14: =A15+1 -> 2019 | B14: ='CPI-U & C-CPI-U Calcs'!G17 -> 1.0367586
A15: =A16+1 -> 2018 | B15: ='CPI-U & C-CPI-U Calcs'!G18 -> 1.016499
A16: 2017 | B16: ='CPI-U & C-CPI-U Calcs'!G19 -> 1
A19: Standard Deduction *
A20: Tax Year | B20: Prev Year Cum CPI | C20: Joint 1 | D20: Joint (rounded) | E20: Single | F20: Single (rounded) | G20: Head of Household | H20: Household (rounded) | I20: Separate | J20: Separate (rounded)
A21: =A22+1 -> 2022 | B21: ='CPI-U & C-CPI-U Calcs'!$F14 -> 1.0786208 | C21: =E21*2 -> 25886.899 | D21: =+TRUNC(C21/100)*100 -> 25800 | E21: =E$25*$B21 -> 12943.449 | F21: =+TRUNC(E21/50)*50 -> 12900 | G21: =G$25*$B21 -> 19415.174 | H21: =+TRUNC(G21/50)*50 -> 19400 | I21: =I$25*$B21 -> 12943.449 | J21: =+TRUNC(I21/50)*50 -> 12900
A22: =A23+1 -> 2021 | B22: ='CPI-U & C-CPI-U Calcs'!$F15 -> 1.0472046 | C22: =E22*2 -> 25132.911 | D22: =+TRUNC(C22/100)*100 -> 25100 | E22: =E$25*$B22 -> 12566.456 | F22: =+TRUNC(E22/50)*50 -> 12550 | G22: =G$25*$B22 -> 18849.684 | H22: =+TRUNC(G22/50)*50 -> 18800 | I22: =I$25*$B22 -> 12566.456 | J22: =+TRUNC(I22/50)*50 -> 12550
A23: =A24+1 -> 2020 | B23: ='CPI-U & C-CPI-U Calcs'!$F16 -> 1.0357497 | C23: =E23*2 -> 24857.992 | D23: =+TRUNC(C23/100)*100 -> 24800 | E23: =E$25*$B23 -> 12428.996 | F23: =+TRUNC(E23/50)*50 -> 12400 | G23: =G$25*$B23 -> 18643.494 | H23: =+TRUNC(G23/50)*50 -> 18600 | I23: =I$25*$B23 -> 12428.996 | J23: =+TRUNC(I23/50)*50 -> 12400
A24: =A25+1 -> 2019 | B24: ='CPI-U & C-CPI-U Calcs'!$F17 -> 1.0199308 | C24: =E24*2 -> 24478.339 | D24: =+TRUNC(C24/100)*100 -> 24400 | E24: =E$25*$B24 -> 12239.169 | F24: =+TRUNC(E24/50)*50 -> 12200 | G24: =G$25*$B24 -> 18358.754 | H24: =+TRUNC(G24/50)*50 -> 18350 | I24: =I$25*$B24 -> 12239.169 | J24: =+TRUNC(I24/50)*50 -> 12200
A25: 2018 | B25: ='CPI-U & C-CPI-U Calcs'!$F18 -> 1 | C25: =E25*2 -> 24000 | D25: =+TRUNC(C25/50)*50 -> 24000 | E25: 12000 | F25: =+TRUNC(E25/50)*50 -> 12000 | G25: 18000 | H25: =+TRUNC(G25/50)*50 -> 18000 | I25: 12000 | J25: =+TRUNC(I25/50)*50 -> 12000
A26: NOTE: Rounding is down to the nearest $100 for joint, $50 single or separate, and $25 for married filing separtely
A27: * Values during the TCJA period starting 2019 that are not current are likely to be wrong to due later restatement of C-CPI-U values.
A28: 1 Joint value calculated as 2X rounded value for single
A31: Standard Deduction - Additional Over Age 65 | H31: Standard Deduction - Basic (for 2026 Sunset)
A32: Tax Year | B32: Prev Year Cum CPI | C32: Joint Age 65 or Older† | D32: Joint (rounded)† | E32: Single Age 65 or Older | F32: Single (rounded) | H32: Joint† | I32: Joint (rounded) | J32: Single | K32: Single (rounded) | L32: Head of Household | M32: Household (rounded) | N32: Separate | O32: Separate (rounded)
A33: =A34+1 -> 2022 | B33: ='CPI-U & C-CPI-U Calcs'!$S14 -> 2.3365871 | C33: =C$67*$B33 -> 1401.9523 | D33: =+TRUNC(C33/50)*50 -> 1400 | E33: =E$67*$B33 -> 1752.4403 | F33: =+TRUNC(E33/50)*50 -> 1750 | H33: =J33*2 -> 14019.523 | I33: =+TRUNC(H33/100)*100 -> 14000 | J33: =J$67*$B33 -> 7009.7613 | K33: =+TRUNC(J33/50)*50 -> 7000 | L33: =L$67*$B33 -> 10280.983 | M33: =+TRUNC(L33/50)*50 -> 10250 | N33: =N$67*$B33 -> 7009.7613 | O33: =+TRUNC(N33/50)*50 -> 7000
A34: =A35+1 -> 2021 | B34: ='CPI-U & C-CPI-U Calcs'!$S15 -> 2.2685312 | C34: =C$67*$B34 -> 1361.1187 | D34: =+TRUNC(C34/50)*50 -> 1350 | E34: =E$67*$B34 -> 1701.3984 | F34: =+TRUNC(E34/50)*50 -> 1700 | H34: =J34*2 -> 13611.187 | I34: =+TRUNC(H34/100)*100 -> 13600 | J34: =J$67*$B34 -> 6805.5935 | K34: =+TRUNC(J34/50)*50 -> 6800 | L34: =L$67*$B34 -> 9981.5371 | M34: =+TRUNC(L34/50)*50 -> 9950 | N34: =N$67*$B34 -> 6805.5935 | O34: =+TRUNC(N34/50)*50 -> 6800
A35: =A36+1 -> 2020 | B35: ='CPI-U & C-CPI-U Calcs'!$S16 -> 2.2437165 | C35: =C$67*$B35 -> 1346.2299 | D35: =+TRUNC(C35/50)*50 -> 1300 | E35: =E$67*$B35 -> 1682.7874 | F35: =+TRUNC(E35/50)*50 -> 1650 | H35: =J35*2 -> 13462.299 | I35: =+TRUNC(H35/100)*100 -> 13400 | J35: =J$67*$B35 -> 6731.1496 | K35: =+TRUNC(J35/50)*50 -> 6700 | L35: =L$67*$B35 -> 9872.3527 | M35: =+TRUNC(L35/50)*50 -> 9850 | N35: =N$67*$B35 -> 6731.1496 | O35: =+TRUNC(N35/50)*50 -> 6700
A36: =A37+1 -> 2019 | B36: ='CPI-U & C-CPI-U Calcs'!$S17 -> 2.2094485 | C36: =C$67*$B36 -> 1325.6691 | D36: =+TRUNC(C36/50)*50 -> 1300 | E36: =E$67*$B36 -> 1657.0864 | F36: =+TRUNC(E36/50)*50 -> 1650 | H36: =J36*2 -> 13256.691 | I36: =+TRUNC(H36/100)*100 -> 13200 | J36: =J$67*$B36 -> 6628.3456 | K36: =+TRUNC(J36/50)*50 -> 6600 | L36: =L$67*$B36 -> 9721.5735 | M36: =+TRUNC(L36/50)*50 -> 9700 | N36: =N$67*$B36 -> 6628.3456 | O36: =+TRUNC(N36/50)*50 -> 6600
A37: 2018 | B37: ='CPI-U & C-CPI-U Calcs'!$S18 -> 2.166273 | C37: =C$67*$B37 -> 1299.7638 | D37: =+TRUNC(C37/50)*50 -> 1250 | E37: =E$67*$B37 -> 1624.7048 | F37: =+TRUNC(E37/50)*50 -> 1600 | H37: =J37*2 -> 12997.638 | I37: =+TRUNC(H37/100)*100 -> 12900 | J37: =J$67*$B37 -> 6498.819 | K37: =+TRUNC(J37/50)*50 -> 6450 | L37: =L$67*$B37 -> 9531.6012 | M37: =+TRUNC(L37/50)*50 -> 9500 | N37: =N$67*$B37 -> 6498.819 | O37: =+TRUNC(N37/50)*50 -> 6450
A38: =A39+1 -> 2017 | B38: ='CPI-U & C-CPI-U Calcs'!$S19 -> 2.1311118 | C38: =C$67*$B38 -> 1278.6671 | D38: =+TRUNC(C38/50)*50 -> 1250 | E38: =E$67*$B38 -> 1598.3338 | F38: =+TRUNC(E38/50)*50 -> 1550 | H38: =J38*2 -> 12786.671 | I38: =+TRUNC(H38/100)*100 -> 12700 | J38: =J$67*$B38 -> 6393.3353 | K38: =+TRUNC(J38/50)*50 -> 6350 | L38: =L$67*$B38 -> 9376.8918 | M38: =+TRUNC(L38/50)*50 -> 9350 | N38: =N$67*$B38 -> 6393.3353 | O38: =+TRUNC(N38/50)*50 -> 6350
A39: =A40+1 -> 2016 | B39: ='CPI-U & C-CPI-U Calcs'!$S20 -> 2.1141442 | C39: =C$67*$B39 -> 1268.4865 | D39: =+TRUNC(C39/50)*50 -> 1250 | E39: =E$67*$B39 -> 1585.6082 | F39: =+TRUNC(E39/50)*50 -> 1550 | H39: =J39*2 -> 12684.865 | I39: =+TRUNC(H39/100)*100 -> 12600 | J39: =J$67*$B39 -> 6342.4327 | K39: =+TRUNC(J39/50)*50 -> 6300 | L39: =L$67*$B39 -> 9302.2346 | M39: =+TRUNC(L39/50)*50 -> 9300 | N39: =N$67*$B39 -> 6342.4327 | O39: =+TRUNC(N39/50)*50 -> 6300
A40: =A41+1 -> 2015 | B40: ='CPI-U & C-CPI-U Calcs'!$S21 -> 2.1046435 | C40: =C$67*$B40 -> 1262.7861 | D40: =+TRUNC(C40/50)*50 -> 1250 | E40: =E$67*$B40 -> 1578.4827 | F40: =+TRUNC(E40/50)*50 -> 1550 | H40: =J40*2 -> 12627.861 | I40: =+TRUNC(H40/100)*100 -> 12600 | J40: =J$67*$B40 -> 6313.9306 | K40: =+TRUNC(J40/50)*50 -> 6300 | L40: =L$67*$B40 -> 9260.4316 | M40: =+TRUNC(L40/50)*50 -> 9250 | N40: =N$67*$B40 -> 6313.9306 | O40: =+TRUNC(N40/50)*50 -> 6300
A41: =A42+1 -> 2014 | B41: ='CPI-U & C-CPI-U Calcs'!$S22 -> 2.0718991 | C41: =C$67*$B41 -> 1243.1395 | D41: =+TRUNC(C41/50)*50 -> 1200 | E41: =E$67*$B41 -> 1553.9243 | F41: =+TRUNC(E41/50)*50 -> 1550 | H41: =J41*2 -> 12431.395 | I41: =+TRUNC(H41/100)*100 -> 12400 | J41: =J$67*$B41 -> 6215.6973 | K41: =+TRUNC(J41/50)*50 -> 6200 | L41: =L$67*$B41 -> 9116.356 | M41: =+TRUNC(L41/50)*50 -> 9100 | N41: =N$67*$B41 -> 6215.6973 | O41: =+TRUNC(N41/50)*50 -> 6200
A42: =A43+1 -> 2013 | B42: ='CPI-U & C-CPI-U Calcs'!$S23 -> 2.0373515 | C42: =C$67*$B42 -> 1222.4109 | D42: =+TRUNC(C42/50)*50 -> 1200 | E42: =E$67*$B42 -> 1528.0137 | F42: =+TRUNC(E42/50)*50 -> 1500 | H42: =J42*2 -> 12224.109 | I42: =+TRUNC(H42/100)*100 -> 12200 | J42: =J$67*$B42 -> 6112.0546 | K42: =+TRUNC(J42/50)*50 -> 6100 | L42: =L$67*$B42 -> 8964.3468 | M42: =+TRUNC(L42/50)*50 -> 8950 | N42: =N$67*$B42 -> 6112.0546 | O42: =+TRUNC(N42/50)*50 -> 6100
A43: =A44+1 -> 2012 | B43: ='CPI-U & C-CPI-U Calcs'!$S24 -> 1.9863 | C43: =C$67*$B43 -> 1191.78 | D43: =+TRUNC(C43/50)*50 -> 1150 | E43: =E$67*$B43 -> 1489.725 | F43: =+TRUNC(E43/50)*50 -> 1450 | H43: =J43*2 -> 11917.8 | I43: =+TRUNC(H43/100)*100 -> 11900 | J43: =J$67*$B43 -> 5958.9001 | K43: =+TRUNC(J43/50)*50 -> 5950 | L43: =L$67*$B43 -> 8739.7202 | M43: =+TRUNC(L43/50)*50 -> 8700 | N43: =N$67*$B43 -> 5958.9001 | O43: =+TRUNC(N43/50)*50 -> 5950
A44: =A45+1 -> 2011 | B44: ='CPI-U & C-CPI-U Calcs'!$S25 -> 1.9392462 | C44: =C$67*$B44 -> 1163.5477 | D44: =+TRUNC(C44/50)*50 -> 1150 | E44: =E$67*$B44 -> 1454.4346 | F44: =+TRUNC(E44/50)*50 -> 1450 | H44: =J44*2 -> 11635.477 | I44: =+TRUNC(H44/100)*100 -> 11600 | J44: =J$67*$B44 -> 5817.7385 | K44: =+TRUNC(J44/50)*50 -> 5800 | L44: =L$67*$B44 -> 8532.6831 | M44: =+TRUNC(L44/50)*50 -> 8500 | N44: =N$67*$B44 -> 5817.7385 | O44: =+TRUNC(N44/50)*50 -> 5800
A45: =A46+1 -> 2010 | B45: ='CPI-U & C-CPI-U Calcs'!$S26 -> 1.9110195 | C45: =C$67*$B45 -> 1146.6117 | D45: =+TRUNC(C45/50)*50 -> 1100 | E45: =E$67*$B45 -> 1433.2646 | F45: =+TRUNC(E45/50)*50 -> 1400 | H45: =J45*2 -> 11466.117 | I45: =+TRUNC(H45/100)*100 -> 11400 | J45: =J$67*$B45 -> 5733.0585 | K45: =+TRUNC(J45/50)*50 -> 5700 | L45: =L$67*$B45 -> 8408.4858 | M45: =+TRUNC(L45/50)*50 -> 8400 | N45: =N$67*$B45 -> 5733.0585 | O45: =+TRUNC(N45/50)*50 -> 5700
A46: =A47+1 -> 2009 | B46: ='CPI-U & C-CPI-U Calcs'!$S27 -> 1.9074713 | C46: =C$67*$B46 -> 1144.4828 | D46: =+TRUNC(C46/50)*50 -> 1100 | E46: =E$67*$B46 -> 1430.6035 | F46: =+TRUNC(E46/50)*50 -> 1400 | H46: =J46*2 -> 11444.828 | I46: =+TRUNC(H46/100)*100 -> 11400 | J46: =J$67*$B46 -> 5722.414 | K46: =+TRUNC(J46/50)*50 -> 5700 | L46: =L$67*$B46 -> 8392.8739 | M46: =+TRUNC(L46/50)*50 -> 8350 | N46: =N$67*$B46 -> 5722.414 | O46: =+TRUNC(N46/50)*50 -> 5700
A47: =A48+1 -> 2008 | B47: ='CPI-U & C-CPI-U Calcs'!$S28 -> 1.829491 | C47: =C$67*$B47 -> 1097.6946 | D47: =+TRUNC(C47/50)*50 -> 1050 | E47: =E$67*$B47 -> 1372.1182 | F47: =+TRUNC(E47/50)*50 -> 1350 | H47: =J47*2 -> 10976.946 | I47: =+TRUNC(H47/100)*100 -> 10900 | J47: =J$67*$B47 -> 5488.473 | K47: =+TRUNC(J47/50)*50 -> 5450 | L47: =L$67*$B47 -> 8049.7604 | M47: =+TRUNC(L47/50)*50 -> 8000 | N47: =N$67*$B47 -> 5488.473 | O47: =+TRUNC(N47/50)*50 -> 5450
A48: =A49+1 -> 2007 | B48: ='CPI-U & C-CPI-U Calcs'!$S29 -> 1.7885846 | C48: =C$67*$B48 -> 1073.1508 | D48: =+TRUNC(C48/50)*50 -> 1050 | E48: =E$67*$B48 -> 1341.4385 | F48: =+TRUNC(E48/50)*50 -> 1300 | H48: =J48*2 -> 10731.508 | I48: =+TRUNC(H48/100)*100 -> 10700 | J48: =J$67*$B48 -> 5365.7538 | K48: =+TRUNC(J48/50)*50 -> 5350 | L48: =L$67*$B48 -> 7869.7723 | M48: =+TRUNC(L48/50)*50 -> 7850 | N48: =N$67*$B48 -> 5365.7538 | O48: =+TRUNC(N48/50)*50 -> 5350
A49: =A50+1 -> 2006 | B49: ='CPI-U & C-CPI-U Calcs'!$S30 -> 1.7213871 | C49: =C$67*$B49 -> 1032.8323 | D49: =+TRUNC(C49/50)*50 -> 1000 | E49: =E$67*$B49 -> 1291.0403 | F49: =+TRUNC(E49/50)*50 -> 1250 | H49: =J49*2 -> 10328.323 | I49: =+TRUNC(H49/100)*100 -> 10300 | J49: =J$67*$B49 -> 5164.1613 | K49: =+TRUNC(J49/50)*50 -> 5150 | L49: =L$67*$B49 -> 7574.1033 | M49: =+TRUNC(L49/50)*50 -> 7550 | N49: =N$67*$B49 -> 5164.1613 | O49: =+TRUNC(N49/50)*50 -> 5150
... A52: =A53+1 -> 2003 | B52: ='CPI-U & C-CPI-U Calcs'!$S33 -> 1.5955499 | C52: =C$67*$B52 -> 957.32996 | D52: =+TRUNC(C52/50)*50 -> 950 | E52: =E$67*$B52 -> 1196.6624 | F52: =+TRUNC(E52/50)*50 -> 1150 | H52: =J52*2 -> 9573.2996 | I52: =+TRUNC(H52/100)*100 -> 9500 | J52: =J$67*$B52 -> 4786.6498 | K52: =+TRUNC(J52/50)*50 -> 4750 | L52: =L$67*$B52 -> 7020.4197 | M52: =+TRUNC(L52/50)*50 -> 7000 | N52: =N$67*$B52 -> 4786.6498 | O52: =+TRUNC(N52/50)*50 -> 4750
A53: =A54+1 -> 2002 | B53: ='CPI-U & C-CPI-U Calcs'!$S34 -> 1.5705462 | C53: =C$67*$B53 -> 942.32773 | D53: =+TRUNC(C53/50)*50 -> 900 | E53: =E$67*$B53 -> 1177.9097 | F53: =+TRUNC(E53/50)*50 -> 1150 | H53: =J53*1.666666667 -> 7852.7311 | I53: =+TRUNC(H53/50)*50 -> 7850 | J53: =J$67*$B53 -> 4711.6386 | K53: =+TRUNC(J53/50)*50 -> 4700 | L53: =L$67*$B53 -> 6910.4033 | M53: =+TRUNC(L53/50)*50 -> 6900 | N53: =N$67*$B53 -> 4711.6386 | O53: =+TRUNC(N53/50)*50 -> 4700
A54: =A55+1 -> 2001 | B54: ='CPI-U & C-CPI-U Calcs'!$S35 -> 1.5205388 | C54: =C$67*$B54 -> 912.32326 | D54: =+TRUNC(C54/50)*50 -> 900 | E54: =E$67*$B54 -> 1140.4041 | F54: =+TRUNC(E54/50)*50 -> 1100 | H54: =J54*1.666666667 -> 7602.6939 | I54: =+TRUNC(H54/50)*50 -> 7600 | J54: =J$67*$B54 -> 4561.6163 | K54: =+TRUNC(J54/50)*50 -> 4550 | L54: =L$67*$B54 -> 6690.3706 | M54: =+TRUNC(L54/50)*50 -> 6650 | N54: =N$67*$B54 -> 4561.6163 | O54: =+TRUNC(N54/50)*50 -> 4550
A55: =A56+1 -> 2000 | B55: ='CPI-U & C-CPI-U Calcs'!$S36 -> 1.4746986 | C55: =C$67*$B55 -> 884.81917 | D55: =+TRUNC(C55/50)*50 -> 850 | E55: =E$67*$B55 -> 1106.024 | F55: =+TRUNC(E55/50)*50 -> 1100 | H55: =J55*1.666666667 -> 7373.4931 | I55: =+TRUNC(H55/50)*50 -> 7350 | J55: =J$67*$B55 -> 4424.0958 | K55: =+TRUNC(J55/50)*50 -> 4400 | L55: =L$67*$B55 -> 6488.6739 | M55: =+TRUNC(L55/50)*50 -> 6450 | N55: =N$67*$B55 -> 4424.0958 | O55: =+TRUNC(N55/50)*50 -> 4400
A56: =A57+1 -> 1999 | B56: ='CPI-U & C-CPI-U Calcs'!$S37 -> 1.448281 | C56: =C$67*$B56 -> 868.9686 | D56: =+TRUNC(C56/50)*50 -> 850 | E56: =E$67*$B56 -> 1086.2107 | F56: =+TRUNC(E56/50)*50 -> 1050 | H56: =J56*1.666666667 -> 7241.405 | I56: =+TRUNC(H56/50)*50 -> 7200 | J56: =J$67*$B56 -> 4344.843 | K56: =+TRUNC(J56/50)*50 -> 4300 | L56: =L$67*$B56 -> 6372.4364 | M56: =+TRUNC(L56/50)*50 -> 6350 | N56: =N$67*$B56 -> 4344.843 | O56: =+TRUNC(N56/50)*50 -> 4300
A57: =A58+1 -> 1998 | B57: ='CPI-U & C-CPI-U Calcs'!$S38 -> 1.4242447 | C57: =C$67*$B57 -> 854.54681 | D57: =+TRUNC(C57/50)*50 -> 850 | E57: =E$67*$B57 -> 1068.1835 | F57: =+TRUNC(E57/50)*50 -> 1050 | H57: =J57*1.666666667 -> 7121.2234 | I57: =+TRUNC(H57/50)*50 -> 7100 | J57: =J$67*$B57 -> 4272.734 | K57: =+TRUNC(J57/50)*50 -> 4250 | L57: =L$67*$B57 -> 6266.6766 | M57: =+TRUNC(L57/50)*50 -> 6250 | N57: =N$67*$B57 -> 4272.734 | O57: =+TRUNC(N57/50)*50 -> 4250
A58: =A59+1 -> 1997 | B58: ='CPI-U & C-CPI-U Calcs'!$S39 -> 1.3862926 | C58: =C$67*$B58 -> 831.77556 | D58: =+TRUNC(C58/50)*50 -> 800 | E58: =E$67*$B58 -> 1039.7195 | F58: =+TRUNC(E58/50)*50 -> 1000 | H58: =J58*1.666666667 -> 6931.463 | I58: =+TRUNC(H58/50)*50 -> 6900 | J58: =J$67*$B58 -> 4158.8778 | K58: =+TRUNC(J58/50)*50 -> 4150 | L58: =L$67*$B58 -> 6099.6875 | M58: =+TRUNC(L58/50)*50 -> 6050 | N58: =N$67*$B58 -> 4158.8778 | O58: =+TRUNC(N58/50)*50 -> 4150
A59: =A60+1 -> 1996 | B59: ='CPI-U & C-CPI-U Calcs'!$S40 -> 1.3490847 | C59: =C$67*$B59 -> 809.45081 | D59: =+TRUNC(C59/50)*50 -> 800 | E59: =E$67*$B59 -> 1011.8135 | F59: =+TRUNC(E59/50)*50 -> 1000 | H59: =J59*2 -> 8094.5081 | I59: =+TRUNC(H59/50)*50 -> 8050 | J59: =J$67*$B59 -> 4047.2541 | K59: =+TRUNC(J59/50)*50 -> 4000 | L59: =L$67*$B59 -> 5935.9726 | M59: =+TRUNC(L59/50)*50 -> 5900 | N59: =N$67*$B59 -> 4047.2541 | O59: =+TRUNC(N59/50)*50 -> 4000
A60: =A61+1 -> 1995 | B60: ='CPI-U & C-CPI-U Calcs'!$S41 -> 1.3118024 | C60: =C$67*$B60 -> 787.08141 | D60: =+TRUNC(C60/50)*50 -> 750 | E60: =E$67*$B60 -> 983.85176 | F60: =+TRUNC(E60/50)*50 -> 950 | H60: =J60*2 -> 7870.8141 | I60: =+TRUNC(H60/50)*50 -> 7850 | J60: =J$67*$B60 -> 3935.4071 | K60: =+TRUNC(J60/50)*50 -> 3900 | L60: =L$67*$B60 -> 5771.9303 | M60: =+TRUNC(L60/50)*50 -> 5750 | N60: =N$67*$B60 -> 3935.4071 | O60: =+TRUNC(N60/50)*50 -> 3900
A61: =A62+1 -> 1994 | B61: ='CPI-U & C-CPI-U Calcs'!$S42 -> 1.2785385 | C61: =C$67*$B61 -> 767.12308 | D61: =+TRUNC(C61/50)*50 -> 750 | E61: =E$67*$B61 -> 958.90385 | F61: =+TRUNC(E61/50)*50 -> 950 | H61: =J61*2 -> 7671.2308 | I61: =+TRUNC(H61/50)*50 -> 7650 | J61: =J$67*$B61 -> 3835.6154 | K61: =+TRUNC(J61/50)*50 -> 3800 | L61: =L$67*$B61 -> 5625.5693 | M61: =+TRUNC(L61/50)*50 -> 5600 | N61: =N$67*$B61 -> 3835.6154 | O61: =+TRUNC(N61/50)*50 -> 3800
A62: =A63+1 -> 1993 | B62: ='CPI-U & C-CPI-U Calcs'!$S43 -> 1.2405864 | C62: =C$67*$B62 -> 744.35184 | D62: =+TRUNC(C62/50)*50 -> 700 | E62: =E$67*$B62 -> 930.4398 | F62: =+TRUNC(E62/50)*50 -> 900 | H62: =J62*2 -> 7443.5184 | I62: =+TRUNC(H62/50)*50 -> 7400 | J62: =J$67*$B62 -> 3721.7592 | K62: =+TRUNC(J62/50)*50 -> 3700 | L62: =L$67*$B62 -> 5458.5801 | M62: =+TRUNC(L62/50)*50 -> 5450 | N62: =N$67*$B62 -> 3721.7592 | O62: =+TRUNC(N62/50)*50 -> 3700
A63: =A64+1 -> 1992 | B63: ='CPI-U & C-CPI-U Calcs'!$S44 -> 1.2038994 | C63: =C$67*$B63 -> 722.33963 | D63: =+TRUNC(C63/50)*50 -> 700 | E63: =E$67*$B63 -> 902.92454 | F63: =+TRUNC(E63/50)*50 -> 900 | H63: =J63*2 -> 7223.3963 | I63: =+TRUNC(H63/50)*50 -> 7200 | J63: =J$67*$B63 -> 3611.6982 | K63: =+TRUNC(J63/50)*50 -> 3600 | L63: =L$67*$B63 -> 5297.1573 | M63: =+TRUNC(L63/50)*50 -> 5250 | N63: =N$67*$B63 -> 3611.6982 | O63: =+TRUNC(N63/50)*50 -> 3600
A64: =A65+1 -> 1991 | B64: ='CPI-U & C-CPI-U Calcs'!$S45 -> 1.1435481 | C64: =C$67*$B64 -> 686.12889 | D64: =+TRUNC(C64/50)*50 -> 650 | E64: =E$67*$B64 -> 857.66111 | F64: =+TRUNC(E64/50)*50 -> 850 | H64: =J64*2 -> 6861.2889 | I64: =+TRUNC(H64/50)*50 -> 6850 | J64: =J$67*$B64 -> 3430.6444 | K64: =+TRUNC(J64/50)*50 -> 3400 | L64: =L$67*$B64 -> 5031.6118 | M64: =+TRUNC(L64/50)*50 -> 5000 | N64: =N$67*$B64 -> 3430.6444 | O64: =+TRUNC(N64/50)*50 -> 3400
A65: =A66+1 -> 1990 | B65: ='CPI-U & C-CPI-U Calcs'!$S46 -> 1.0907873 | C65: =C$67*$B65 -> 654.47239 | D65: =+TRUNC(C65/50)*50 -> 650 | E65: =E$67*$B65 -> 818.09049 | F65: =+TRUNC(E65/50)*50 -> 800 | H65: =J65*2 -> 6544.7239 | I65: =+TRUNC(H65/50)*50 -> 6500 | J65: =J$67*$B65 -> 3272.362 | K65: =+TRUNC(J65/50)*50 -> 3250 | L65: =L$67*$B65 -> 4799.4642 | M65: =+TRUNC(L65/50)*50 -> 4750 | N65: =N$67*$B65 -> 3272.362 | O65: =+TRUNC(N65/50)*50 -> 3250
A66: =A67+1 -> 1989 | B66: ='CPI-U & C-CPI-U Calcs'!$S47 -> 1.0413752 | C66: =C$67*$B66 -> 624.82512 | D66: =+TRUNC(C66/50)*50 -> 600 | E66: =E$67*$B66 -> 781.0314 | F66: =+TRUNC(E66/50)*50 -> 750 | H66: =H$67*$B66 -> 6248.2512 | I66: =+TRUNC(H66/50)*50 -> 6200 | J66: =J$67*$B66 -> 3124.1256 | K66: =+TRUNC(J66/50)*50 -> 3100 | L66: =L$67*$B66 -> 4582.0509 | M66: =+TRUNC(L66/50)*50 -> 4550 | N66: =N$67*$B66 -> 3124.1256 | O66: =+TRUNC(N66/50)*50 -> 3100
A67: 1988 | B67: ='CPI-U & C-CPI-U Calcs'!$S48 -> 1 | C67: 600 | D67: 600 | E67: 750 | F67: 750 | H67: 6000 | I67: =+TRUNC(H67/50)*50 -> 6000 | J67: 3000 | K67: =+TRUNC(J67/50)*50 -> 3000 | L67: 4400 | M67: =+TRUNC(L67/50)*50 -> 4400 | N67: 3000 | O67: =+TRUNC(N67/25)*25 -> 3000
C68: † Joint amount is per filer over age 65. | H68: † Joint amount is 2.0X single. From 1989-2002 joint was 1.66667X single.
A71: Personal Exemption (for 2026 Sunset)
A72: Tax Year | B72: Prev Year Cum CPI | C72: Exemption | D72: Exemption (rounded)
A73: =A74+1 -> 2022 | B73: ='CPI-U & C-CPI-U Calcs'!$R14 -> 2.2437514 | C73: =C$106*$B73 -> 4487.5028 | D73: =+TRUNC(C73/50)*50 -> 4450
A74: =A75+1 -> 2021 | B74: ='CPI-U & C-CPI-U Calcs'!$R15 -> 2.1783994 | C74: =C$106*$B74 -> 4356.7989 | D74: =+TRUNC(C74/50)*50 -> 4350
A75: =A76+1 -> 2020 | B75: ='CPI-U & C-CPI-U Calcs'!$R16 -> 2.1545707 | C75: =C$106*$B75 -> 4309.1415 | D75: =+TRUNC(C75/50)*50 -> 4300
A76: =A77+1 -> 2019 | B76: ='CPI-U & C-CPI-U Calcs'!$R17 -> 2.1216642 | C76: =C$106*$B76 -> 4243.3285 | D76: =+TRUNC(C76/50)*50 -> 4200
A77: =A78+1 -> 2018 | B77: ='CPI-U & C-CPI-U Calcs'!$R18 -> 2.0802041 | C77: =C$106*$B77 -> 4160.4083 | D77: =+TRUNC(C77/50)*50 -> 4150
A78: =A79+1 -> 2017 | B78: ='CPI-U & C-CPI-U Calcs'!$R19 -> 2.0464399 | C78: =C$106*$B78 -> 4092.8798 | D78: =+TRUNC(C78/50)*50 -> 4050
A79: =A80+1 -> 2016 | B79: ='CPI-U & C-CPI-U Calcs'!$R20 -> 2.0301465 | C79: =C$106*$B79 -> 4060.293 | D79: =+TRUNC(C79/50)*50 -> 4050
A80: =A81+1 -> 2015 | B80: ='CPI-U & C-CPI-U Calcs'!$R21 -> 2.0210233 | C80: =C$106*$B80 -> 4042.0466 | D80: =+TRUNC(C80/50)*50 -> 4000
A81: =A82+1 -> 2014 | B81: ='CPI-U & C-CPI-U Calcs'!$R22 -> 1.9895798 | C81: =C$106*$B81 -> 3979.1596 | D81: =+TRUNC(C81/50)*50 -> 3950
A82: =A83+1 -> 2013 | B82: ='CPI-U & C-CPI-U Calcs'!$R23 -> 1.9564049 | C82: =C$106*$B82 -> 3912.8098 | D82: =+TRUNC(C82/50)*50 -> 3900
A83: =A84+1 -> 2012 | B83: ='CPI-U & C-CPI-U Calcs'!$R24 -> 1.9073817 | C83: =C$106*$B83 -> 3814.7635 | D83: =+TRUNC(C83/50)*50 -> 3800
A84: =A85+1 -> 2011 | B84: ='CPI-U & C-CPI-U Calcs'!$R25 -> 1.8621974 | C84: =C$106*$B84 -> 3724.3947 | D84: =+TRUNC(C84/50)*50 -> 3700
... A105: =A106+1 -> 1990 | B105: ='CPI-U & C-CPI-U Calcs'!$R46 -> 1.0474489 | C105: =C$106*$B105 -> 2094.8978 | D105: =+TRUNC(C105/50)*50 -> 2050
A106: 1989 | B106: ='CPI-U & C-CPI-U Calcs'!$R47 -> 1 | C106: 2000 | D106: =+TRUNC(C106/50)*50 -> 2000
A109: Personal Exemption Phase Out (for 2026 Sunset)
A110: Tax Year | B110: Prev Year Cum CPI | C110: Joint | D110: Joint (rounded) | E110: Single | F110: Single (rounded) | G110: Head of Household | H110: Household (rounded) | I110: Separate | J110: Separate (rounded)
A111: =A112+1 -> 2022 | B111: ='CPI-U & C-CPI-U Calcs'!$H14 -> 1.1468748 | C111: =C$120*$B111 -> 344062.43 | D111: =+TRUNC(C111/50)*50 -> 344050 | E111: =E$120*$B111 -> 286718.69 | F111: =+TRUNC(E111/50)*50 -> 286700 | G111: =G$120*$B111 -> 315390.56 | H111: =+TRUNC(G111/50)*50 -> 315350 | I111: =I$120*$B111 -> 172031.22 | J111: =+TRUNC(I111/25)*25 -> 172025
A112: =A113+1 -> 2021 | B112: ='CPI-U & C-CPI-U Calcs'!$H15 -> 1.1134707 | C112: =C$120*$B112 -> 334041.2 | D112: =+TRUNC(C112/50)*50 -> 334000 | E112: =E$120*$B112 -> 278367.66 | F112: =+TRUNC(E112/50)*50 -> 278350 | G112: =G$120*$B112 -> 306204.43 | H112: =+TRUNC(G112/50)*50 -> 306200 | I112: =I$120*$B112 -> 167020.6 | J112: =+TRUNC(I112/25)*25 -> 167000
A113: =A114+1 -> 2020 | B113: ='CPI-U & C-CPI-U Calcs'!$H16 -> 1.1012908 | C113: =C$120*$B113 -> 330387.24 | D113: =+TRUNC(C113/50)*50 -> 330350 | E113: =E$120*$B113 -> 275322.7 | F113: =+TRUNC(E113/50)*50 -> 275300 | G113: =G$120*$B113 -> 302854.97 | H113: =+TRUNC(G113/50)*50 -> 302850 | I113: =I$120*$B113 -> 165193.62 | J113: =+TRUNC(I113/25)*25 -> 165175
A114: =A115+1 -> 2019 | B114: ='CPI-U & C-CPI-U Calcs'!$H17 -> 1.0844709 | C114: =C$120*$B114 -> 325341.28 | D114: =+TRUNC(C114/50)*50 -> 325300 | E114: =E$120*$B114 -> 271117.73 | F114: =+TRUNC(E114/50)*50 -> 271100 | G114: =G$120*$B114 -> 298229.51 | H114: =+TRUNC(G114/50)*50 -> 298200 | I114: =I$120*$B114 -> 162670.64 | J114: =+TRUNC(I114/25)*25 -> 162650
A115: =A116+1 -> 2018 | B115: ='CPI-U & C-CPI-U Calcs'!$H18 -> 1.063279 | C115: =C$120*$B115 -> 318983.69 | D115: =+TRUNC(C115/50)*50 -> 318950 | E115: =E$120*$B115 -> 265819.74 | F115: =+TRUNC(E115/50)*50 -> 265800 | G115: =G$120*$B115 -> 292401.71 | H115: =+TRUNC(G115/50)*50 -> 292400 | I115: =I$120*$B115 -> 159491.84 | J115: =+TRUNC(I115/25)*25 -> 159475
A116: =A117+1 -> 2017 | B116: ='CPI-U & C-CPI-U Calcs'!$H19 -> 1.0460206 | C116: =C$120*$B116 -> 313806.19 | D116: =+TRUNC(C116/50)*50 -> 313800 | E116: =E$120*$B116 -> 261505.16 | F116: =+TRUNC(E116/50)*50 -> 261500 | G116: =G$120*$B116 -> 287655.68 | H116: =+TRUNC(G116/50)*50 -> 287650 | I116: =I$120*$B116 -> 156903.1 | J116: =+TRUNC(I116/25)*25 -> 156900
A117: =A118+1 -> 2016 | B117: ='CPI-U & C-CPI-U Calcs'!$H20 -> 1.0376924 | C117: =C$120*$B117 -> 311307.72 | D117: =+TRUNC(C117/50)*50 -> 311300 | E117: =E$120*$B117 -> 259423.1 | F117: =+TRUNC(E117/50)*50 -> 259400 | G117: =G$120*$B117 -> 285365.41 | H117: =+TRUNC(G117/50)*50 -> 285350 | I117: =I$120*$B117 -> 155653.86 | J117: =+TRUNC(I117/25)*25 -> 155650
A118: =A119+1 -> 2015 | B118: ='CPI-U & C-CPI-U Calcs'!$H21 -> 1.0330292 | C118: =C$120*$B118 -> 309908.75 | D118: =+TRUNC(C118/50)*50 -> 309900 | E118: =E$120*$B118 -> 258257.29 | F118: =+TRUNC(E118/50)*50 -> 258250 | G118: =G$120*$B118 -> 284083.02 | H118: =+TRUNC(G118/50)*50 -> 284050 | I118: =I$120*$B118 -> 154954.37 | J118: =+TRUNC(I118/25)*25 -> 154950
A119: =A120+1 -> 2014 | B119: ='CPI-U & C-CPI-U Calcs'!$H22 -> 1.0169571 | C119: =C$120*$B119 -> 305087.13 | D119: =+TRUNC(C119/50)*50 -> 305050 | E119: =E$120*$B119 -> 254239.27 | F119: =+TRUNC(E119/50)*50 -> 254200 | G119: =G$120*$B119 -> 279663.2 | H119: =+TRUNC(G119/50)*50 -> 279650 | I119: =I$120*$B119 -> 152543.56 | J119: =+TRUNC(I119/25)*25 -> 152525
A120: 2013 | B120: ='CPI-U & C-CPI-U Calcs'!$H23 -> 1 | C120: 300000 | D120: =+TRUNC(C120/50)*50 -> 300000 | E120: 250000 | F120: =+TRUNC(E120/50)*50 -> 250000 | G120: 275000 | H120: =+TRUNC(G120/50)*50 -> 275000 | I120: 150000 | J120: =+TRUNC(I120/50)*50 -> 150000
A123: Itemized Deduction Phase Out (for 2026 Sunset)
A124: Tax Year | B124: Prev Year Cum CPI | C124: Joint | D124: Joint (rounded) | E124: Single | F124: Single (rounded) | G124: Head of Household | H124: Household (rounded) | I124: Separate | J124: Separate (rounded)
A125: =A126+1 -> 2022 | B125: ='CPI-U & C-CPI-U Calcs'!$H14 -> 1.1468748 | C125: =C$120*$B125 -> 344062.43 | D125: =+TRUNC(C125/50)*50 -> 344050 | E125: =E$120*$B125 -> 286718.69 | F125: =+TRUNC(E125/50)*50 -> 286700 | G125: =G$120*$B125 -> 315390.56 | H125: =+TRUNC(G125/50)*50 -> 315350 | I125: =I$120*$B125 -> 172031.22 | J125: =+TRUNC(I125/25)*25 -> 172025
A126: =A127+1 -> 2021 | B126: ='CPI-U & C-CPI-U Calcs'!$H15 -> 1.1134707 | C126: =C$120*$B126 -> 334041.2 | D126: =+TRUNC(C126/50)*50 -> 334000 | E126: =E$120*$B126 -> 278367.66 | F126: =+TRUNC(E126/50)*50 -> 278350 | G126: =G$120*$B126 -> 306204.43 | H126: =+TRUNC(G126/50)*50 -> 306200 | I126: =I$120*$B126 -> 167020.6 | J126: =+TRUNC(I126/25)*25 -> 167000
A127: =A128+1 -> 2020 | B127: ='CPI-U & C-CPI-U Calcs'!$H16 -> 1.1012908 | C127: =C$120*$B127 -> 330387.24 | D127: =+TRUNC(C127/50)*50 -> 330350 | E127: =E$120*$B127 -> 275322.7 | F127: =+TRUNC(E127/50)*50 -> 275300 | G127: =G$120*$B127 -> 302854.97 | H127: =+TRUNC(G127/50)*50 -> 302850 | I127: =I$120*$B127 -> 165193.62 | J127: =+TRUNC(I127/25)*25 -> 165175
A128: =A129+1 -> 2019 | B128: ='CPI-U & C-CPI-U Calcs'!$H17 -> 1.0844709 | C128: =C$120*$B128 -> 325341.28 | D128: =+TRUNC(C128/50)*50 -> 325300 | E128: =E$120*$B128 -> 271117.73 | F128: =+TRUNC(E128/50)*50 -> 271100 | G128: =G$120*$B128 -> 298229.51 | H128: =+TRUNC(G128/50)*50 -> 298200 | I128: =I$120*$B128 -> 162670.64 | J128: =+TRUNC(I128/25)*25 -> 162650
A129: =A130+1 -> 2018 | B129: ='CPI-U & C-CPI-U Calcs'!$H18 -> 1.063279 | C129: =C$120*$B129 -> 318983.69 | D129: =+TRUNC(C129/50)*50 -> 318950 | E129: =E$120*$B129 -> 265819.74 | F129: =+TRUNC(E129/50)*50 -> 265800 | G129: =G$120*$B129 -> 292401.71 | H129: =+TRUNC(G129/50)*50 -> 292400 | I129: =I$120*$B129 -> 159491.84 | J129: =+TRUNC(I129/25)*25 -> 159475
A130: =A131+1 -> 2017 | B130: ='CPI-U & C-CPI-U Calcs'!$H19 -> 1.0460206 | C130: =C$120*$B130 -> 313806.19 | D130: =+TRUNC(C130/50)*50 -> 313800 | E130: =E$120*$B130 -> 261505.16 | F130: =+TRUNC(E130/50)*50 -> 261500 | G130: =G$120*$B130 -> 287655.68 | H130: =+TRUNC(G130/50)*50 -> 287650 | I130: =I$120*$B130 -> 156903.1 | J130: =+TRUNC(I130/25)*25 -> 156900
A131: =A132+1 -> 2016 | B131: ='CPI-U & C-CPI-U Calcs'!$H20 -> 1.0376924 | C131: =C$120*$B131 -> 311307.72 | D131: =+TRUNC(C131/50)*50 -> 311300 | E131: =E$120*$B131 -> 259423.1 | F131: =+TRUNC(E131/50)*50 -> 259400 | G131: =G$120*$B131 -> 285365.41 | H131: =+TRUNC(G131/50)*50 -> 285350 | I131: =I$120*$B131 -> 155653.86 | J131: =+TRUNC(I131/25)*25 -> 155650
A132: =A133+1 -> 2015 | B132: ='CPI-U & C-CPI-U Calcs'!$H21 -> 1.0330292 | C132: =C$120*$B132 -> 309908.75 | D132: =+TRUNC(C132/50)*50 -> 309900 | E132: =E$120*$B132 -> 258257.29 | F132: =+TRUNC(E132/50)*50 -> 258250 | G132: =G$120*$B132 -> 284083.02 | H132: =+TRUNC(G132/50)*50 -> 284050 | I132: =I$120*$B132 -> 154954.37 | J132: =+TRUNC(I132/25)*25 -> 154950
A133: =A134+1 -> 2014 | B133: ='CPI-U & C-CPI-U Calcs'!$H22 -> 1.0169571 | C133: =C$120*$B133 -> 305087.13 | D133: =+TRUNC(C133/50)*50 -> 305050 | E133: =E$120*$B133 -> 254239.27 | F133: =+TRUNC(E133/50)*50 -> 254200 | G133: =G$120*$B133 -> 279663.2 | H133: =+TRUNC(G133/50)*50 -> 279650 | I133: =I$120*$B133 -> 152543.56 | J133: =+TRUNC(I133/25)*25 -> 152525
A134: 2013 | B134: ='CPI-U & C-CPI-U Calcs'!$H23 -> 1 | C134: 300000 | D134: =+TRUNC(C134/50)*50 -> 300000 | E134: 250000 | F134: =+TRUNC(E134/50)*50 -> 250000 | G134: 275000 | H134: =+TRUNC(G134/50)*50 -> 275000 | I134: 150000 | J134: =+TRUNC(I134/50)*50 -> 150000
A137: QBI (Qualified Business Income) Deduction Phase Out
...

Sheet Tax Brackets
A1: Income Tax Brackets
A2: NOTE: All values based upon "taxable year".
A3: These are IRS published values. The raw values that we use are under the tabs showing tax law extension.
A4: *** See "2022-2026 IRS Updates" sheet for complete updated 2022-2026 values from IRS Rev. Procs. 2021-45 through 2025-32 and OBBBA 2025 ***
A6: Income Tax Brackets
A7: 2021 Tax Rate Schedules
A8: Schedule Y-1 - Joint | D8: Schedule X - Single | G8: Schedule Z - Head of Household | J8: Schedule Y-2 - Separate | M8: Schedule for Trusts
A9: From | B9: To | C9: Tax Rate | D9: From | E9: To | F9: Rate | G9: From | H9: To | I9: Tax Rate | J9: From | K9: To | L9: Tax Rate | M9: From | N9: To | O9: Tax Rate
A10: 0 | B10: ='Tax Bracket Calcs'!F$22 -> 19900 | C10: 0.1 | D10: 0 | E10: ='Tax Bracket Calcs'!M$22 -> 9950 | F10: 0.1 | G10: 0 | H10: ='Tax Bracket Calcs'!T$22 -> 14200 | I10: 0.1 | J10: 0 | K10: ='Tax Bracket Calcs'!AA$22 -> 9950 | L10: 0.1 | M10: 0 | N10: ='Tax Bracket Calcs'!AH$22 -> 2650 | O10: 0.1
A11: =B10 -> 19900 | B11: ='Tax Bracket Calcs'!G$22 -> 81050 | C11: 0.12 | D11: =E10 -> 9950 | E11: ='Tax Bracket Calcs'!N$22 -> 40525 | F11: 0.12 | G11: =H10 -> 14200 | H11: ='Tax Bracket Calcs'!U$22 -> 54200 | I11: 0.12 | J11: =K10 -> 9950 | K11: ='Tax Bracket Calcs'!AB$22 -> 40525 | L11: 0.12 | M11: 0 | N11: ='Tax Bracket Calcs'!AI$22 -> unused | O11: 0.12
A12: =B11 -> 81050 | B12: ='Tax Bracket Calcs'!H$22 -> 172750 | C12: 0.22 | D12: =E11 -> 40525 | E12: ='Tax Bracket Calcs'!O$22 -> 86375 | F12: 0.22 | G12: =H11 -> 54200 | H12: ='Tax Bracket Calcs'!V$22 -> 86350 | I12: 0.22 | J12: =K11 -> 40525 | K12: ='Tax Bracket Calcs'!AC$22 -> 86375 | L12: 0.22 | M12: =N11 -> unused | N12: ='Tax Bracket Calcs'!AJ$22 -> unused | O12: 0.22
A13: =B12 -> 172750 | B13: ='Tax Bracket Calcs'!I$22 -> 329850 | C13: 0.24 | D13: =E12 -> 86375 | E13: ='Tax Bracket Calcs'!P$22 -> 164925 | F13: 0.24 | G13: =H12 -> 86350 | H13: ='Tax Bracket Calcs'!W$22 -> 164900 | I13: 0.24 | J13: =K12 -> 86375 | K13: ='Tax Bracket Calcs'!AD$22 -> 164925 | L13: 0.24 | M13: =N12 -> unused | N13: ='Tax Bracket Calcs'!AK$22 -> 9550 | O13: 0.24
A14: =B13 -> 329850 | B14: ='Tax Bracket Calcs'!J$22 -> 418850 | C14: 0.32 | D14: =E13 -> 164925 | E14: ='Tax Bracket Calcs'!Q$22 -> 209425 | F14: 0.32 | G14: =H13 -> 164900 | H14: ='Tax Bracket Calcs'!X$22 -> 209400 | I14: 0.32 | J14: =K13 -> 164925 | K14: ='Tax Bracket Calcs'!AE$22 -> 209425 | L14: 0.32 | M14: =N13 -> 9550 | N14: ='Tax Bracket Calcs'!AL$22 -> unused | O14: 0.32
A15: =B14 -> 418850 | B15: ='Tax Bracket Calcs'!K$22 -> 628300 | C15: 0.35 | D15: =E14 -> 209425 | E15: ='Tax Bracket Calcs'!R$22 -> 523600 | F15: 0.35 | G15: =H14 -> 209400 | H15: ='Tax Bracket Calcs'!Y$22 -> 523600 | I15: 0.35 | J15: =K14 -> 209425 | K15: ='Tax Bracket Calcs'!AF$22 -> 314150 | L15: 0.35 | M15: =N14 -> unused | N15: ='Tax Bracket Calcs'!AM$22 -> 13050 | O15: 0.35
A16: =B15 -> 628300 | B16: above | C16: 0.37 | D16: =E15 -> 523600 | E16: above | F16: 0.37 | G16: =H15 -> 523600 | H16: above | I16: 0.37 | J16: =K15 -> 314150 | K16: above | L16: 0.37 | M16: =N15 -> 13050 | N16: above | O16: 0.37
A19: 2020 Tax Rate Schedules
A20: Schedule Y-1 - Joint | D20: Schedule X - Single | G20: Schedule Z - Head of Household | J20: Schedule Y-2 - Separate | M20: Schedule for Trusts
A21: From | B21: To | C21: Tax Rate | D21: From | E21: To | F21: Rate | G21: From | H21: To | I21: Tax Rate | J21: From | K21: To | L21: Tax Rate | M21: From | N21: To | O21: Tax Rate
A22: 0 | B22: ='Tax Bracket Calcs'!F$23 -> 19700 | C22: 0.1 | D22: 0 | E22: ='Tax Bracket Calcs'!M$23 -> 9850 | F22: 0.1 | G22: 0 | H22: ='Tax Bracket Calcs'!T$23 -> 14050 | I22: 0.1 | J22: 0 | K22: ='Tax Bracket Calcs'!AA$23 -> 9850 | L22: 0.1 | M22: 0 | N22: ='Tax Bracket Calcs'!AH$23 -> 2600 | O22: 0.1
A23: =B22 -> 19700 | B23: ='Tax Bracket Calcs'!G$23 -> 80150 | C23: 0.12 | D23: =E22 -> 9850 | E23: ='Tax Bracket Calcs'!N$23 -> 40075 | F23: 0.12 | G23: =H22 -> 14050 | H23: ='Tax Bracket Calcs'!U$23 -> 53650 | I23: 0.12 | J23: =K22 -> 9850 | K23: ='Tax Bracket Calcs'!AB$23 -> 40075 | L23: 0.12 | M23: 0 | N23: ='Tax Bracket Calcs'!AI$23 -> unused | O23: 0.12
A24: =B23 -> 80150 | B24: ='Tax Bracket Calcs'!H$23 -> 170850 | C24: 0.22 | D24: =E23 -> 40075 | E24: ='Tax Bracket Calcs'!O$23 -> 85425 | F24: 0.22 | G24: =H23 -> 53650 | H24: ='Tax Bracket Calcs'!V$23 -> 85400 | I24: 0.22 | J24: =K23 -> 40075 | K24: ='Tax Bracket Calcs'!AC$23 -> 85425 | L24: 0.22 | M24: =N23 -> unused | N24: ='Tax Bracket Calcs'!AJ$23 -> unused | O24: 0.22
A25: =B24 -> 170850 | B25: ='Tax Bracket Calcs'!I$23 -> 326250 | C25: 0.24 | D25: =E24 -> 85425 | E25: ='Tax Bracket Calcs'!P$23 -> 163125 | F25: 0.24 | G25: =H24 -> 85400 | H25: ='Tax Bracket Calcs'!W$23 -> 163100 | I25: 0.24 | J25: =K24 -> 85425 | K25: ='Tax Bracket Calcs'!AD$23 -> 163125 | L25: 0.24 | M25: =N24 -> unused | N25: ='Tax Bracket Calcs'!AK$23 -> 9450 | O25: 0.24
A26: =B25 -> 326250 | B26: ='Tax Bracket Calcs'!J$23 -> 414250 | C26: 0.32 | D26: =E25 -> 163125 | E26: ='Tax Bracket Calcs'!Q$23 -> 207125 | F26: 0.32 | G26: =H25 -> 163100 | H26: ='Tax Bracket Calcs'!X$23 -> 207100 | I26: 0.32 | J26: =K25 -> 163125 | K26: ='Tax Bracket Calcs'!AE$23 -> 207125 | L26: 0.32 | M26: =N25 -> 9450 | N26: ='Tax Bracket Calcs'!AL$23 -> unused | O26: 0.32
A27: =B26 -> 414250 | B27: ='Tax Bracket Calcs'!K$23 -> 621400 | C27: 0.35 | D27: =E26 -> 207125 | E27: ='Tax Bracket Calcs'!R$23 -> 517850 | F27: 0.35 | G27: =H26 -> 207100 | H27: ='Tax Bracket Calcs'!Y$23 -> 517850 | I27: 0.35 | J27: =K26 -> 207125 | K27: ='Tax Bracket Calcs'!AF$23 -> 310700 | L27: 0.35 | M27: =N26 -> unused | N27: ='Tax Bracket Calcs'!AM$23 -> 12900 | O27: 0.35
A28: =B27 -> 621400 | B28: above | C28: 0.37 | D28: =E27 -> 517850 | E28: above | F28: 0.37 | G28: =H27 -> 517850 | H28: above | I28: 0.37 | J28: =K27 -> 310700 | K28: above | L28: 0.37 | M28: =N27 -> 12900 | N28: above | O28: 0.37
A31: 2019 Tax Rate Schedules
A32: Schedule Y-1 - Joint | D32: Schedule X - Single | G32: Schedule Z - Head of Household | J32: Schedule Y-2 - Separate | M32: Schedule for Trusts
A33: From | B33: To | C33: Tax Rate | D33: From | E33: To | F33: Rate | G33: From | H33: To | I33: Tax Rate | J33: From | K33: To | L33: Tax Rate | M33: From | N33: To | O33: Tax Rate
A34: 0 | B34: ='Tax Bracket Calcs'!F$24 -> 19400 | C34: 0.1 | D34: 0 | E34: ='Tax Bracket Calcs'!M$24 -> 9700 | F34: 0.1 | G34: 0 | H34: ='Tax Bracket Calcs'!T$24 -> 13850 | I34: 0.1 | J34: 0 | K34: ='Tax Bracket Calcs'!AA$24 -> 9700 | L34: 0.1 | M34: 0 | N34: ='Tax Bracket Calcs'!AH$24 -> 2600 | O34: 0.1
A35: =B34 -> 19400 | B35: ='Tax Bracket Calcs'!G$24 -> 78900 | C35: 0.12 | D35: =E34 -> 9700 | E35: ='Tax Bracket Calcs'!N$24 -> 39450 | F35: 0.12 | G35: =H34 -> 13850 | H35: ='Tax Bracket Calcs'!U$24 -> 52800 | I35: 0.12 | J35: =K34 -> 9700 | K35: ='Tax Bracket Calcs'!AB$24 -> 39450 | L35: 0.12 | M35: 0 | N35: ='Tax Bracket Calcs'!AI$24 -> unused | O35: 0.12
A36: =B35 -> 78900 | B36: ='Tax Bracket Calcs'!H$24 -> 168250 | C36: 0.22 | D36: =E35 -> 39450 | E36: ='Tax Bracket Calcs'!O$24 -> 84125 | F36: 0.22 | G36: =H35 -> 52800 | H36: ='Tax Bracket Calcs'!V$24 -> 84100 | I36: 0.22 | J36: =K35 -> 39450 | K36: ='Tax Bracket Calcs'!AC$24 -> 84125 | L36: 0.22 | M36: =N35 -> unused | N36: ='Tax Bracket Calcs'!AJ$24 -> unused | O36: 0.22
A37: =B36 -> 168250 | B37: ='Tax Bracket Calcs'!I$24 -> 321250 | C37: 0.24 | D37: =E36 -> 84125 | E37: ='Tax Bracket Calcs'!P$24 -> 160625 | F37: 0.24 | G37: =H36 -> 84100 | H37: ='Tax Bracket Calcs'!W$24 -> 160600 | I37: 0.24 | J37: =K36 -> 84125 | K37: ='Tax Bracket Calcs'!AD$24 -> 160625 | L37: 0.24 | M37: =N36 -> unused | N37: ='Tax Bracket Calcs'!AK$24 -> 9300 | O37: 0.24
A38: =B37 -> 321250 | B38: ='Tax Bracket Calcs'!J$24 -> 407950 | C38: 0.32 | D38: =E37 -> 160625 | E38: ='Tax Bracket Calcs'!Q$24 -> 203975 | F38: 0.32 | G38: =H37 -> 160600 | H38: ='Tax Bracket Calcs'!X$24 -> 203950 | I38: 0.32 | J38: =K37 -> 160625 | K38: ='Tax Bracket Calcs'!AE$24 -> 203975 | L38: 0.32 | M38: =N37 -> 9300 | N38: ='Tax Bracket Calcs'!AL$24 -> unused | O38: 0.32
A39: =B38 -> 407950 | B39: ='Tax Bracket Calcs'!K$24 -> 611950 | C39: 0.35 | D39: =E38 -> 203975 | E39: ='Tax Bracket Calcs'!R$24 -> 509950 | F39: 0.35 | G39: =H38 -> 203950 | H39: ='Tax Bracket Calcs'!Y$24 -> 509950 | I39: 0.35 | J39: =K38 -> 203975 | K39: ='Tax Bracket Calcs'!AF$24 -> 305975 | L39: 0.35 | M39: =N38 -> unused | N39: ='Tax Bracket Calcs'!AM$24 -> 12700 | O39: 0.35
A40: =B39 -> 611950 | B40: above | C40: 0.37 | D40: =E39 -> 509950 | E40: above | F40: 0.37 | G40: =H39 -> 509950 | H40: above | I40: 0.37 | J40: =K39 -> 305975 | K40: above | L40: 0.37 | M40: =N39 -> 12700 | N40: above | O40: 0.37
A43: 2018 Tax Rate Schedules
A44: Schedule Y-1 - Joint | D44: Schedule X - Single | G44: Schedule Z - Head of Household | J44: Schedule Y-2 - Separate | M44: Schedule for Trusts
A45: From | B45: To | C45: Tax Rate | D45: From | E45: To | F45: Rate | G45: From | H45: To | I45: Tax Rate | J45: From | K45: To | L45: Tax Rate | M45: From | N45: To | O45: Tax Rate
A46: 0 | B46: ='Tax Bracket Calcs'!F$25 -> 19050 | C46: 0.1 | D46: 0 | E46: ='Tax Bracket Calcs'!M$25 -> 9525 | F46: 0.1 | G46: 0 | H46: ='Tax Bracket Calcs'!T$25 -> 13600 | I46: 0.1 | J46: 0 | K46: ='Tax Bracket Calcs'!AA$25 -> 9525 | L46: 0.1 | M46: 0 | N46: ='Tax Bracket Calcs'!AH$25 -> 2550 | O46: 0.1
A47: =B46 -> 19050 | B47: ='Tax Bracket Calcs'!G$25 -> 77400 | C47: 0.12 | D47: =E46 -> 9525 | E47: ='Tax Bracket Calcs'!N$25 -> 38700 | F47: 0.15 | G47: =H46 -> 13600 | H47: ='Tax Bracket Calcs'!U$25 -> 51800 | I47: 0.15 | J47: =K46 -> 9525 | K47: ='Tax Bracket Calcs'!AB$25 -> 38700 | L47: 0.15 | M47: 0 | N47: ='Tax Bracket Calcs'!AI$25 -> unused | O47: 0.15
A48: =B47 -> 77400 | B48: ='Tax Bracket Calcs'!H$25 -> 165000 | C48: 0.22 | D48: =E47 -> 38700 | E48: ='Tax Bracket Calcs'!O$25 -> 82500 | F48: 0.25 | G48: =H47 -> 51800 | H48: ='Tax Bracket Calcs'!V$25 -> 82500 | I48: 0.25 | J48: =K47 -> 38700 | K48: ='Tax Bracket Calcs'!AC$25 -> 82500 | L48: 0.25 | M48: =N47 -> unused | N48: ='Tax Bracket Calcs'!AJ$25 -> unused | O48: 0.25
A49: =B48 -> 165000 | B49: ='Tax Bracket Calcs'!I$25 -> 315000 | C49: 0.24 | D49: =E48 -> 82500 | E49: ='Tax Bracket Calcs'!P$25 -> 157500 | F49: 0.28 | G49: =H48 -> 82500 | H49: ='Tax Bracket Calcs'!W$25 -> 157500 | I49: 0.28 | J49: =K48 -> 82500 | K49: ='Tax Bracket Calcs'!AD$25 -> 157500 | L49: 0.28 | M49: =N48 -> unused | N49: ='Tax Bracket Calcs'!AK$25 -> 9150 | O49: 0.28
A50: =B49 -> 315000 | B50: ='Tax Bracket Calcs'!J$25 -> 400000 | C50: 0.32 | D50: =E49 -> 157500 | E50: ='Tax Bracket Calcs'!Q$25 -> 200000 | F50: 0.33 | G50: =H49 -> 157500 | H50: ='Tax Bracket Calcs'!X$25 -> 200000 | I50: 0.33 | J50: =K49 -> 157500 | K50: ='Tax Bracket Calcs'!AE$25 -> 200000 | L50: 0.33 | M50: =N49 -> 9150 | N50: ='Tax Bracket Calcs'!AL$25 -> unused | O50: 0.33
A51: =B50 -> 400000 | B51: ='Tax Bracket Calcs'!K$25 -> 600000 | C51: 0.35 | D51: =E50 -> 200000 | E51: ='Tax Bracket Calcs'!R$25 -> 500000 | F51: 0.35 | G51: =H50 -> 200000 | H51: ='Tax Bracket Calcs'!Y$25 -> 500000 | I51: 0.35 | J51: =K50 -> 200000 | K51: ='Tax Bracket Calcs'!AF$25 -> 300000 | L51: 0.35 | M51: =N50 -> unused | N51: ='Tax Bracket Calcs'!AM$25 -> 12500 | O51: 0.35
A52: =B51 -> 600000 | B52: above | C52: 0.37 | D52: =E51 -> 500000 | E52: above | F52: 0.396 | G52: =H51 -> 500000 | H52: above | I52: 0.396 | J52: =K51 -> 300000 | K52: above | L52: 0.396 | M52: =N51 -> 12500 | N52: above | O52: 0.396
A55: Income Tax Brackets (for 2026 Sunset)
A56: 2019 Tax Rate Schedules
A57: Schedule Y-1 - Joint | D57: Schedule X - Single | G57: Schedule Z - Head of Household | J57: Schedule Y-2 - Separate | M57: Schedule for Trusts
A58: From | B58: To | C58: Tax Rate | D58: From | E58: To | F58: Tax Rate | G58: From | H58: To | I58: Tax Rate | J58: From | K58: To | L58: Tax Rate | M58: From | N58: To | O58: Tax Rate
A59: 0 | B59: ='Tax Bracket Calcs'!F$71 -> 19350 | C59: 0.1 | D59: 0 | E59: ='Tax Bracket Calcs'!M$71 -> 9675 | F59: 0.1 | G59: 0 | H59: ='Tax Bracket Calcs'!T$71 -> 13800 | I59: 0.1 | J59: 0 | K59: ='Tax Bracket Calcs'!AA$71 -> 9675 | L59: 0.1 | M59: 0 | N59: ='Tax Bracket Calcs'!AH$71 -> 0 | O59: 0.1
A60: =B59 -> 19350 | B60: ='Tax Bracket Calcs'!G$71 -> 78700 | C60: 0.15 | D60: =E59 -> 9675 | E60: ='Tax Bracket Calcs'!N$71 -> 39350 | F60: 0.15 | G60: =H59 -> 13800 | H60: ='Tax Bracket Calcs'!U$71 -> 52700 | I60: 0.15 | J60: =K59 -> 9675 | K60: ='Tax Bracket Calcs'!AB$71 -> 39350 | L60: 0.15 | M60: 0 | N60: ='Tax Bracket Calcs'!AI$71 -> 2650 | O60: 0.15
A61: =B60 -> 78700 | B61: ='Tax Bracket Calcs'!H$71 -> 158750 | C61: 0.25 | D61: =E60 -> 39350 | E61: ='Tax Bracket Calcs'!O$71 -> 95250 | F61: 0.25 | G61: =H60 -> 52700 | H61: ='Tax Bracket Calcs'!V$71 -> 136050 | I61: 0.25 | J61: =K60 -> 39350 | K61: ='Tax Bracket Calcs'!AC$71 -> 79375 | L61: 0.25 | M61: =N60 -> 2650 | N61: ='Tax Bracket Calcs'!AJ$71 -> 6200 | O61: 0.25
A62: =B61 -> 158750 | B62: ='Tax Bracket Calcs'!I$71 -> 241900 | C62: 0.28 | D62: =E61 -> 95250 | E62: ='Tax Bracket Calcs'!P$71 -> 198700 | F62: 0.28 | G62: =H61 -> 136050 | H62: ='Tax Bracket Calcs'!W$71 -> 220300 | I62: 0.28 | J62: =K61 -> 79375 | K62: ='Tax Bracket Calcs'!AD$71 -> 120950 | L62: 0.28 | M62: =N61 -> 6200 | N62: ='Tax Bracket Calcs'!AK$71 -> 9500 | O62: 0.28
A63: =B62 -> 241900 | B63: ='Tax Bracket Calcs'!J$71 -> 432000 | C63: 0.33 | D63: =E62 -> 198700 | E63: ='Tax Bracket Calcs'!Q$71 -> 432000 | F63: 0.33 | G63: =H62 -> 220300 | H63: ='Tax Bracket Calcs'!X$71 -> 432000 | I63: 0.33 | J63: =K62 -> 120950 | K63: ='Tax Bracket Calcs'!AE$71 -> 216000 | L63: 0.33 | M63: =N62 -> 9500 | N63: ='Tax Bracket Calcs'!AL$71 -> 12950 | O63: 0.33
A64: =B63 -> 432000 | B64: ='Tax Bracket Calcs'!K$71 -> 488000 | C64: 0.35 | D64: =E63 -> 432000 | E64: ='Tax Bracket Calcs'!R$71 -> 433750 | F64: 0.35 | G64: =H63 -> 432000 | H64: ='Tax Bracket Calcs'!Y$71 -> 460900 | I64: 0.35 | J64: =K63 -> 216000 | K64: ='Tax Bracket Calcs'!AF$71 -> 244000 | L64: 0.35 | M64: =N63 -> 12950 | N64: ='Tax Bracket Calcs'!AM$71 -> unused | O64: 0.35
A65: =B64 -> 488000 | B65: above | C65: 0.396 | D65: =E64 -> 433750 | E65: above | F65: 0.396 | G65: =H64 -> 460900 | H65: above | I65: 0.396 | J65: =K64 -> 244000 | K65: above | L65: 0.396 | M65: =N64 -> unused | N65: above | O65: 0.396
A67: 2018 Tax Rate Schedules
A68: Schedule Y-1 - Joint | D68: Schedule X - Single | G68: Schedule Z - Head of Household | J68: Schedule Y-2 - Separate | M68: Schedule for Trusts
A69: From | B69: To | C69: Tax Rate | D69: From | E69: To | F69: Tax Rate | G69: From | H69: To | I69: Tax Rate | J69: From | K69: To | L69: Tax Rate | M69: From | N69: To | O69: Tax Rate
A70: 0 | B70: ='Tax Bracket Calcs'!F$72 -> 19000 | C70: 0.1 | D70: 0 | E70: ='Tax Bracket Calcs'!M$72 -> 9500 | F70: 0.1 | G70: 0 | H70: ='Tax Bracket Calcs'!T$72 -> 13550 | I70: 0.1 | J70: 0 | K70: ='Tax Bracket Calcs'!AA$72 -> 9500 | L70: 0.1 | M70: 0 | N70: ='Tax Bracket Calcs'!AH$72 -> 0 | O70: 0.1
A71: =B70 -> 19000 | B71: ='Tax Bracket Calcs'!G$72 -> 77100 | C71: 0.15 | D71: =E70 -> 9500 | E71: ='Tax Bracket Calcs'!N$72 -> 38550 | F71: 0.15 | G71: =H70 -> 13550 | H71: ='Tax Bracket Calcs'!U$72 -> 51650 | I71: 0.15 | J71: =K70 -> 9500 | K71: ='Tax Bracket Calcs'!AB$72 -> 38550 | L71: 0.15 | M71: 0 | N71: ='Tax Bracket Calcs'!AI$72 -> 2600 | O71: 0.15
A72: =B71 -> 77100 | B72: ='Tax Bracket Calcs'!H$72 -> 155650 | C72: 0.25 | D72: =E71 -> 38550 | E72: ='Tax Bracket Calcs'!O$72 -> 93400 | F72: 0.25 | G72: =H71 -> 51650 | H72: ='Tax Bracket Calcs'!V$72 -> 133400 | I72: 0.25 | J72: =K71 -> 38550 | K72: ='Tax Bracket Calcs'!AC$72 -> 77825 | L72: 0.25 | M72: =N71 -> 2600 | N72: ='Tax Bracket Calcs'!AJ$72 -> 6100 | O72: 0.25
A73: =B72 -> 155650 | B73: ='Tax Bracket Calcs'!I$72 -> 237200 | C73: 0.28 | D73: =E72 -> 93400 | E73: ='Tax Bracket Calcs'!P$72 -> 194800 | F73: 0.28 | G73: =H72 -> 133400 | H73: ='Tax Bracket Calcs'!W$72 -> 216000 | I73: 0.28 | J73: =K72 -> 77825 | K73: ='Tax Bracket Calcs'!AD$72 -> 118600 | L73: 0.28 | M73: =N72 -> 6100 | N73: ='Tax Bracket Calcs'!AK$72 -> 9300 | O73: 0.28
A74: =B73 -> 237200 | B74: ='Tax Bracket Calcs'!J$72 -> 423550 | C74: 0.33 | D74: =E73 -> 194800 | E74: ='Tax Bracket Calcs'!Q$72 -> 423550 | F74: 0.33 | G74: =H73 -> 216000 | H74: ='Tax Bracket Calcs'!X$72 -> 423550 | I74: 0.33 | J74: =K73 -> 118600 | K74: ='Tax Bracket Calcs'!AE$72 -> 211775 | L74: 0.33 | M74: =N73 -> 9300 | N74: ='Tax Bracket Calcs'!AL$72 -> 12700 | O74: 0.33
A75: =B74 -> 423550 | B75: ='Tax Bracket Calcs'!K$72 -> 478450 | C75: 0.35 | D75: =E74 -> 423550 | E75: ='Tax Bracket Calcs'!R$72 -> 425300 | F75: 0.35 | G75: =H74 -> 423550 | H75: ='Tax Bracket Calcs'!Y$72 -> 451850 | I75: 0.35 | J75: =K74 -> 211775 | K75: ='Tax Bracket Calcs'!AF$72 -> 239225 | L75: 0.35 | M75: =N74 -> 12700 | N75: ='Tax Bracket Calcs'!AM$72 -> unused | O75: 0.35
A76: =B75 -> 478450 | B76: above | C76: 0.396 | D76: =E75 -> 425300 | E76: above | F76: 0.396 | G76: =H75 -> 451850 | H76: above | I76: 0.396 | J76: =K75 -> 239225 | K76: above | L76: 0.396 | M76: =N75 -> unused | N76: above | O76: 0.396
A78: 2017 Tax Rate Schedules
A79: Schedule Y-1 - Joint | D79: Schedule X - Single | G79: Schedule Z - Head of Household | J79: Schedule Y-2 - Separate | M79: Schedule for Trusts
A80: From | B80: To | C80: Tax Rate | D80: From | E80: To | F80: Tax Rate | G80: From | H80: To | I80: Tax Rate | J80: From | K80: To | L80: Tax Rate | M80: From | N80: To | O80: Tax Rate
A81: 0 | B81: ='Tax Bracket Calcs'!F$73 -> 18650 | C81: 0.1 | D81: 0 | E81: ='Tax Bracket Calcs'!M$73 -> 9325 | F81: 0.1 | G81: 0 | H81: ='Tax Bracket Calcs'!T$73 -> 13350 | I81: 0.1 | J81: 0 | K81: ='Tax Bracket Calcs'!AA$73 -> 9325 | L81: 0.1 | M81: 0 | N81: ='Tax Bracket Calcs'!AH$73 -> 0 | O81: 0.1
A82: =B81 -> 18650 | B82: ='Tax Bracket Calcs'!G$73 -> 75900 | C82: 0.15 | D82: =E81 -> 9325 | E82: ='Tax Bracket Calcs'!N$73 -> 37950 | F82: 0.15 | G82: =H81 -> 13350 | H82: ='Tax Bracket Calcs'!U$73 -> 50800 | I82: 0.15 | J82: =K81 -> 9325 | K82: ='Tax Bracket Calcs'!AB$73 -> 37950 | L82: 0.15 | M82: 0 | N82: ='Tax Bracket Calcs'!AI$73 -> 2550 | O82: 0.15
A83: =B82 -> 75900 | B83: ='Tax Bracket Calcs'!H$73 -> 153100 | C83: 0.25 | D83: =E82 -> 37950 | E83: ='Tax Bracket Calcs'!O$73 -> 91900 | F83: 0.25 | G83: =H82 -> 50800 | H83: ='Tax Bracket Calcs'!V$73 -> 131200 | I83: 0.25 | J83: =K82 -> 37950 | K83: ='Tax Bracket Calcs'!AC$73 -> 76550 | L83: 0.25 | M83: =N82 -> 2550 | N83: ='Tax Bracket Calcs'!AJ$73 -> 6000 | O83: 0.25
A84: =B83 -> 153100 | B84: ='Tax Bracket Calcs'!I$73 -> 233350 | C84: 0.28 | D84: =E83 -> 91900 | E84: ='Tax Bracket Calcs'!P$73 -> 191650 | F84: 0.28 | G84: =H83 -> 131200 | H84: ='Tax Bracket Calcs'!W$73 -> 212500 | I84: 0.28 | J84: =K83 -> 76550 | K84: ='Tax Bracket Calcs'!AD$73 -> 116675 | L84: 0.28 | M84: =N83 -> 6000 | N84: ='Tax Bracket Calcs'!AK$73 -> 9150 | O84: 0.28
A85: =B84 -> 233350 | B85: ='Tax Bracket Calcs'!J$73 -> 416700 | C85: 0.33 | D85: =E84 -> 191650 | E85: ='Tax Bracket Calcs'!Q$73 -> 416700 | F85: 0.33 | G85: =H84 -> 212500 | H85: ='Tax Bracket Calcs'!X$73 -> 416700 | I85: 0.33 | J85: =K84 -> 116675 | K85: ='Tax Bracket Calcs'!AE$73 -> 208350 | L85: 0.33 | M85: =N84 -> 9150 | N85: ='Tax Bracket Calcs'!AL$73 -> 12500 | O85: 0.33
A86: =B85 -> 416700 | B86: ='Tax Bracket Calcs'!K$73 -> 470700 | C86: 0.35 | D86: =E85 -> 416700 | E86: ='Tax Bracket Calcs'!R$73 -> 418400 | F86: 0.35 | G86: =H85 -> 416700 | H86: ='Tax Bracket Calcs'!Y$73 -> 444550 | I86: 0.35 | J86: =K85 -> 208350 | K86: ='Tax Bracket Calcs'!AF$73 -> 235350 | L86: 0.35 | M86: =N85 -> 12500 | N86: ='Tax Bracket Calcs'!AM$73 -> unused | O86: 0.35
A87: =B86 -> 470700 | B87: above | C87: 0.396 | D87: =E86 -> 418400 | E87: above | F87: 0.396 | G87: =H86 -> 444550 | H87: above | I87: 0.396 | J87: =K86 -> 235350 | K87: above | L87: 0.396 | M87: =N86 -> unused | N87: above | O87: 0.396

Sheet Tax Bracket Calcs
A1: CPI Indexing Calculations for Income & Capital Gains Tax Brackets
A2: These calculations are used to index IRS base numbers from the internal revenue code to future years.
A4: Color Coding:
A5: Green | B5: Base value that is indexed to get subsequent year values.
A6: Red | B6: Future values based upon a CPI value (3% in the examples) picked out of the air.
A7: Gray | B7: Values maintained to support the sunset provisions in 2026.
A9: Income Tax Brackets
F10: Married Filing Jointly | M10: Single | T10: Head of Household | AA10: Married Filing Separately | AH10: Trusts & Estates
A11: Tax Year | E11: CPI (base year 2018) | F11: 10% Bracket | G11: 12% Bracket | H11: 22% Bracket | I11: 24% Bracket | J11: 32% Bracket | K11: 35% Bracket | L11: 37% Bracket | M11: 10% Bracket | N11: 12% Bracket | O11: 22% Bracket | P11: 24% Bracket | Q11: 32% Bracket | R11: 35% Bracket | S11: 37% Bracket | T11: 10% Bracket | U11: 12% Bracket | V11: 22% Bracket | W11: 24% Bracket | X11: 32% Bracket | Y11: 35% Bracket | Z11: 37% Bracket | AA11: 10% Bracket | AB11: 12% Bracket | AC11: 22% Bracket | AD11: 24% Bracket | AE11: 32% Bracket | AF11: 35% Bracket | AG11: 37% Bracket | AH11: 10% Bracket | AI11: 12% Bracket | AJ11: 22% Bracket | AK11: 24% Bracket | AL11: 32% Bracket | AM11: 35% Bracket | AN11: 37% Bracket
A12: =A13+1 -> 2022 | E12: ='CPI-U & C-CPI-U Calcs'!$F14 -> 1.0786208 | F12: =F$16*$E12 -> 20547.726 | G12: =G$16*$E12 -> 83485.249 | H12: =H$16*$E12 -> 177972.43 | I12: =I$16*$E12 -> 339765.55 | J12: =J$16*$E12 -> 431448.31 | K12: =K$16*$E12 -> 647172.47 | L12: excess | M12: =M$16*$E12 -> 10273.863 | N12: =N$16*$E12 -> 41742.624 | O12: =O$16*$E12 -> 88986.215 | P12: =P$16*$E12 -> 169882.77 | Q12: =Q$16*$E12 -> 215724.16 | R12: =R$16*$E12 -> 539310.39 | S12: excess | T12: =T$16*$E12 -> 14669.243 | U12: =U$16*$E12 -> 55872.557 | V12: =V$16*$E12 -> 88986.215 | W12: =W$16*$E12 -> 169882.77 | X12: =X$16*$E12 -> 215724.16 | Y12: =Y$16*$E12 -> 539310.39 | Z12: excess | AA12: =AA$16*$E12 -> 10273.863 | AB12: =AB$16*$E12 -> 41742.624 | AC12: =AC$16*$E12 -> 88986.215 | AD12: =AD$16*$E12 -> 169882.77 | AE12: =AE$16*$E12 -> 215724.16 | AF12: =AF$16*$E12 -> 323586.24 | AG12: excess | AH12: =AH$16*$E12 -> 2750.483 | AI12: unused | AJ12: unused | AK12: =AK$16*$E12 -> 9869.3802 | AL12: unused | AM12: =AM$16*$E12 -> 13482.76 | AN12: excess
A13: =A14+1 -> 2021 | E13: ='CPI-U & C-CPI-U Calcs'!$F15 -> 1.0472046 | F13: =F$16*$E13 -> 19949.248 | G13: =G$16*$E13 -> 81053.639 | H13: =H$16*$E13 -> 172788.77 | I13: =I$16*$E13 -> 329869.46 | J13: =J$16*$E13 -> 418881.86 | K13: =K$16*$E13 -> 628322.79 | L13: excess | M13: =M$16*$E13 -> 9974.6242 | N13: =N$16*$E13 -> 40526.82 | O13: =O$16*$E13 -> 86394.383 | P13: =P$16*$E13 -> 164934.73 | Q13: =Q$16*$E13 -> 209440.93 | R13: =R$16*$E13 -> 523602.32 | S13: excess | T13: =T$16*$E13 -> 14241.983 | U13: =U$16*$E13 -> 54245.201 | V13: =V$16*$E13 -> 86394.383 | W13: =W$16*$E13 -> 164934.73 | X13: =X$16*$E13 -> 209440.93 | Y13: =Y$16*$E13 -> 523602.32 | Z13: excess | AA13: =AA$16*$E13 -> 9974.6242 | AB13: =AB$16*$E13 -> 40526.82 | AC13: =AC$16*$E13 -> 86394.383 | AD13: =AD$16*$E13 -> 164934.73 | AE13: =AE$16*$E13 -> 209440.93 | AF13: =AF$16*$E13 -> 314161.39 | AG13: excess | AH13: =AH$16*$E13 -> 2670.3718 | AI13: unused | AJ13: unused | AK13: =AK$16*$E13 -> 9581.9225 | AL13: unused | AM13: =AM$16*$E13 -> 13090.058 | AN13: excess
A14: =A15+1 -> 2020 | E14: ='CPI-U & C-CPI-U Calcs'!$F16 -> 1.0357497 | F14: =F$16*$E14 -> 19731.031 | G14: =G$16*$E14 -> 80167.024 | H14: =H$16*$E14 -> 170898.69 | I14: =I$16*$E14 -> 326261.14 | J14: =J$16*$E14 -> 414299.86 | K14: =K$16*$E14 -> 621449.8 | L14: excess | M14: =M$16*$E14 -> 9865.5155 | N14: =N$16*$E14 -> 40083.512 | O14: =O$16*$E14 -> 85449.347 | P14: =P$16*$E14 -> 163130.57 | Q14: =Q$16*$E14 -> 207149.93 | R14: =R$16*$E14 -> 517874.83 | S14: excess | T14: =T$16*$E14 -> 14086.195 | U14: =U$16*$E14 -> 53651.832 | V14: =V$16*$E14 -> 85449.347 | W14: =W$16*$E14 -> 163130.57 | X14: =X$16*$E14 -> 207149.93 | Y14: =Y$16*$E14 -> 517874.83 | Z14: excess | AA14: =AA$16*$E14 -> 9865.5155 | AB14: =AB$16*$E14 -> 40083.512 | AC14: =AC$16*$E14 -> 85449.347 | AD14: =AD$16*$E14 -> 163130.57 | AE14: =AE$16*$E14 -> 207149.93 | AF14: =AF$16*$E14 -> 310724.9 | AG14: excess | AH14: =AH$16*$E14 -> 2641.1616 | AI14: unused | AJ14: unused | AK14: =AK$16*$E14 -> 9477.1094 | AL14: unused | AM14: =AM$16*$E14 -> 12946.871 | AN14: excess
A15: =A16+1 -> 2019 | E15: ='CPI-U & C-CPI-U Calcs'!$F17 -> 1.0199308 | F15: =F$16*$E15 -> 19429.681 | G15: =G$16*$E15 -> 78942.643 | H15: =H$16*$E15 -> 168288.58 | I15: =I$16*$E15 -> 321278.2 | J15: =J$16*$E15 -> 407972.31 | K15: =K$16*$E15 -> 611958.47 | L15: excess | M15: =M$16*$E15 -> 9714.8407 | N15: =N$16*$E15 -> 39471.321 | O15: =O$16*$E15 -> 84144.29 | P15: =P$16*$E15 -> 160639.1 | Q15: =Q$16*$E15 -> 203986.16 | R15: =R$16*$E15 -> 509965.39 | S15: excess | T15: =T$16*$E15 -> 13871.059 | U15: =U$16*$E15 -> 52832.415 | V15: =V$16*$E15 -> 84144.29 | W15: =W$16*$E15 -> 160639.1 | X15: =X$16*$E15 -> 203986.16 | Y15: =Y$16*$E15 -> 509965.39 | Z15: excess | AA15: =AA$16*$E15 -> 9714.8407 | AB15: =AB$16*$E15 -> 39471.321 | AC15: =AC$16*$E15 -> 84144.29 | AD15: =AD$16*$E15 -> 160639.1 | AE15: =AE$16*$E15 -> 203986.16 | AF15: =AF$16*$E15 -> 305979.23 | AG15: excess | AH15: =AH$16*$E15 -> 2600.8235 | AI15: unused | AJ15: unused | AK15: =AK$16*$E15 -> 9332.3667 | AL15: unused | AM15: =AM$16*$E15 -> 12749.135 | AN15: excess
A16: 2018 | E16: ='CPI-U & C-CPI-U Calcs'!$F18 -> 1 | F16: 19050 | G16: 77400 | H16: 165000 | I16: 315000 | J16: 400000 | K16: 600000 | L16: excess | M16: 9525 | N16: 38700 | O16: 82500 | P16: 157500 | Q16: 200000 | R16: 500000 | S16: excess | T16: 13600 | U16: 51800 | V16: 82500 | W16: 157500 | X16: 200000 | Y16: 500000 | Z16: excess | AA16: 9525 | AB16: 38700 | AC16: 82500 | AD16: 157500 | AE16: 200000 | AF16: 300000 | AG16: excess | AH16: 2550 | AI16: unused | AJ16: unused | AK16: 9150 | AL16: unused | AM16: 12500 | AN16: excess
AA17: * NOTE: Actual law sets this to 50% of the rounded Joint amount.
A18: Rounded Income Tax Brackets
F19: Married Filing Jointly | M19: Single | T19: Head of Household | AA19: Married Filing Separately | AH19: Trusts & Estates
A20: Tax Year | F20: 10% Bracket | G20: 12% Bracket | H20: 22% Bracket | I20: 24% Bracket | J20: 32% Bracket | K20: 35% Bracket | L20: 37% Bracket | M20: 10% Bracket | N20: 12% Bracket | O20: 22% Bracket | P20: 24% Bracket | Q20: 32% Bracket | R20: 35% Bracket | S20: 37% Bracket | T20: 10% Bracket | U20: 12% Bracket | V20: 22% Bracket | W20: 24% Bracket | X20: 32% Bracket | Y20: 35% Bracket | Z20: 37% Bracket | AA20: 10% Bracket | AB20: 12% Bracket | AC20: 22% Bracket | AD20: 24% Bracket | AE20: 32% Bracket | AF20: 35% Bracket | AG20: 37% Bracket | AH20: 10% Bracket | AI20: 12% Bracket | AJ20: 22% Bracket | AK20: 24% Bracket | AL20: 32% Bracket | AM20: 35% Bracket | AN20: 37% Bracket
A21: =A22+1 -> 2022 | F21: =TRUNC(F12/50)*50 -> 20500 | G21: =TRUNC(G12/50)*50 -> 83450 | H21: =TRUNC(H12/50)*50 -> 177950 | I21: =TRUNC(I12/50)*50 -> 339750 | J21: =TRUNC(J12/50)*50 -> 431400 | K21: =TRUNC(K12/50)*50 -> 647150 | L21: excess | M21: =TRUNC(M12/25)*25 -> 10250 | N21: =TRUNC(N12/25)*25 -> 41725 | O21: =TRUNC(O12/25)*25 -> 88975 | P21: =TRUNC(P12/25)*25 -> 169875 | Q21: =TRUNC(Q12/25)*25 -> 215700 | R21: =TRUNC(R12/25)*25 -> 539300 | S21: excess | T21: =TRUNC(T12/50)*50 -> 14650 | U21: =TRUNC(U12/50)*50 -> 55850 | V21: =TRUNC(V12/50)*50 -> 88950 | W21: =TRUNC(W12/50)*50 -> 169850 | X21: =TRUNC(X12/50)*50 -> 215700 | Y21: =TRUNC(Y12/50)*50 -> 539300 | Z21: excess | AA21: =TRUNC(AA12/25)*25 -> 10250 | AB21: =TRUNC(AB12/50)*50 -> 41700 | AC21: =TRUNC(AC12/25)*25 -> 88975 | AD21: =TRUNC(AD12/25)*25 -> 169875 | AE21: =TRUNC(AE12/25)*25 -> 215700 | AF21: =TRUNC(AF12/25)*25 -> 323575 | AG21: excess | AH21: =TRUNC(AH12/50)*50 -> 2750 | AI21: =AI12 -> unused | AJ21: =AJ12 -> unused | AK21: =TRUNC(AK12/50)*50 -> 9850 | AL21: =AL12 -> unused | AM21: =TRUNC(AM12/50)*50 -> 13450 | AN21: =AN12 -> excess
A22: =A23+1 -> 2021 | F22: =TRUNC(F13/50)*50 -> 19900 | G22: =TRUNC(G13/50)*50 -> 81050 | H22: =TRUNC(H13/50)*50 -> 172750 | I22: =TRUNC(I13/50)*50 -> 329850 | J22: =TRUNC(J13/50)*50 -> 418850 | K22: =TRUNC(K13/50)*50 -> 628300 | L22: excess | M22: =TRUNC(M13/25)*25 -> 9950 | N22: =TRUNC(N13/25)*25 -> 40525 | O22: =TRUNC(O13/25)*25 -> 86375 | P22: =TRUNC(P13/25)*25 -> 164925 | Q22: =TRUNC(Q13/25)*25 -> 209425 | R22: =TRUNC(R13/25)*25 -> 523600 | S22: excess | T22: =TRUNC(T13/50)*50 -> 14200 | U22: =TRUNC(U13/50)*50 -> 54200 | V22: =TRUNC(V13/50)*50 -> 86350 | W22: =TRUNC(W13/50)*50 -> 164900 | X22: =TRUNC(X13/50)*50 -> 209400 | Y22: =TRUNC(Y13/50)*50 -> 523600 | Z22: excess | AA22: =TRUNC(AA13/25)*25 -> 9950 | AB22: =TRUNC(AB13/25)*25 -> 40525 | AC22: =TRUNC(AC13/25)*25 -> 86375 | AD22: =TRUNC(AD13/25)*25 -> 164925 | AE22: =TRUNC(AE13/25)*25 -> 209425 | AF22: =TRUNC(AF13/25)*25 -> 314150 | AG22: excess | AH22: =TRUNC(AH13/50)*50 -> 2650 | AI22: =AI13 -> unused | AJ22: =AJ13 -> unused | AK22: =TRUNC(AK13/50)*50 -> 9550 | AL22: =AL13 -> unused | AM22: =TRUNC(AM13/50)*50 -> 13050 | AN22: =AN13 -> excess
A23: =A24+1 -> 2020 | F23: =TRUNC(F14/50)*50 -> 19700 | G23: =TRUNC(G14/50)*50 -> 80150 | H23: =TRUNC(H14/50)*50 -> 170850 | I23: =TRUNC(I14/50)*50 -> 326250 | J23: =TRUNC(J14/50)*50 -> 414250 | K23: =TRUNC(K14/50)*50 -> 621400 | L23: excess | M23: =TRUNC(M14/25)*25 -> 9850 | N23: =TRUNC(N14/25)*25 -> 40075 | O23: =TRUNC(O14/25)*25 -> 85425 | P23: =TRUNC(P14/25)*25 -> 163125 | Q23: =TRUNC(Q14/25)*25 -> 207125 | R23: =TRUNC(R14/25)*25 -> 517850 | S23: excess | T23: =TRUNC(T14/50)*50 -> 14050 | U23: =TRUNC(U14/50)*50 -> 53650 | V23: =TRUNC(V14/50)*50 -> 85400 | W23: =TRUNC(W14/50)*50 -> 163100 | X23: =TRUNC(X14/50)*50 -> 207100 | Y23: =TRUNC(Y14/50)*50 -> 517850 | Z23: excess | AA23: =TRUNC(AA14/25)*25 -> 9850 | AB23: =TRUNC(AB14/25)*25 -> 40075 | AC23: =TRUNC(AC14/25)*25 -> 85425 | AD23: =TRUNC(AD14/25)*25 -> 163125 | AE23: =TRUNC(AE14/25)*25 -> 207125 | AF23: =TRUNC(AF14/25)*25 -> 310700 | AG23: excess | AH23: =TRUNC(AH14/50)*50 -> 2600 | AI23: =AI14 -> unused | AJ23: =AJ14 -> unused | AK23: =TRUNC(AK14/50)*50 -> 9450 | AL23: =AL14 -> unused | AM23: =TRUNC(AM14/50)*50 -> 12900 | AN23: =AN14 -> excess
A24: =A25+1 -> 2019 | F24: =TRUNC(F15/50)*50 -> 19400 | G24: =TRUNC(G15/50)*50 -> 78900 | H24: =TRUNC(H15/50)*50 -> 168250 | I24: =TRUNC(I15/50)*50 -> 321250 | J24: =TRUNC(J15/50)*50 -> 407950 | K24: =TRUNC(K15/50)*50 -> 611950 | L24: excess | M24: =TRUNC(M15/25)*25 -> 9700 | N24: =TRUNC(N15/25)*25 -> 39450 | O24: =TRUNC(O15/25)*25 -> 84125 | P24: =TRUNC(P15/25)*25 -> 160625 | Q24: =TRUNC(Q15/25)*25 -> 203975 | R24: =TRUNC(R15/25)*25 -> 509950 | S24: excess | T24: =TRUNC(T15/50)*50 -> 13850 | U24: =TRUNC(U15/50)*50 -> 52800 | V24: =TRUNC(V15/50)*50 -> 84100 | W24: =TRUNC(W15/50)*50 -> 160600 | X24: =TRUNC(X15/50)*50 -> 203950 | Y24: =TRUNC(Y15/50)*50 -> 509950 | Z24: excess | AA24: =TRUNC(AA15/25)*25 -> 9700 | AB24: =TRUNC(AB15/25)*25 -> 39450 | AC24: =TRUNC(AC15/25)*25 -> 84125 | AD24: =TRUNC(AD15/25)*25 -> 160625 | AE24: =TRUNC(AE15/25)*25 -> 203975 | AF24: =TRUNC(AF15/25)*25 -> 305975 | AG24: excess | AH24: =TRUNC(AH15/50)*50 -> 2600 | AI24: =AI15 -> unused | AJ24: =AJ15 -> unused | AK24: =TRUNC(AK15/50)*50 -> 9300 | AL24: =AL15 -> unused | AM24: =TRUNC(AM15/50)*50 -> 12700 | AN24: =AN15 -> excess
A25: 2018 | F25: =TRUNC(F16/50)*50 -> 19050 | G25: =TRUNC(G16/50)*50 -> 77400 | H25: =TRUNC(H16/50)*50 -> 165000 | I25: =TRUNC(I16/50)*50 -> 315000 | J25: =TRUNC(J16/50)*50 -> 400000 | K25: =TRUNC(K16/50)*50 -> 600000 | L25: excess | M25: =TRUNC(M16/25)*25 -> 9525 | N25: =TRUNC(N16/25)*25 -> 38700 | O25: =TRUNC(O16/25)*25 -> 82500 | P25: =TRUNC(P16/25)*25 -> 157500 | Q25: =TRUNC(Q16/25)*25 -> 200000 | R25: =TRUNC(R16/25)*25 -> 500000 | S25: excess | T25: =TRUNC(T16/50)*50 -> 13600 | U25: =TRUNC(U16/50)*50 -> 51800 | V25: =TRUNC(V16/50)*50 -> 82500 | W25: =TRUNC(W16/50)*50 -> 157500 | X25: =TRUNC(X16/50)*50 -> 200000 | Y25: =TRUNC(Y16/50)*50 -> 500000 | Z25: excess | AA25: =TRUNC(AA16/25)*25 -> 9525 | AB25: =TRUNC(AB16/25)*25 -> 38700 | AC25: =TRUNC(AC16/25)*25 -> 82500 | AD25: =TRUNC(AD16/25)*25 -> 157500 | AE25: =TRUNC(AE16/25)*25 -> 200000 | AF25: =TRUNC(AF16/25)*25 -> 300000 | AG25: excess | AH25: =TRUNC(AH16/50)*50 -> 2550 | AI25: =AI16 -> unused | AJ25: =AJ16 -> unused | AK25: =TRUNC(AK16/50)*50 -> 9150 | AL25: =AL16 -> unused | AM25: =AM16 -> 12500 | AN25: =AN16 -> excess
A29: Income Tax Brackets (for 2026 Sunset)
F30: Married Filing Jointly | M30: Single | T30: Head of Household | AA30: Married Filing Separately | AH30: Trusts & Estates
A31: Tax Year | B31: CPI (base year 2013) | C31: CPI (base year 2003) | D31: CPI (base year 1993) | E31: CPI (base year 1994) | F31: 10% Bracket | G31: 15% Bracket | H31: 25% Bracket | I31: 28% Bracket | J31: 33% Bracket | K31: 35% Bracket | L31: 39.6% Bracket | M31: 10% Bracket | N31: 15% Bracket | O31: 25% Bracket | P31: 28% Bracket | Q31: 33% Bracket | R31: 35% Bracket | S31: 39.6% Bracket | T31: 10% Bracket | U31: 15% Bracket | V31: 25% Bracket | W31: 28% Bracket | X31: 33% Bracket | Y31: 35% Bracket | Z31: 39.6% Bracket | AA31: 10% Bracket | AB31: 15% Bracket | AC31: 25% Bracket | AD31: 28% Bracket | AE31: 33% Bracket | AF31: 35% Bracket | AG31: 39.6% Bracket | AH31: 10% Bracket | AI31: 15% Bracket | AJ31: 25% Bracket | AK31: 28% Bracket | AL31: 33% Bracket | AM31: 35% Bracket | AN31: 39.6% Bracket
A32: =A33+1 -> 2022 | B32: ='CPI-U & C-CPI-U Calcs'!$H14 -> 1.1468748 | C32: ='CPI-U & C-CPI-U Calcs'!$L14 -> 1.46444 | D32: ='CPI-U & C-CPI-U Calcs'!$P14 -> 1.8834537 | E32: ='CPI-U & C-CPI-U Calcs'!$O14 -> 1.8275454 | F32: =F$51*$C32 -> 20502.16 | G32: =G$61*$D32 -> 83248.655 | H32: =H$61*$D32 -> 167909.9 | I32: =I$60*$E32 -> 255856.35 | J32: =J$60*$E32 -> 456886.35 | K32: =K$41*$B32 -> 516093.65 | L32: excess | M32: =M$51*$C32 -> 10251.08 | N32: =N$61*$D32 -> 41624.328 | O32: =O$61*$D32 -> 100764.78 | P32: =P$60*$E32 -> 210167.72 | Q32: =Q$60*$E32 -> 456886.35 | R32: =R$41*$B32 -> 458749.91 | S32: excess | T32: =T$51*$C32 -> 14644.4 | U32: =U$61*$D32 -> 55750.231 | V32: =V$61*$D32 -> 143895.87 | W32: =W$60*$E32 -> 233012.04 | X32: =X$60*$E32 -> 456886.35 | Y32: =Y$41*$B32 -> 487421.78 | Z32: excess | AA32: =AA$51*$C32 -> 10251.08 | AB32: =AB$61*$D32 -> 41624.328 | AC32: =AC$61*$D32 -> 83954.951 | AD32: =AD$60*$E32 -> 127928.18 | AE32: =AE$60*$E32 -> 228443.17 | AF32: =AF$41*$B32 -> 258046.82 | AG32: excess | AH32: 0 | AI32: =AI$61*$D32 -> 2825.1806 | AJ32: =AJ$61*$D32 -> 6592.0881 | AK32: =AK$60*$E32 -> 10051.5 | AL32: =AL$60*$E32 -> 13706.59 | AM32: =AM33 -> unused | AN32: excess
A33: =A34+1 -> 2021 | B33: ='CPI-U & C-CPI-U Calcs'!$H15 -> 1.1134707 | C33: ='CPI-U & C-CPI-U Calcs'!$L15 -> 1.4217864 | D33: ='CPI-U & C-CPI-U Calcs'!$P15 -> 1.8285959 | E33: ='CPI-U & C-CPI-U Calcs'!$O15 -> 1.7743159 | F33: =F$51*$C33 -> 19905.009 | G33: =G$61*$D33 -> 80823.937 | H33: =H$61*$D33 -> 163019.32 | I33: =I$60*$E33 -> 248404.23 | J33: =J$60*$E33 -> 443578.98 | K33: =K$41*$B33 -> 501061.8 | L33: excess | M33: =M$51*$C33 -> 9952.5046 | N33: =N$61*$D33 -> 40411.969 | O33: =O$61*$D33 -> 97829.879 | P33: =P$60*$E33 -> 204046.33 | Q33: =Q$60*$E33 -> 443578.98 | R33: =R$41*$B33 -> 445388.26 | S33: excess | T33: =T$51*$C33 -> 14217.864 | U33: =U$61*$D33 -> 54126.438 | V33: =V$61*$D33 -> 139704.72 | W33: =W$60*$E33 -> 226225.28 | X33: =X$60*$E33 -> 443578.98 | Y33: =Y$41*$B33 -> 473225.03 | Z33: excess | AA33: =AA$51*$C33 -> 9952.5046 | AB33: =AB$61*$D33 -> 40411.969 | AC33: =AC$61*$D33 -> 81509.661 | AD33: =AD$60*$E33 -> 124202.11 | AE33: =AE$60*$E33 -> 221789.49 | AF33: =AF$41*$B33 -> 250530.9 | AG33: excess | AH33: 0 | AI33: =AI$61*$D33 -> 2742.8938 | AJ33: =AJ$61*$D33 -> 6400.0855 | AK33: =AK$60*$E33 -> 9758.7375 | AL33: =AL$60*$E33 -> 13307.369 | AM33: =AM34 -> unused | AN33: excess
A34: =A35+1 -> 2020 | B34: ='CPI-U & C-CPI-U Calcs'!$H16 -> 1.1012908 | C34: ='CPI-U & C-CPI-U Calcs'!$L16 -> 1.406234 | D34: ='CPI-U & C-CPI-U Calcs'!$P16 -> 1.8085935 | E34: ='CPI-U & C-CPI-U Calcs'!$O16 -> 1.7549073 | F34: =F$51*$C34 -> 19687.276 | G34: =G$61*$D34 -> 79939.834 | H34: =H$61*$D34 -> 161236.11 | I34: =I$60*$E34 -> 245687.03 | J34: =J$60*$E34 -> 438726.83 | K34: =K$41*$B34 -> 495580.86 | L34: excess | M34: =M$51*$C34 -> 9843.6379 | N34: =N$61*$D34 -> 39969.917 | O34: =O$61*$D34 -> 96759.754 | P34: =P$60*$E34 -> 201814.34 | Q34: =Q$60*$E34 -> 438726.83 | R34: =R$41*$B34 -> 440516.32 | S34: excess | T34: =T$51*$C34 -> 14062.34 | U34: =U$61*$D34 -> 53534.368 | V34: =V$61*$D34 -> 138176.55 | W34: =W$60*$E34 -> 223750.68 | X34: =X$60*$E34 -> 438726.83 | Y34: =Y$41*$B34 -> 468048.59 | Z34: excess | AA34: =AA$51*$C34 -> 9843.6379 | AB34: =AB$61*$D34 -> 39969.917 | AC34: =AC$61*$D34 -> 80618.057 | AD34: =AD$60*$E34 -> 122843.51 | AE34: =AE$60*$E34 -> 219363.42 | AF34: =AF$41*$B34 -> 247790.43 | AG34: excess | AH34: 0 | AI34: =AI$61*$D34 -> 2712.8903 | AJ34: =AJ$61*$D34 -> 6330.0774 | AK34: =AK$60*$E34 -> 9651.9903 | AL34: =AL$60*$E34 -> 13161.805 | AM34: =AM35 -> unused | AN34: excess
A35: =A36+1 -> 2019 | B35: ='CPI-U & C-CPI-U Calcs'!$H17 -> 1.0844709 | C35: ='CPI-U & C-CPI-U Calcs'!$L17 -> 1.3847567 | D35: ='CPI-U & C-CPI-U Calcs'!$P17 -> 1.7809711 | E35: ='CPI-U & C-CPI-U Calcs'!$O17 -> 1.7281048 | F35: =F$51*$C35 -> 19386.594 | G35: =G$61*$D35 -> 78718.923 | H35: =H$61*$D35 -> 158773.57 | I35: =I$60*$E35 -> 241934.68 | J35: =J$60*$E35 -> 432026.21 | K35: =K$41*$B35 -> 488011.92 | L35: excess | M35: =M$51*$C35 -> 9693.2972 | N35: =N$61*$D35 -> 39359.461 | O35: =O$61*$D35 -> 95281.954 | P35: =P$60*$E35 -> 198732.06 | Q35: =Q$60*$E35 -> 432026.21 | R35: =R$41*$B35 -> 433788.37 | S35: excess | T35: =T$51*$C35 -> 13847.567 | U35: =U$61*$D35 -> 52716.745 | V35: =V$61*$D35 -> 136066.19 | W35: =W$60*$E35 -> 220333.37 | X35: =X$60*$E35 -> 432026.21 | Y35: =Y$41*$B35 -> 460900.15 | Z35: excess | AA35: =AA$51*$C35 -> 9693.2972 | AB35: =AB$61*$D35 -> 39359.461 | AC35: =AC$61*$D35 -> 79386.787 | AD35: =AD$60*$E35 -> 120967.34 | AE35: =AE$60*$E35 -> 216013.11 | AF35: =AF$41*$B35 -> 244005.96 | AG35: excess | AH35: 0 | AI35: =AI$61*$D35 -> 2671.4567 | AJ35: =AJ$61*$D35 -> 6233.3989 | AK35: =AK$60*$E35 -> 9504.5766 | AL35: =AL$60*$E35 -> 12960.786 | AM35: =AM36 -> unused | AN35: excess
A36: =A37+1 -> 2018 | B36: ='CPI-U & C-CPI-U Calcs'!$H18 -> 1.063279 | C36: ='CPI-U & C-CPI-U Calcs'!$L18 -> 1.3576968 | D36: ='CPI-U & C-CPI-U Calcs'!$P18 -> 1.7461686 | E36: ='CPI-U & C-CPI-U Calcs'!$O18 -> 1.6943354 | F36: =F$51*$C36 -> 19007.755 | G36: =G$61*$D36 -> 77180.652 | H36: =H$61*$D36 -> 155670.93 | I36: =I$60*$E36 -> 237206.96 | J36: =J$60*$E36 -> 423583.85 | K36: =K$41*$B36 -> 478475.53 | L36: excess | M36: =M$51*$C36 -> 9503.8775 | N36: =N$61*$D36 -> 38590.326 | O36: =O$61*$D36 -> 93420.02 | P36: =P$60*$E36 -> 194848.57 | Q36: =Q$60*$E36 -> 423583.85 | R36: =R$41*$B36 -> 425311.58 | S36: excess | T36: =T$51*$C36 -> 13576.968 | U36: =U$61*$D36 -> 51686.59 | V36: =V$61*$D36 -> 133407.28 | W36: =W$60*$E36 -> 216027.76 | X36: =X$60*$E36 -> 423583.85 | Y36: =Y$41*$B36 -> 451893.55 | Z36: excess | AA36: =AA$51*$C36 -> 9503.8775 | AB36: =AB$61*$D36 -> 38590.326 | AC36: =AC$61*$D36 -> 77835.465 | AD36: =AD$60*$E36 -> 118603.48 | AE36: =AE$60*$E36 -> 211791.93 | AF36: =AF$41*$B36 -> 239237.76 | AG36: excess | AH36: 0 | AI36: =AI$61*$D36 -> 2619.2529 | AJ36: =AJ$61*$D36 -> 6111.5901 | AK36: =AK$60*$E36 -> 9318.8448 | AL36: =AL$60*$E36 -> 12707.516 | AM36: =AM37 -> unused | AN36: excess
A37: =A38+1 -> 2017 | B37: ='CPI-U & C-CPI-U Calcs'!$H19 -> 1.0460206 | C37: ='CPI-U & C-CPI-U Calcs'!$L19 -> 1.3356597 | D37: ='CPI-U & C-CPI-U Calcs'!$P19 -> 1.7178262 | E37: ='CPI-U & C-CPI-U Calcs'!$O19 -> 1.6668343 | F37: =F$51*$C37 -> 18699.236 | G37: =G$61*$D37 -> 75927.917 | H37: =H$61*$D37 -> 153144.2 | I37: =I$60*$E37 -> 233356.8 | J37: =J$60*$E37 -> 416708.57 | K37: =K$41*$B37 -> 470709.29 | L37: excess | M37: =M$51*$C37 -> 9349.618 | N37: =N$61*$D37 -> 37963.958 | O37: =O$61*$D37 -> 91903.7 | P37: =P$60*$E37 -> 191685.94 | Q37: =Q$60*$E37 -> 416708.57 | R37: =R$41*$B37 -> 418408.26 | S37: excess | T37: =T$51*$C37 -> 13356.597 | U37: =U$61*$D37 -> 50847.654 | V37: =V$61*$D37 -> 131241.92 | W37: =W$60*$E37 -> 212521.37 | X37: =X$60*$E37 -> 416708.57 | Y37: =Y$41*$B37 -> 444558.77 | Z37: excess | AA37: =AA$51*$C37 -> 9349.618 | AB37: =AB$61*$D37 -> 37963.958 | AC37: =AC$61*$D37 -> 76572.101 | AD37: =AD$60*$E37 -> 116678.4 | AE37: =AE$60*$E37 -> 208354.29 | AF37: =AF$41*$B37 -> 235354.65 | AG37: excess | AH37: 0 | AI37: =AI$61*$D37 -> 2576.7392 | AJ37: =AJ$61*$D37 -> 6012.3916 | AK37: =AK$60*$E37 -> 9167.5886 | AL37: =AL$60*$E37 -> 12501.257 | AM37: =AM38 -> unused | AN37: excess
A38: =A39+1 -> 2016 | B38: ='CPI-U & C-CPI-U Calcs'!$H20 -> 1.0376924 | C38: ='CPI-U & C-CPI-U Calcs'!$L20 -> 1.3250254 | D38: ='CPI-U & C-CPI-U Calcs'!$P20 -> 1.7041491 | E38: ='CPI-U & C-CPI-U Calcs'!$O20 -> 1.6535632 | F38: =F$51*$C38 -> 18550.356 | G38: =G$61*$D38 -> 75323.391 | H38: =H$61*$D38 -> 151924.89 | I38: =I$60*$E38 -> 231498.85 | J38: =J$60*$E38 -> 413390.81 | K38: =K$41*$B38 -> 466961.58 | L38: excess | M38: =M$51*$C38 -> 9275.1779 | N38: =N$61*$D38 -> 37661.696 | O38: =O$61*$D38 -> 91171.978 | P38: =P$60*$E38 -> 190159.77 | Q38: =Q$60*$E38 -> 413390.81 | R38: =R$41*$B38 -> 415076.96 | S38: excess | T38: =T$51*$C38 -> 13250.254 | U38: =U$61*$D38 -> 50442.814 | V38: =V$61*$D38 -> 130196.99 | W38: =W$60*$E38 -> 210829.31 | X38: =X$60*$E38 -> 413390.81 | Y38: =Y$41*$B38 -> 441019.27 | Z38: excess | AA38: =AA$51*$C38 -> 9275.1779 | AB38: =AB$61*$D38 -> 37661.696 | AC38: =AC$61*$D38 -> 75962.447 | AD38: =AD$60*$E38 -> 115749.43 | AE38: =AE$60*$E38 -> 206695.4 | AF38: =AF$41*$B38 -> 233480.79 | AG38: excess | AH38: 0 | AI38: =AI$61*$D38 -> 2556.2237 | AJ38: =AJ$61*$D38 -> 5964.5219 | AK38: =AK$60*$E38 -> 9094.5978 | AL38: =AL$60*$E38 -> 12401.724 | AM38: =AM39 -> unused | AN38: excess
A39: =A40+1 -> 2015 | B39: ='CPI-U & C-CPI-U Calcs'!$H21 -> 1.0330292 | C39: ='CPI-U & C-CPI-U Calcs'!$L21 -> 1.3190709 | D39: ='CPI-U & C-CPI-U Calcs'!$P21 -> 1.6964909 | E39: ='CPI-U & C-CPI-U Calcs'!$O21 -> 1.6461324 | F39: =F$51*$C39 -> 18466.993 | G39: =G$61*$D39 -> 74984.898 | H39: =H$61*$D39 -> 151242.16 | I39: =I$60*$E39 -> 230458.53 | J39: =J$60*$E39 -> 411533.09 | K39: =K$41*$B39 -> 464863.12 | L39: excess | M39: =M$51*$C39 -> 9233.4966 | N39: =N$61*$D39 -> 37492.449 | O39: =O$61*$D39 -> 90762.264 | P39: =P$60*$E39 -> 189305.22 | Q39: =Q$60*$E39 -> 411533.09 | R39: =R$41*$B39 -> 413211.66 | S39: excess | T39: =T$51*$C39 -> 13190.709 | U39: =U$61*$D39 -> 50216.131 | V39: =V$61*$D39 -> 129611.91 | W39: =W$60*$E39 -> 209881.88 | X39: =X$60*$E39 -> 411533.09 | Y39: =Y$41*$B39 -> 439037.39 | Z39: excess | AA39: =AA$51*$C39 -> 9233.4966 | AB39: =AB$61*$D39 -> 37492.449 | AC39: =AC$61*$D39 -> 75621.082 | AD39: =AD$60*$E39 -> 115229.26 | AE39: =AE$60*$E39 -> 205766.54 | AF39: =AF$41*$B39 -> 232431.56 | AG39: excess | AH39: 0 | AI39: =AI$61*$D39 -> 2544.7364 | AJ39: =AJ$61*$D39 -> 5937.7182 | AK39: =AK$60*$E39 -> 9053.728 | AL39: =AL$60*$E39 -> 12345.993 | AM39: =AM40 -> unused | AN39: excess
A40: =A41+1 -> 2014 | B40: ='CPI-U & C-CPI-U Calcs'!$H22 -> 1.0169571 | C40: ='CPI-U & C-CPI-U Calcs'!$L22 -> 1.2985486 | D40: ='CPI-U & C-CPI-U Calcs'!$P22 -> 1.6700966 | E40: ='CPI-U & C-CPI-U Calcs'!$O22 -> 1.6205215 | F40: =F$51*$C40 -> 18179.68 | G40: =G$61*$D40 -> 73818.269 | H40: =H$61*$D40 -> 148889.11 | I40: =I$60*$E40 -> 226873.01 | J40: =J$60*$E40 -> 405130.38 | K40: =K$41*$B40 -> 457630.69 | L40: excess | M40: =M$51*$C40 -> 9089.84 | N40: =N$61*$D40 -> 36909.134 | O40: =O$61*$D40 -> 89350.167 | P40: =P$60*$E40 -> 186359.97 | Q40: =Q$60*$E40 -> 405130.38 | R40: =R$41*$B40 -> 406782.84 | S40: excess | T40: =T$51*$C40 -> 12985.486 | U40: =U$61*$D40 -> 49434.859 | V40: =V$61*$D40 -> 127595.38 | W40: =W$60*$E40 -> 206616.49 | X40: =X$60*$E40 -> 405130.38 | Y40: =Y$41*$B40 -> 432206.76 | Z40: excess | AA40: =AA$51*$C40 -> 9089.84 | AB40: =AB$61*$D40 -> 36909.134 | AC40: =AC$61*$D40 -> 74444.555 | AD40: =AD$60*$E40 -> 113436.51 | AE40: =AE$60*$E40 -> 202565.19 | AF40: =AF$41*$B40 -> 228815.35 | AG40: excess | AH40: 0 | AI40: =AI$61*$D40 -> 2505.1449 | AJ40: =AJ$61*$D40 -> 5845.338 | AK40: =AK$60*$E40 -> 8912.8683 | AL40: =AL$60*$E40 -> 12153.911 | AM40: =AM41 -> unused | AN40: excess
A41: =A42+1 -> 2013 | B41: ='CPI-U & C-CPI-U Calcs'!$H23 -> 1 | C41: ='CPI-U & C-CPI-U Calcs'!$L23 -> 1.2768961 | D41: ='CPI-U & C-CPI-U Calcs'!$P23 -> 1.6422488 | E41: ='CPI-U & C-CPI-U Calcs'!$O23 -> 1.5935004 | F41: =F$51*$C41 -> 17876.546 | G41: =G$61*$D41 -> 72587.398 | H41: =H$61*$D41 -> 146406.48 | I41: =I$60*$E41 -> 223090.05 | J41: =J$60*$E41 -> 398375.09 | K41: 450000 | L41: excess | M41: =M$51*$C41 -> 8938.2729 | N41: =N$61*$D41 -> 36293.699 | O41: =O$61*$D41 -> 87860.312 | P41: =P$60*$E41 -> 183252.54 | Q41: =Q$60*$E41 -> 398375.09 | R41: 400000 | S41: excess | T41: =T$51*$C41 -> 12768.961 | U41: =U$61*$D41 -> 48610.565 | V41: =V$61*$D41 -> 125467.81 | W41: =W$60*$E41 -> 203171.3 | X41: =X$60*$E41 -> 398375.09 | Y41: 425000 | Z41: excess | AA41: =AA$51*$C41 -> 8938.2729 | AB41: =AB$61*$D41 -> 36293.699 | AC41: =AC$61*$D41 -> 73203.241 | AD41: =AD$60*$E41 -> 111545.03 | AE41: =AE$60*$E41 -> 199187.55 | AF41: 225000 | AG41: excess | AH41: 0 | AI41: =AI$61*$D41 -> 2463.3732 | AJ41: =AJ$61*$D41 -> 5747.8709 | AK41: =AK$60*$E41 -> 8764.2521 | AL41: =AL$60*$E41 -> 11951.253 | AM41: unused | AN41: excess
A42: =A43+1 -> 2012 | C42: ='CPI-U & C-CPI-U Calcs'!$L24 -> 1.2449 | D42: ='CPI-U & C-CPI-U Calcs'!$P24 -> 1.6010977 | E42: ='CPI-U & C-CPI-U Calcs'!$O24 -> 1.5535708 | F42: =F$51*$C42 -> 17428.599 | G42: =G$61*$D42 -> 70768.519 | H42: =H$61*$D42 -> 142737.86 | I42: =I$60*$E42 -> 217499.91 | J42: =J$60*$E42 -> 388392.7 | L42: excess | M42: =M$51*$C42 -> 8714.2997 | N42: =N$61*$D42 -> 35384.259 | O42: =O$61*$D42 -> 85658.728 | P42: =P$60*$E42 -> 178660.64 | Q42: =Q$60*$E42 -> 388392.7 | S42: excess | T42: =T$51*$C42 -> 12449 | U42: =U$61*$D42 -> 47392.492 | V42: =V$61*$D42 -> 122323.87 | W42: =W$60*$E42 -> 198080.28 | X42: =X$60*$E42 -> 388392.7 | Z42: excess | AA42: =AA$51*$C42 -> 8714.2997 | AB42: =AB$61*$D42 -> 35384.259 | AC42: =AC$61*$D42 -> 71368.931 | AD42: =AD$60*$E42 -> 108749.96 | AE42: =AE$60*$E42 -> 194196.35 | AG42: excess | AH42: 0 | AI42: =AI$61*$D42 -> 2401.6466 | AJ42: =AJ$61*$D42 -> 5603.842 | AK42: =AK$60*$E42 -> 8544.6394 | AL42: =AL$60*$E42 -> 11651.781
A43: =A44+1 -> 2011 | C43: ='CPI-U & C-CPI-U Calcs'!$L25 -> 1.2154093 | D43: ='CPI-U & C-CPI-U Calcs'!$P25 -> 1.563169 | E43: ='CPI-U & C-CPI-U Calcs'!$O25 -> 1.5167679 | F43: =F$51*$C43 -> 17015.73 | G43: =G$61*$D43 -> 69092.069 | H43: =H$61*$D43 -> 139356.51 | I43: =I$60*$E43 -> 212347.51 | J43: =J$60*$E43 -> 379191.99 | L43: excess | M43: =M$51*$C43 -> 8507.8648 | N43: =N$61*$D43 -> 34546.034 | O43: =O$61*$D43 -> 83629.54 | P43: =P$60*$E43 -> 174428.31 | Q43: =Q$60*$E43 -> 379191.99 | S43: excess | T43: =T$51*$C43 -> 12154.093 | U43: =U$61*$D43 -> 46269.802 | V43: =V$61*$D43 -> 119426.11 | W43: =W$60*$E43 -> 193387.91 | X43: =X$60*$E43 -> 379191.99 | Z43: excess | AA43: =AA$51*$C43 -> 8507.8648 | AB43: =AB$61*$D43 -> 34546.034 | AC43: =AC$61*$D43 -> 69678.257 | AD43: =AD$60*$E43 -> 106173.76 | AE43: =AE$60*$E43 -> 189595.99 | AG43: excess | AH43: 0 | AI43: =AI$61*$D43 -> 2344.7535 | AJ43: =AJ$61*$D43 -> 5471.0914 | AK43: =AK$60*$E43 -> 8342.2237 | AL43: =AL$60*$E43 -> 11375.76
A44: =A45+1 -> 2010 | C44: ='CPI-U & C-CPI-U Calcs'!$L26 -> 1.1977184 | D44: ='CPI-U & C-CPI-U Calcs'!$P26 -> 1.5404163 | E44: ='CPI-U & C-CPI-U Calcs'!$O26 -> 1.4946906 | F44: =F$51*$C44 -> 16768.057 | G44: =G$61*$D44 -> 68086.4 | H44: =H$61*$D44 -> 137328.11 | I44: =I$60*$E44 -> 209256.69 | J44: =J$60*$E44 -> 373672.66 | L44: excess | M44: =M$51*$C44 -> 8384.0287 | N44: =N$61*$D44 -> 34043.2 | O44: =O$61*$D44 -> 82412.272 | P44: =P$60*$E44 -> 171889.42 | Q44: =Q$60*$E44 -> 373672.66 | S44: excess | T44: =T$51*$C44 -> 11977.184 | U44: =U$61*$D44 -> 45596.322 | V44: =V$61*$D44 -> 117687.8 | W44: =W$60*$E44 -> 190573.06 | X44: =X$60*$E44 -> 373672.66 | Z44: excess | AA44: =AA$51*$C44 -> 8384.0287 | AB44: =AB$61*$D44 -> 34043.2 | AC44: =AC$61*$D44 -> 68664.056 | AD44: =AD$60*$E44 -> 104628.35 | AE44: =AE$60*$E44 -> 186836.33 | AG44: excess | AH44: 0 | AI44: =AI$61*$D44 -> 2310.6244 | AJ44: =AJ$61*$D44 -> 5391.457 | AK44: =AK$60*$E44 -> 8220.7986 | AL44: =AL$60*$E44 -> 11210.18
A45: =A46+1 -> 2009 | C45: ='CPI-U & C-CPI-U Calcs'!$L27 -> 1.1954946 | D45: ='CPI-U & C-CPI-U Calcs'!$P27 -> 1.5375562 | E45: ='CPI-U & C-CPI-U Calcs'!$O27 -> 1.4919155 | F45: =F$51*$C45 -> 16736.925 | G45: =G$61*$D45 -> 67959.986 | H45: =H$61*$D45 -> 137073.14 | I45: =I$60*$E45 -> 208868.17 | J45: =J$60*$E45 -> 372978.87 | L45: excess | M45: =M$51*$C45 -> 8368.4623 | N45: =N$61*$D45 -> 33979.993 | O45: =O$61*$D45 -> 82259.259 | P45: =P$60*$E45 -> 171570.28 | Q45: =Q$60*$E45 -> 372978.87 | S45: excess | T45: =T$51*$C45 -> 11954.946 | U45: =U$61*$D45 -> 45511.665 | V45: =V$61*$D45 -> 117469.3 | W45: =W$60*$E45 -> 190219.22 | X45: =X$60*$E45 -> 372978.87 | Z45: excess | AA45: =AA$51*$C45 -> 8368.4623 | AB45: =AB$61*$D45 -> 33979.993 | AC45: =AC$61*$D45 -> 68536.569 | AD45: =AD$60*$E45 -> 104434.08 | AE45: =AE$60*$E45 -> 186489.44 | AG45: excess | AH45: 0 | AI45: =AI$61*$D45 -> 2306.3344 | AJ45: =AJ$61*$D45 -> 5381.4468 | AK45: =AK$60*$E45 -> 8205.5352 | AL45: =AL$60*$E45 -> 11189.366
A46: =A47+1 -> 2008 | C46: ='CPI-U & C-CPI-U Calcs'!$L28 -> 1.146621 | D46: ='CPI-U & C-CPI-U Calcs'!$P28 -> 1.4746986 | E46: ='CPI-U & C-CPI-U Calcs'!$O28 -> 1.4309237 | F46: =F$51*$C46 -> 16052.693 | G46: =G$61*$D46 -> 65181.677 | H46: =H$61*$D46 -> 131469.38 | I46: =I$60*$E46 -> 200329.32 | J46: =J$60*$E46 -> 357730.92 | L46: excess | M46: =M$51*$C46 -> 8026.3467 | N46: =N$61*$D46 -> 32590.839 | O46: =O$61*$D46 -> 78896.374 | P46: =P$60*$E46 -> 164556.22 | Q46: =Q$60*$E46 -> 357730.92 | S46: excess | T46: =T$51*$C46 -> 11466.21 | U46: =U$61*$D46 -> 43651.078 | V46: =V$61*$D46 -> 112666.97 | W46: =W$60*$E46 -> 182442.77 | X46: =X$60*$E46 -> 357730.92 | Z46: excess | AA46: =AA$51*$C46 -> 8026.3467 | AB46: =AB$61*$D46 -> 32590.839 | AC46: =AC$61*$D46 -> 65734.689 | AD46: =AD$60*$E46 -> 100164.66 | AE46: =AE$60*$E46 -> 178865.46 | AG46: excess | AH46: 0 | AI46: =AI$61*$D46 -> 2212.0479 | AJ46: =AJ$61*$D46 -> 5161.445 | AK46: =AK$60*$E46 -> 7870.0803 | AL46: =AL$60*$E46 -> 10731.928
A47: =A48+1 -> 2007 | C47: ='CPI-U & C-CPI-U Calcs'!$L29 -> 1.1209832 | D47: ='CPI-U & C-CPI-U Calcs'!$P29 -> 1.4417252 | E47: ='CPI-U & C-CPI-U Calcs'!$O29 -> 1.398929 | F47: =F$51*$C47 -> 15693.764 | G47: =G$61*$D47 -> 63724.252 | H47: =H$61*$D47 -> 128529.8 | I47: =I$60*$E47 -> 195850.07 | J47: =J$60*$E47 -> 349732.26 | L47: excess | M47: =M$51*$C47 -> 7846.8821 | N47: =N$61*$D47 -> 31862.126 | O47: =O$61*$D47 -> 77132.296 | P47: =P$60*$E47 -> 160876.84 | Q47: =Q$60*$E47 -> 349732.26 | S47: excess | T47: =T$51*$C47 -> 11209.832 | U47: =U$61*$D47 -> 42675.064 | V47: =V$61*$D47 -> 110147.8 | W47: =W$60*$E47 -> 178363.45 | X47: =X$60*$E47 -> 349732.26 | Z47: excess | AA47: =AA$51*$C47 -> 7846.8821 | AB47: =AB$61*$D47 -> 31862.126 | AC47: =AC$61*$D47 -> 64264.899 | AD47: =AD$60*$E47 -> 97925.033 | AE47: =AE$60*$E47 -> 174866.13 | AG47: excess | AH47: 0 | AI47: =AI$61*$D47 -> 2162.5877 | AJ47: =AJ$61*$D47 -> 5046.038 | AK47: =AK$60*$E47 -> 7694.1098 | AL47: =AL$60*$E47 -> 10491.968
A48: =A49+1 -> 2006 | C48: ='CPI-U & C-CPI-U Calcs'!$L30 -> 1.0788676 | D48: ='CPI-U & C-CPI-U Calcs'!$P30 -> 1.3875592 | E48: ='CPI-U & C-CPI-U Calcs'!$O30 -> 1.346371 | F48: =F$51*$C48 -> 15104.146 | G48: =G$61*$D48 -> 61330.118 | H48: =H$61*$D48 -> 123700.91 | I48: =I$60*$E48 -> 188491.94 | J48: =J$60*$E48 -> 336592.75 | L48: excess | M48: =M$51*$C48 -> 7552.0731 | N48: =N$61*$D48 -> 30665.059 | O48: =O$61*$D48 -> 74234.419 | P48: =P$60*$E48 -> 154832.66 | Q48: =Q$60*$E48 -> 336592.75 | S48: excess | T48: =T$51*$C48 -> 10788.676 | U48: =U$61*$D48 -> 41071.753 | V48: =V$61*$D48 -> 106009.53 | W48: =W$60*$E48 -> 171662.3 | X48: =X$60*$E48 -> 336592.75 | Z48: excess | AA48: =AA$51*$C48 -> 7552.0731 | AB48: =AB$61*$D48 -> 30665.059 | AC48: =AC$61*$D48 -> 61850.453 | AD48: =AD$60*$E48 -> 94245.969 | AE48: =AE$60*$E48 -> 168296.37 | AG48: excess | AH48: 0 | AI48: =AI$61*$D48 -> 2081.3389 | AJ48: =AJ$61*$D48 -> 4856.4573 | AK48: =AK$60*$E48 -> 7405.0405 | AL48: =AL$60*$E48 -> 10097.782
A49: =A50+1 -> 2005 | C49: ='CPI-U & C-CPI-U Calcs'!$L31 -> 1.0463598 | D49: ='CPI-U & C-CPI-U Calcs'!$P31 -> 1.3457501 | E49: ='CPI-U & C-CPI-U Calcs'!$O31 -> 1.3058029 | F49: =F$51*$C49 -> 14649.037 | G49: =G$61*$D49 -> 59482.155 | H49: =H$61*$D49 -> 119973.62 | I49: =I$60*$E49 -> 182812.41 | J49: =J$60*$E49 -> 326450.73 | L49: excess | M49: =M$51*$C49 -> 7324.5184 | N49: =N$61*$D49 -> 29741.077 | O49: =O$61*$D49 -> 71997.631 | P49: =P$60*$E49 -> 150167.34 | Q49: =Q$60*$E49 -> 326450.73 | S49: excess | T49: =T$51*$C49 -> 10463.598 | U49: =U$61*$D49 -> 39834.203 | V49: =V$61*$D49 -> 102815.31 | W49: =W$60*$E49 -> 166489.87 | X49: =X$60*$E49 -> 326450.73 | Z49: excess | AA49: =AA$51*$C49 -> 7324.5184 | AB49: =AB$61*$D49 -> 29741.077 | AC49: =AC$61*$D49 -> 59986.811 | AD49: =AD$60*$E49 -> 91406.205 | AE49: =AE$60*$E49 -> 163225.37 | AG49: excess | AH49: 0 | AI49: =AI$61*$D49 -> 2018.6252 | AJ49: =AJ$61*$D49 -> 4710.1254 | AK49: =AK$60*$E49 -> 7181.9161 | AL49: =AL$60*$E49 -> 9793.5219
A50: =A51+1 -> 2004 | C50: ='CPI-U & C-CPI-U Calcs'!$L32 -> 1.0228068 | D50: ='CPI-U & C-CPI-U Calcs'!$P32 -> 1.315458 | E50: ='CPI-U & C-CPI-U Calcs'!$O32 -> 1.27641 | F50: =F$51*$C50 -> 14319.295 | G50: =G$61*$D50 -> 58143.243 | H50: =H$61*$D50 -> 117273.08 | I50: =I$60*$E50 -> 178697.4 | J50: =J$60*$E50 -> 319102.5 | L50: excess | M50: =M$51*$C50 -> 7159.6474 | N50: =N$61*$D50 -> 29071.621 | O50: =O$61*$D50 -> 70377.002 | P50: =P$60*$E50 -> 146787.15 | Q50: =Q$60*$E50 -> 319102.5 | S50: excess | T50: =T$51*$C50 -> 10228.068 | U50: =U$61*$D50 -> 38937.556 | V50: =V$61*$D50 -> 100500.99 | W50: =W$60*$E50 -> 162742.27 | X50: =X$60*$E50 -> 319102.5 | Z50: excess | AA50: =AA$51*$C50 -> 7159.6474 | AB50: =AB$61*$D50 -> 29071.621 | AC50: =AC$61*$D50 -> 58636.539 | AD50: =AD$60*$E50 -> 89348.699 | AE50: =AE$60*$E50 -> 159551.25 | AG50: excess | AH50: 0 | AI50: =AI$61*$D50 -> 1973.187 | AJ50: =AJ$61*$D50 -> 4604.1029 | AK50: =AK$60*$E50 -> 7020.2549 | AL50: =AL$60*$E50 -> 9573.0749
A51: =A52+1 -> 2003 | C51: ='CPI-U & C-CPI-U Calcs'!$L33 -> 1 | D51: ='CPI-U & C-CPI-U Calcs'!$P33 -> 1.2861256 | E51: ='CPI-U & C-CPI-U Calcs'!$O33 -> 1.2479483 | F51: 14000 | G51: =G$61*$D51 -> 56846.752 | H51: =H$61*$D51 -> 114658.1 | I51: =I$60*$E51 -> 174712.76 | J51: =J$60*$E51 -> 311987.08 | L51: excess | M51: 7000 | N51: =N$61*$D51 -> 28423.376 | O51: =O$61*$D51 -> 68807.72 | P51: =P$60*$E51 -> 143514.06 | Q51: =Q$60*$E51 -> 311987.08 | S51: excess | T51: 10000 | U51: =U$61*$D51 -> 38069.318 | V51: =V$61*$D51 -> 98259.996 | W51: =W$60*$E51 -> 159113.41 | X51: =X$60*$E51 -> 311987.08 | Z51: excess | AA51: 7000 | AB51: =AB$61*$D51 -> 28423.376 | AC51: =AC$61*$D51 -> 57329.049 | AD51: =AD$60*$E51 -> 87356.382 | AE51: =AE$60*$E51 -> 155993.54 | AG51: excess | AH51: 0 | AI51: =AI$61*$D51 -> 1929.1884 | AJ51: =AJ$61*$D51 -> 4501.4396 | AK51: =AK$60*$E51 -> 6863.7157 | AL51: =AL$60*$E51 -> 9359.6124
A52: =A53+1 -> 2002 | D52: ='CPI-U & C-CPI-U Calcs'!$P34 -> 1.2659708 | E52: ='CPI-U & C-CPI-U Calcs'!$O34 -> 1.2283918 | G52: =G$61*$D52 -> 55955.911 | H52: =H$61*$D52 -> 112861.3 | I52: =I$60*$E52 -> 171974.86 | J52: =J$60*$E52 -> 307097.96 | L52: excess | N52: =N$61*$D52 -> 27977.956 | O52: =O$61*$D52 -> 67729.44 | P52: =P$60*$E52 -> 141265.06 | Q52: =Q$60*$E52 -> 307097.96 | S52: excess | U52: =U$61*$D52 -> 37472.737 | V52: =V$61*$D52 -> 96720.173 | W52: =W$60*$E52 -> 156619.96 | X52: =X$60*$E52 -> 307097.96 | Z52: excess | AB52: =AB$61*$D52 -> 27977.956 | AC52: =AC$61*$D52 -> 56430.651 | AD52: =AD$60*$E52 -> 85987.428 | AE52: =AE$60*$E52 -> 153548.98 | AG52: excess | AI52: =AI$61*$D52 -> 1898.9563 | AJ52: =AJ$61*$D52 -> 4430.898 | AK52: =AK$60*$E52 -> 6756.1551 | AL52: =AL$60*$E52 -> 9212.9387
A53: =A54+1 -> 2001 | D53: ='CPI-U & C-CPI-U Calcs'!$P35 -> 1.2256613 | E53: ='CPI-U & C-CPI-U Calcs'!$O35 -> 1.1892789 | G53: =G$61*$D53 -> 54174.231 | H53: =H$61*$D53 -> 109267.71 | I53: =I$60*$E53 -> 166499.04 | J53: =J$60*$E53 -> 297319.71 | L53: excess | N53: =N$61*$D53 -> 27087.115 | O53: =O$61*$D53 -> 65572.881 | P53: =P$60*$E53 -> 136767.07 | Q53: =Q$60*$E53 -> 297319.71 | S53: excess | U53: =U$61*$D53 -> 36279.575 | V53: =V$61*$D53 -> 93640.525 | W53: =W$60*$E53 -> 151633.05 | X53: =X$60*$E53 -> 297319.71 | Z53: excess | AB53: =AB$61*$D53 -> 27087.115 | AC53: =AC$61*$D53 -> 54633.854 | AD53: =AD$60*$E53 -> 83249.52 | AE53: =AE$60*$E53 -> 148659.86 | AG53: excess | AI53: =AI$61*$D53 -> 1838.492 | AJ53: =AJ$61*$D53 -> 4289.8146 | AK53: =AK$60*$E53 -> 6541.0337 | AL53: =AL$60*$E53 -> 8919.5914
A54: =A55+1 -> 2000 | D54: ='CPI-U & C-CPI-U Calcs'!$P36 -> 1.1887109 | E54: ='CPI-U & C-CPI-U Calcs'!$O36 -> 1.1534253 | G54: =G$61*$D54 -> 52541.023 | H54: =H$61*$D54 -> 105973.58 | I54: =I$60*$E54 -> 161479.54 | J54: =J$60*$E54 -> 288356.32 | L54: excess | N54: =N$61*$D54 -> 26270.512 | O54: =O$61*$D54 -> 63596.035 | P54: =P$60*$E54 -> 132643.91 | Q54: =Q$60*$E54 -> 288356.32 | S54: excess | U54: =U$61*$D54 -> 35185.844 | V54: =V$61*$D54 -> 90817.515 | W54: =W$60*$E54 -> 147061.73 | X54: =X$60*$E54 -> 288356.32 | Z54: excess | AB54: =AB$61*$D54 -> 26270.512 | AC54: =AC$61*$D54 -> 52986.79 | AD54: =AD$60*$E54 -> 80739.771 | AE54: =AE$60*$E54 -> 144178.16 | AG54: excess | AI54: =AI$61*$D54 -> 1783.0664 | AJ54: =AJ$61*$D54 -> 4160.4883 | AK54: =AK$60*$E54 -> 6343.8391 | AL54: =AL$60*$E54 -> 8650.6897
A55: =A56+1 -> 1999 | D55: ='CPI-U & C-CPI-U Calcs'!$P37 -> 1.1674165 | E55: ='CPI-U & C-CPI-U Calcs'!$O37 -> 1.1327629 | G55: =G$61*$D55 -> 51599.808 | H55: =H$61*$D55 -> 104075.18 | I55: =I$60*$E55 -> 158586.81 | J55: =J$60*$E55 -> 283190.73 | L55: excess | N55: =N$61*$D55 -> 25799.904 | O55: =O$61*$D55 -> 62456.781 | P55: =P$60*$E55 -> 130267.74 | Q55: =Q$60*$E55 -> 283190.73 | S55: excess | U55: =U$61*$D55 -> 34555.528 | V55: =V$61*$D55 -> 89190.618 | W55: =W$60*$E55 -> 144427.27 | X55: =X$60*$E55 -> 283190.73 | Z55: excess | AB55: =AB$61*$D55 -> 25799.904 | AC55: =AC$61*$D55 -> 52037.589 | AD55: =AD$60*$E55 -> 79293.406 | AE55: =AE$60*$E55 -> 141595.37 | AG55: excess | AI55: =AI$61*$D55 -> 1751.1247 | AJ55: =AJ$61*$D55 -> 4085.9577 | AK55: =AK$60*$E55 -> 6230.1961 | AL55: =AL$60*$E55 -> 8495.722
A56: =A57+1 -> 1998 | D56: ='CPI-U & C-CPI-U Calcs'!$P38 -> 1.1480415 | E56: ='CPI-U & C-CPI-U Calcs'!$O38 -> 1.1139631 | G56: =G$61*$D56 -> 50743.435 | H56: =H$61*$D56 -> 102347.9 | I56: =I$60*$E56 -> 155954.83 | J56: =J$60*$E56 -> 278490.77 | L56: excess | N56: =N$61*$D56 -> 25371.717 | O56: =O$61*$D56 -> 61420.221 | P56: =P$60*$E56 -> 128105.76 | Q56: =Q$60*$E56 -> 278490.77 | S56: excess | U56: =U$61*$D56 -> 33982.029 | V56: =V$61*$D56 -> 87710.371 | W56: =W$60*$E56 -> 142030.3 | X56: =X$60*$E56 -> 278490.77 | Z56: excess | AB56: =AB$61*$D56 -> 25371.717 | AC56: =AC$61*$D56 -> 51173.95 | AD56: =AD$60*$E56 -> 77977.417 | AE56: =AE$60*$E56 -> 139245.39 | AG56: excess | AI56: =AI$61*$D56 -> 1722.0623 | AJ56: =AJ$61*$D56 -> 4018.1453 | AK56: =AK$60*$E56 -> 6126.797 | AL56: =AL$60*$E56 -> 8354.7232
A57: =A58+1 -> 1997 | D57: ='CPI-U & C-CPI-U Calcs'!$P39 -> 1.1174495 | E57: ='CPI-U & C-CPI-U Calcs'!$O39 -> 1.0842791 | G57: =G$61*$D57 -> 49391.266 | H57: =H$61*$D57 -> 99620.62 | I57: =I$60*$E57 -> 151799.08 | J57: =J$60*$E57 -> 271069.79 | L57: excess | N57: =N$61*$D57 -> 24695.633 | O57: =O$61*$D57 -> 59783.546 | P57: =P$60*$E57 -> 124692.1 | Q57: =Q$60*$E57 -> 271069.79 | S57: excess | U57: =U$61*$D57 -> 33076.504 | V57: =V$61*$D57 -> 85373.139 | W57: =W$60*$E57 -> 138245.59 | X57: =X$60*$E57 -> 271069.79 | Z57: excess | AB57: =AB$61*$D57 -> 24695.633 | AC57: =AC$61*$D57 -> 49810.31 | AD57: =AD$60*$E57 -> 75899.54 | AE57: =AE$60*$E57 -> 135534.89 | AG57: excess | AI57: =AI$61*$D57 -> 1676.1742 | AJ57: =AJ$61*$D57 -> 3911.0731 | AK57: =AK$60*$E57 -> 5963.5353 | AL57: =AL$60*$E57 -> 8132.0936
A58: =A59+1 -> 1996 | D58: ='CPI-U & C-CPI-U Calcs'!$P40 -> 1.0874573 | E58: ='CPI-U & C-CPI-U Calcs'!$O40 -> 1.0551772 | G58: =G$61*$D58 -> 48065.611 | H58: =H$61*$D58 -> 96946.815 | I58: =I$60*$E58 -> 147724.81 | J58: =J$60*$E58 -> 263794.31 | L58: excess | N58: =N$61*$D58 -> 24032.805 | O58: =O$61*$D58 -> 58178.963 | P58: =P$60*$E58 -> 121345.38 | Q58: =Q$60*$E58 -> 263794.31 | S58: excess | U58: =U$61*$D58 -> 32188.735 | V58: =V$61*$D58 -> 83081.735 | W58: =W$60*$E58 -> 134535.1 | X58: =X$60*$E58 -> 263794.31 | Z58: excess | AB58: =AB$61*$D58 -> 24032.805 | AC58: =AC$61*$D58 -> 48473.407 | AD58: =AD$60*$E58 -> 73862.406 | AE58: =AE$60*$E58 -> 131897.15 | AG58: excess | AI58: =AI$61*$D58 -> 1631.1859 | AJ58: =AJ$61*$D58 -> 3806.1004 | AK58: =AK$60*$E58 -> 5803.4748 | AL58: =AL$60*$E58 -> 7913.8292
A59: =A60+1 -> 1995 | D59: ='CPI-U & C-CPI-U Calcs'!$P41 -> 1.0574051 | E59: ='CPI-U & C-CPI-U Calcs'!$O41 -> 1.0260171 | G59: =G$61*$D59 -> 46737.304 | H59: =H$61*$D59 -> 94267.662 | I59: =I$60*$E59 -> 143642.4 | J59: =J$60*$E59 -> 256504.28 | L59: excess | N59: =N$61*$D59 -> 23368.652 | O59: =O$61*$D59 -> 56571.171 | P59: =P$60*$E59 -> 117991.97 | Q59: =Q$60*$E59 -> 256504.28 | S59: excess | U59: =U$61*$D59 -> 31299.19 | V59: =V$61*$D59 -> 80785.748 | W59: =W$60*$E59 -> 130817.18 | X59: =X$60*$E59 -> 256504.28 | Z59: excess | AB59: =AB$61*$D59 -> 23368.652 | AC59: =AC$61*$D59 -> 47133.831 | AD59: =AD$60*$E59 -> 71821.198 | AE59: =AE$60*$E59 -> 128252.14 | AG59: excess | AI59: =AI$61*$D59 -> 1586.1076 | AJ59: =AJ$61*$D59 -> 3700.9178 | AK59: =AK$60*$E59 -> 5643.0941 | AL59: =AL$60*$E59 -> 7695.1283
A60: =A61+1 -> 1994 | D60: ='CPI-U & C-CPI-U Calcs'!$P42 -> 1.030592 | E60: ='CPI-U & C-CPI-U Calcs'!$O42 -> 1 | G60: =G$61*$D60 -> 45552.168 | H60: =H$61*$D60 -> 91877.281 | I60: 140000 | J60: 250000 | L60: excess | N60: =N$61*$D60 -> 22776.084 | O60: =O$61*$D60 -> 55136.674 | P60: 115000 | Q60: 250000 | S60: excess | U60: =U$61*$D60 -> 30505.525 | V60: =V$61*$D60 -> 78737.232 | W60: 127500 | X60: 250000 | Z60: excess | AB60: =AB$61*$D60 -> 22776.084 | AC60: =AC$61*$D60 -> 45938.64 | AD60: 70000 | AE60: 125000 | AG60: excess | AI60: =AI$61*$D60 -> 1545.8881 | AJ60: =AJ$61*$D60 -> 3607.0722 | AK60: 5500 | AL60: 7500
A61: 1993 | D61: ='CPI-U & C-CPI-U Calcs'!$P43 -> 1 | G61: 44200 | H61: 89150 | N61: 22100 | O61: 53500 | U61: 29600 | V61: 76400 | AB61: 22100 | AC61: 44575 | AI61: 1500 | AJ61: 3500
F62: * NOTE: The 10% and 15% bracket values are 2x the rounded Single values. | AA62: * NOTE: Actual law sets this to 50% of the rounded Joint amount.
F63: These columns calculate out to the same result.
A65: Rounded Income Tax Brackets (for 2026 Sunset)
F66: Married Filing Jointly | M66: Single | T66: Head of Household | AA66: Married Filing Separately | AH66: Trusts & Estates
A67: Tax Year | F67: 10% Bracket | G67: 15% Bracket | H67: 25% Bracket | I67: 28% Bracket | J67: 33% Bracket | K67: 35% Bracket | L67: 39.6% Bracket | M67: 10% Bracket | N67: 15% Bracket | O67: 25% Bracket | P67: 28% Bracket | Q67: 33% Bracket | R67: 35% Bracket | S67: 39.6% Bracket | T67: 10% Bracket | U67: 15% Bracket | V67: 25% Bracket | W67: 28% Bracket | X67: 33% Bracket | Y67: 35% Bracket | Z67: 39.6% Bracket | AA67: 10% Bracket | AB67: 15% Bracket | AC67: 25% Bracket | AD67: 28% Bracket | AE67: 33% Bracket | AF67: 35% Bracket | AG67: 39.6% Bracket | AH67: 10% Bracket | AI67: 15% Bracket | AJ67: 25% Bracket | AK67: 28% Bracket | AL67: 33% Bracket | AM67: 35% Bracket | AN67: 39.6% Bracket
A68: =A69+1 -> 2022 | F68: =TRUNC(F32/50)*50 -> 20500 | G68: =TRUNC(G32/100)*100 -> 83200 | H68: =TRUNC(H32/50)*50 -> 167900 | I68: =TRUNC(I32/50)*50 -> 255850 | J68: =TRUNC(J32/50)*50 -> 456850 | K68: =TRUNC(K32/50)*50 -> 516050 | L68: excess | M68: =TRUNC(M32/25)*25 -> 10250 | N68: =TRUNC(N32/50)*50 -> 41600 | O68: =TRUNC(O32/50)*50 -> 100750 | P68: =TRUNC(P32/50)*50 -> 210150 | Q68: =TRUNC(Q32/50)*50 -> 456850 | R68: =TRUNC(R32/50)*50 -> 458700 | S68: excess | T68: =TRUNC(T32/50)*50 -> 14600 | U68: =TRUNC(U32/50)*50 -> 55750 | V68: =TRUNC(V32/50)*50 -> 143850 | W68: =TRUNC(W32/50)*50 -> 233000 | X68: =TRUNC(X32/50)*50 -> 456850 | Y68: =TRUNC(Y32/50)*50 -> 487400 | Z68: excess | AA68: =TRUNC(AA32/25)*25 -> 10250 | AB68: =TRUNC(AB32/50)*50 -> 41600 | AC68: =TRUNC(AC32/25)*25 -> 83950 | AD68: =TRUNC(AD32/25)*25 -> 127925 | AE68: =TRUNC(AE32/25)*25 -> 228425 | AF68: =TRUNC(AF32/25)*25 -> 258025 | AG68: excess | AH68: =TRUNC(AH32/50)*50 -> 0 | AI68: =TRUNC(AI32/50)*50 -> 2800 | AJ68: =TRUNC(AJ32/50)*50 -> 6550 | AK68: =TRUNC(AK32/50)*50 -> 10050 | AL68: =TRUNC(AL32/50)*50 -> 13700 | AM68: =AM32 -> unused | AN68: =AN32 -> excess
A69: =A70+1 -> 2021 | F69: =TRUNC(F33/50)*50 -> 19900 | G69: =TRUNC(G33/100)*100 -> 80800 | H69: =TRUNC(H33/50)*50 -> 163000 | I69: =TRUNC(I33/50)*50 -> 248400 | J69: =TRUNC(J33/50)*50 -> 443550 | K69: =TRUNC(K33/50)*50 -> 501050 | L69: excess | M69: =TRUNC(M33/25)*25 -> 9950 | N69: =TRUNC(N33/50)*50 -> 40400 | O69: =TRUNC(O33/50)*50 -> 97800 | P69: =TRUNC(P33/50)*50 -> 204000 | Q69: =TRUNC(Q33/50)*50 -> 443550 | R69: =TRUNC(R33/50)*50 -> 445350 | S69: excess | T69: =TRUNC(T33/50)*50 -> 14200 | U69: =TRUNC(U33/50)*50 -> 54100 | V69: =TRUNC(V33/50)*50 -> 139700 | W69: =TRUNC(W33/50)*50 -> 226200 | X69: =TRUNC(X33/50)*50 -> 443550 | Y69: =TRUNC(Y33/50)*50 -> 473200 | Z69: excess | AA69: =TRUNC(AA33/25)*25 -> 9950 | AB69: =TRUNC(AB33/50)*50 -> 40400 | AC69: =TRUNC(AC33/25)*25 -> 81500 | AD69: =TRUNC(AD33/25)*25 -> 124200 | AE69: =TRUNC(AE33/25)*25 -> 221775 | AF69: =TRUNC(AF33/25)*25 -> 250525 | AG69: excess | AH69: =TRUNC(AH33/50)*50 -> 0 | AI69: =TRUNC(AI33/50)*50 -> 2700 | AJ69: =TRUNC(AJ33/50)*50 -> 6400 | AK69: =TRUNC(AK33/50)*50 -> 9750 | AL69: =TRUNC(AL33/50)*50 -> 13300 | AM69: =AM33 -> unused | AN69: =AN33 -> excess
A70: =A71+1 -> 2020 | F70: =TRUNC(F34/50)*50 -> 19650 | G70: =TRUNC(G34/100)*100 -> 79900 | H70: =TRUNC(H34/50)*50 -> 161200 | I70: =TRUNC(I34/50)*50 -> 245650 | J70: =TRUNC(J34/50)*50 -> 438700 | K70: =TRUNC(K34/50)*50 -> 495550 | L70: excess | M70: =TRUNC(M34/25)*25 -> 9825 | N70: =TRUNC(N34/50)*50 -> 39950 | O70: =TRUNC(O34/50)*50 -> 96750 | P70: =TRUNC(P34/50)*50 -> 201800 | Q70: =TRUNC(Q34/50)*50 -> 438700 | R70: =TRUNC(R34/50)*50 -> 440500 | S70: excess | T70: =TRUNC(T34/50)*50 -> 14050 | U70: =TRUNC(U34/50)*50 -> 53500 | V70: =TRUNC(V34/50)*50 -> 138150 | W70: =TRUNC(W34/50)*50 -> 223750 | X70: =TRUNC(X34/50)*50 -> 438700 | Y70: =TRUNC(Y34/50)*50 -> 468000 | Z70: excess | AA70: =TRUNC(AA34/25)*25 -> 9825 | AB70: =TRUNC(AB34/50)*50 -> 39950 | AC70: =TRUNC(AC34/25)*25 -> 80600 | AD70: =TRUNC(AD34/25)*25 -> 122825 | AE70: =TRUNC(AE34/25)*25 -> 219350 | AF70: =TRUNC(AF34/25)*25 -> 247775 | AG70: excess | AH70: =TRUNC(AH34/50)*50 -> 0 | AI70: =TRUNC(AI34/50)*50 -> 2700 | AJ70: =TRUNC(AJ34/50)*50 -> 6300 | AK70: =TRUNC(AK34/50)*50 -> 9650 | AL70: =TRUNC(AL34/50)*50 -> 13150 | AM70: =AM34 -> unused | AN70: =AN34 -> excess
A71: =A72+1 -> 2019 | F71: =TRUNC(F35/50)*50 -> 19350 | G71: =TRUNC(G35/100)*100 -> 78700 | H71: =TRUNC(H35/50)*50 -> 158750 | I71: =TRUNC(I35/50)*50 -> 241900 | J71: =TRUNC(J35/50)*50 -> 432000 | K71: =TRUNC(K35/50)*50 -> 488000 | L71: excess | M71: =TRUNC(M35/25)*25 -> 9675 | N71: =TRUNC(N35/50)*50 -> 39350 | O71: =TRUNC(O35/50)*50 -> 95250 | P71: =TRUNC(P35/50)*50 -> 198700 | Q71: =TRUNC(Q35/50)*50 -> 432000 | R71: =TRUNC(R35/50)*50 -> 433750 | S71: excess | T71: =TRUNC(T35/50)*50 -> 13800 | U71: =TRUNC(U35/50)*50 -> 52700 | V71: =TRUNC(V35/50)*50 -> 136050 | W71: =TRUNC(W35/50)*50 -> 220300 | X71: =TRUNC(X35/50)*50 -> 432000 | Y71: =TRUNC(Y35/50)*50 -> 460900 | Z71: excess | AA71: =TRUNC(AA35/25)*25 -> 9675 | AB71: =TRUNC(AB35/50)*50 -> 39350 | AC71: =TRUNC(AC35/25)*25 -> 79375 | AD71: =TRUNC(AD35/25)*25 -> 120950 | AE71: =TRUNC(AE35/25)*25 -> 216000 | AF71: =TRUNC(AF35/25)*25 -> 244000 | AG71: excess | AH71: =TRUNC(AH35/50)*50 -> 0 | AI71: =TRUNC(AI35/50)*50 -> 2650 | AJ71: =TRUNC(AJ35/50)*50 -> 6200 | AK71: =TRUNC(AK35/50)*50 -> 9500 | AL71: =TRUNC(AL35/50)*50 -> 12950 | AM71: =AM35 -> unused | AN71: =AN35 -> excess
A72: =A73+1 -> 2018 | F72: =TRUNC(F36/50)*50 -> 19000 | G72: =TRUNC(G36/100)*100 -> 77100 | H72: =TRUNC(H36/50)*50 -> 155650 | I72: =TRUNC(I36/50)*50 -> 237200 | J72: =TRUNC(J36/50)*50 -> 423550 | K72: =TRUNC(K36/50)*50 -> 478450 | L72: excess | M72: =TRUNC(M36/25)*25 -> 9500 | N72: =TRUNC(N36/50)*50 -> 38550 | O72: =TRUNC(O36/50)*50 -> 93400 | P72: =TRUNC(P36/50)*50 -> 194800 | Q72: =TRUNC(Q36/50)*50 -> 423550 | R72: =TRUNC(R36/50)*50 -> 425300 | S72: excess | T72: =TRUNC(T36/50)*50 -> 13550 | U72: =TRUNC(U36/50)*50 -> 51650 | V72: =TRUNC(V36/50)*50 -> 133400 | W72: =TRUNC(W36/50)*50 -> 216000 | X72: =TRUNC(X36/50)*50 -> 423550 | Y72: =TRUNC(Y36/50)*50 -> 451850 | Z72: excess | AA72: =TRUNC(AA36/25)*25 -> 9500 | AB72: =TRUNC(AB36/50)*50 -> 38550 | AC72: =TRUNC(AC36/25)*25 -> 77825 | AD72: =TRUNC(AD36/25)*25 -> 118600 | AE72: =TRUNC(AE36/25)*25 -> 211775 | AF72: =TRUNC(AF36/25)*25 -> 239225 | AG72: excess | AH72: =TRUNC(AH36/50)*50 -> 0 | AI72: =TRUNC(AI36/50)*50 -> 2600 | AJ72: =TRUNC(AJ36/50)*50 -> 6100 | AK72: =TRUNC(AK36/50)*50 -> 9300 | AL72: =TRUNC(AL36/50)*50 -> 12700 | AM72: =AM36 -> unused | AN72: =AN36 -> excess
A73: =A74+1 -> 2017 | F73: =TRUNC(F37/50)*50 -> 18650 | G73: =TRUNC(G37/100)*100 -> 75900 | H73: =TRUNC(H37/50)*50 -> 153100 | I73: =TRUNC(I37/50)*50 -> 233350 | J73: =TRUNC(J37/50)*50 -> 416700 | K73: =TRUNC(K37/50)*50 -> 470700 | L73: excess | M73: =TRUNC(M37/25)*25 -> 9325 | N73: =TRUNC(N37/50)*50 -> 37950 | O73: =TRUNC(O37/50)*50 -> 91900 | P73: =TRUNC(P37/50)*50 -> 191650 | Q73: =TRUNC(Q37/50)*50 -> 416700 | R73: =TRUNC(R37/50)*50 -> 418400 | S73: excess | T73: =TRUNC(T37/50)*50 -> 13350 | U73: =TRUNC(U37/50)*50 -> 50800 | V73: =TRUNC(V37/50)*50 -> 131200 | W73: =TRUNC(W37/50)*50 -> 212500 | X73: =TRUNC(X37/50)*50 -> 416700 | Y73: =TRUNC(Y37/50)*50 -> 444550 | Z73: excess | AA73: =TRUNC(AA37/25)*25 -> 9325 | AB73: =TRUNC(AB37/50)*50 -> 37950 | AC73: =TRUNC(AC37/25)*25 -> 76550 | AD73: =TRUNC(AD37/25)*25 -> 116675 | AE73: =TRUNC(AE37/25)*25 -> 208350 | AF73: =TRUNC(AF37/25)*25 -> 235350 | AG73: excess | AH73: =TRUNC(AH37/50)*50 -> 0 | AI73: =TRUNC(AI37/50)*50 -> 2550 | AJ73: =TRUNC(AJ37/50)*50 -> 6000 | AK73: =TRUNC(AK37/50)*50 -> 9150 | AL73: =TRUNC(AL37/50)*50 -> 12500 | AM73: =AM37 -> unused | AN73: =AN37 -> excess
A74: =A75+1 -> 2016 | F74: =TRUNC(F38/50)*50 -> 18550 | G74: =TRUNC(G38/100)*100 -> 75300 | H74: =TRUNC(H38/50)*50 -> 151900 | I74: =TRUNC(I38/50)*50 -> 231450 | J74: =TRUNC(J38/50)*50 -> 413350 | K74: =TRUNC(K38/50)*50 -> 466950 | L74: excess | M74: =TRUNC(M38/25)*25 -> 9275 | N74: =TRUNC(N38/50)*50 -> 37650 | O74: =TRUNC(O38/50)*50 -> 91150 | P74: =TRUNC(P38/50)*50 -> 190150 | Q74: =TRUNC(Q38/50)*50 -> 413350 | R74: =TRUNC(R38/50)*50 -> 415050 | S74: excess | T74: =TRUNC(T38/50)*50 -> 13250 | U74: =TRUNC(U38/50)*50 -> 50400 | V74: =TRUNC(V38/50)*50 -> 130150 | W74: =TRUNC(W38/50)*50 -> 210800 | X74: =TRUNC(X38/50)*50 -> 413350 | Y74: =TRUNC(Y38/50)*50 -> 441000 | Z74: excess | AA74: =TRUNC(AA38/25)*25 -> 9275 | AB74: =TRUNC(AB38/50)*50 -> 37650 | AC74: =TRUNC(AC38/25)*25 -> 75950 | AD74: =TRUNC(AD38/25)*25 -> 115725 | AE74: =TRUNC(AE38/25)*25 -> 206675 | AF74: =TRUNC(AF38/25)*25 -> 233475 | AG74: excess | AH74: =TRUNC(AH38/50)*50 -> 0 | AI74: =TRUNC(AI38/50)*50 -> 2550 | AJ74: =TRUNC(AJ38/50)*50 -> 5950 | AK74: =TRUNC(AK38/50)*50 -> 9050 | AL74: =TRUNC(AL38/50)*50 -> 12400 | AM74: =AM38 -> unused | AN74: =AN38 -> excess
A75: =A76+1 -> 2015 | F75: =TRUNC(F39/50)*50 -> 18450 | G75: =TRUNC(G39/100)*100 -> 74900 | H75: =TRUNC(H39/50)*50 -> 151200 | I75: =TRUNC(I39/50)*50 -> 230450 | J75: =TRUNC(J39/50)*50 -> 411500 | K75: =TRUNC(K39/50)*50 -> 464850 | L75: excess | M75: =TRUNC(M39/25)*25 -> 9225 | N75: =TRUNC(N39/50)*50 -> 37450 | O75: =TRUNC(O39/50)*50 -> 90750 | P75: =TRUNC(P39/50)*50 -> 189300 | Q75: =TRUNC(Q39/50)*50 -> 411500 | R75: =TRUNC(R39/50)*50 -> 413200 | S75: excess | T75: =TRUNC(T39/50)*50 -> 13150 | U75: =TRUNC(U39/50)*50 -> 50200 | V75: =TRUNC(V39/50)*50 -> 129600 | W75: =TRUNC(W39/50)*50 -> 209850 | X75: =TRUNC(X39/50)*50 -> 411500 | Y75: =TRUNC(Y39/50)*50 -> 439000 | Z75: excess | AA75: =TRUNC(AA39/25)*25 -> 9225 | AB75: =TRUNC(AB39/50)*50 -> 37450 | AC75: =TRUNC(AC39/25)*25 -> 75600 | AD75: =TRUNC(AD39/25)*25 -> 115225 | AE75: =TRUNC(AE39/25)*25 -> 205750 | AF75: =TRUNC(AF39/25)*25 -> 232425 | AG75: excess | AH75: =TRUNC(AH39/50)*50 -> 0 | AI75: =TRUNC(AI39/50)*50 -> 2500 | AJ75: =TRUNC(AJ39/50)*50 -> 5900 | AK75: =TRUNC(AK39/50)*50 -> 9050 | AL75: =TRUNC(AL39/50)*50 -> 12300 | AM75: =AM39 -> unused | AN75: =AN39 -> excess
A76: =A77+1 -> 2014 | F76: =TRUNC(F40/50)*50 -> 18150 | G76: =TRUNC(G40/100)*100 -> 73800 | H76: =TRUNC(H40/50)*50 -> 148850 | I76: =TRUNC(I40/50)*50 -> 226850 | J76: =TRUNC(J40/50)*50 -> 405100 | K76: =TRUNC(K40/50)*50 -> 457600 | L76: excess | M76: =TRUNC(M40/25)*25 -> 9075 | N76: =TRUNC(N40/50)*50 -> 36900 | O76: =TRUNC(O40/50)*50 -> 89350 | P76: =TRUNC(P40/50)*50 -> 186350 | Q76: =TRUNC(Q40/50)*50 -> 405100 | R76: =TRUNC(R40/50)*50 -> 406750 | S76: excess | T76: =TRUNC(T40/50)*50 -> 12950 | U76: =TRUNC(U40/50)*50 -> 49400 | V76: =TRUNC(V40/50)*50 -> 127550 | W76: =TRUNC(W40/50)*50 -> 206600 | X76: =TRUNC(X40/50)*50 -> 405100 | Y76: =TRUNC(Y40/50)*50 -> 432200 | Z76: excess | AA76: =TRUNC(AA40/25)*25 -> 9075 | AB76: =TRUNC(AB40/50)*50 -> 36900 | AC76: =TRUNC(AC40/25)*25 -> 74425 | AD76: =TRUNC(AD40/25)*25 -> 113425 | AE76: =TRUNC(AE40/25)*25 -> 202550 | AF76: =TRUNC(AF40/25)*25 -> 228800 | AG76: excess | AH76: =TRUNC(AH40/50)*50 -> 0 | AI76: =TRUNC(AI40/50)*50 -> 2500 | AJ76: =TRUNC(AJ40/50)*50 -> 5800 | AK76: =TRUNC(AK40/50)*50 -> 8900 | AL76: =TRUNC(AL40/50)*50 -> 12150 | AM76: =AM40 -> unused | AN76: =AN40 -> excess
A77: =A78+1 -> 2013 | F77: =TRUNC(F41/50)*50 -> 17850 | G77: =TRUNC(G41/100)*100 -> 72500 | H77: =TRUNC(H41/50)*50 -> 146400 | I77: =TRUNC(I41/50)*50 -> 223050 | J77: =TRUNC(J41/50)*50 -> 398350 | K77: =TRUNC(K41/50)*50 -> 450000 | L77: excess | M77: =TRUNC(M41/25)*25 -> 8925 | N77: =TRUNC(N41/50)*50 -> 36250 | O77: =TRUNC(O41/50)*50 -> 87850 | P77: =TRUNC(P41/50)*50 -> 183250 | Q77: =TRUNC(Q41/50)*50 -> 398350 | R77: =TRUNC(R41/50)*50 -> 400000 | S77: excess | T77: =TRUNC(T41/50)*50 -> 12750 | U77: =TRUNC(U41/50)*50 -> 48600 | V77: =TRUNC(V41/50)*50 -> 125450 | W77: =TRUNC(W41/50)*50 -> 203150 | X77: =TRUNC(X41/50)*50 -> 398350 | Y77: =TRUNC(Y41/50)*50 -> 425000 | Z77: excess | AA77: =TRUNC(AA41/25)*25 -> 8925 | AB77: =TRUNC(AB41/50)*50 -> 36250 | AC77: =TRUNC(AC41/25)*25 -> 73200 | AD77: =TRUNC(AD41/25)*25 -> 111525 | AE77: =TRUNC(AE41/25)*25 -> 199175 | AF77: =TRUNC(AF41/25)*25 -> 225000 | AG77: excess | AH77: =TRUNC(AH41/50)*50 -> 0 | AI77: =TRUNC(AI41/50)*50 -> 2450 | AJ77: =TRUNC(AJ41/50)*50 -> 5700 | AK77: =TRUNC(AK41/50)*50 -> 8750 | AL77: =TRUNC(AL41/50)*50 -> 11950 | AM77: =AM41 -> unused | AN77: =AN41 -> excess
A78: =A79+1 -> 2012 | F78: =TRUNC(F42/50)*50 -> 17400 | G78: =TRUNC(G42/100)*100 -> 70700 | H78: =TRUNC(H42/50)*50 -> 142700 | I78: =TRUNC(I42/50)*50 -> 217450 | J78: =TRUNC(J42/50)*50 -> 388350 | L78: excess | M78: =TRUNC(M42/25)*25 -> 8700 | N78: =TRUNC(N42/50)*50 -> 35350 | O78: =TRUNC(O42/50)*50 -> 85650 | P78: =TRUNC(P42/50)*50 -> 178650 | Q78: =TRUNC(Q42/50)*50 -> 388350 | S78: excess | T78: =TRUNC(T42/50)*50 -> 12400 | U78: =TRUNC(U42/50)*50 -> 47350 | V78: =TRUNC(V42/50)*50 -> 122300 | W78: =TRUNC(W42/50)*50 -> 198050 | X78: =TRUNC(X42/50)*50 -> 388350 | Z78: excess | AA78: =TRUNC(AA42/25)*25 -> 8700 | AB78: =TRUNC(AB42/50)*50 -> 35350 | AC78: =TRUNC(AC42/25)*25 -> 71350 | AD78: =TRUNC(AD42/25)*25 -> 108725 | AE78: =TRUNC(AE42/25)*25 -> 194175 | AG78: excess | AH78: =TRUNC(AH42/50)*50 -> 0 | AI78: =TRUNC(AI42/50)*50 -> 2400 | AJ78: =TRUNC(AJ42/50)*50 -> 5600 | AK78: =TRUNC(AK42/50)*50 -> 8500 | AL78: =TRUNC(AL42/50)*50 -> 11650
A79: =A80+1 -> 2011 | F79: =TRUNC(F43/50)*50 -> 17000 | G79: =TRUNC(G43/100)*100 -> 69000 | H79: =TRUNC(H43/50)*50 -> 139350 | I79: =TRUNC(I43/50)*50 -> 212300 | J79: =TRUNC(J43/50)*50 -> 379150 | L79: excess | M79: =TRUNC(M43/25)*25 -> 8500 | N79: =TRUNC(N43/50)*50 -> 34500 | O79: =TRUNC(O43/50)*50 -> 83600 | P79: =TRUNC(P43/50)*50 -> 174400 | Q79: =TRUNC(Q43/50)*50 -> 379150 | S79: excess | T79: =TRUNC(T43/50)*50 -> 12150 | U79: =TRUNC(U43/50)*50 -> 46250 | V79: =TRUNC(V43/50)*50 -> 119400 | W79: =TRUNC(W43/50)*50 -> 193350 | X79: =TRUNC(X43/50)*50 -> 379150 | Z79: excess | AA79: =TRUNC(AA43/25)*25 -> 8500 | AB79: =TRUNC(AB43/50)*50 -> 34500 | AC79: =TRUNC(AC43/25)*25 -> 69675 | AD79: =TRUNC(AD43/25)*25 -> 106150 | AE79: =TRUNC(AE43/25)*25 -> 189575 | AG79: excess | AH79: =TRUNC(AH43/50)*50 -> 0 | AI79: =TRUNC(AI43/50)*50 -> 2300 | AJ79: =TRUNC(AJ43/50)*50 -> 5450 | AK79: =TRUNC(AK43/50)*50 -> 8300 | AL79: =TRUNC(AL43/50)*50 -> 11350
A80: =A81+1 -> 2010 | F80: =TRUNC(F44/50)*50 -> 16750 | G80: =TRUNC(G44/100)*100 -> 68000 | H80: =TRUNC(H44/50)*50 -> 137300 | I80: =TRUNC(I44/50)*50 -> 209250 | J80: =TRUNC(J44/50)*50 -> 373650 | L80: excess | M80: =TRUNC(M44/25)*25 -> 8375 | N80: =TRUNC(N44/50)*50 -> 34000 | O80: =TRUNC(O44/50)*50 -> 82400 | P80: =TRUNC(P44/50)*50 -> 171850 | Q80: =TRUNC(Q44/50)*50 -> 373650 | S80: excess | T80: =TRUNC(T44/50)*50 -> 11950 | U80: =TRUNC(U44/50)*50 -> 45550 | V80: =TRUNC(V44/50)*50 -> 117650 | W80: =TRUNC(W44/50)*50 -> 190550 | X80: =TRUNC(X44/50)*50 -> 373650 | Z80: excess | AA80: =TRUNC(AA44/25)*25 -> 8375 | AB80: =TRUNC(AB44/50)*50 -> 34000 | AC80: =TRUNC(AC44/25)*25 -> 68650 | AD80: =TRUNC(AD44/25)*25 -> 104625 | AE80: =TRUNC(AE44/25)*25 -> 186825 | AG80: excess | AH80: =TRUNC(AH44/50)*50 -> 0 | AI80: =TRUNC(AI44/50)*50 -> 2300 | AJ80: =TRUNC(AJ44/50)*50 -> 5350 | AK80: =TRUNC(AK44/50)*50 -> 8200 | AL80: =TRUNC(AL44/50)*50 -> 11200
A81: =A82+1 -> 2009 | F81: =TRUNC(F45/50)*50 -> 16700 | G81: =TRUNC(G45/100)*100 -> 67900 | H81: =TRUNC(H45/50)*50 -> 137050 | I81: =TRUNC(I45/50)*50 -> 208850 | J81: =TRUNC(J45/50)*50 -> 372950 | L81: excess | M81: =TRUNC(M45/25)*25 -> 8350 | N81: =TRUNC(N45/50)*50 -> 33950 | O81: =TRUNC(O45/50)*50 -> 82250 | P81: =TRUNC(P45/50)*50 -> 171550 | Q81: =TRUNC(Q45/50)*50 -> 372950 | S81: excess | T81: =TRUNC(T45/50)*50 -> 11950 | U81: =TRUNC(U45/50)*50 -> 45500 | V81: =TRUNC(V45/50)*50 -> 117450 | W81: =TRUNC(W45/50)*50 -> 190200 | X81: =TRUNC(X45/50)*50 -> 372950 | Z81: excess | AA81: =TRUNC(AA45/25)*25 -> 8350 | AB81: =TRUNC(AB45/50)*50 -> 33950 | AC81: =TRUNC(AC45/25)*25 -> 68525 | AD81: =TRUNC(AD45/25)*25 -> 104425 | AE81: =TRUNC(AE45/25)*25 -> 186475 | AG81: excess | AH81: =TRUNC(AH45/50)*50 -> 0 | AI81: =TRUNC(AI45/50)*50 -> 2300 | AJ81: =TRUNC(AJ45/50)*50 -> 5350 | AK81: =TRUNC(AK45/50)*50 -> 8200 | AL81: =TRUNC(AL45/50)*50 -> 11150
A82: =A83+1 -> 2008 | F82: =TRUNC(F46/50)*50 -> 16050 | G82: =TRUNC(G46/100)*100 -> 65100 | H82: =TRUNC(H46/50)*50 -> 131450 | I82: =TRUNC(I46/50)*50 -> 200300 | J82: =TRUNC(J46/50)*50 -> 357700 | L82: excess | M82: =TRUNC(M46/25)*25 -> 8025 | N82: =TRUNC(N46/50)*50 -> 32550 | O82: =TRUNC(O46/50)*50 -> 78850 | P82: =TRUNC(P46/50)*50 -> 164550 | Q82: =TRUNC(Q46/50)*50 -> 357700 | S82: excess | T82: =TRUNC(T46/50)*50 -> 11450 | U82: =TRUNC(U46/50)*50 -> 43650 | V82: =TRUNC(V46/50)*50 -> 112650 | W82: =TRUNC(W46/50)*50 -> 182400 | X82: =TRUNC(X46/50)*50 -> 357700 | Z82: excess | AA82: =TRUNC(AA46/25)*25 -> 8025 | AB82: =TRUNC(AB46/50)*50 -> 32550 | AC82: =TRUNC(AC46/25)*25 -> 65725 | AD82: =TRUNC(AD46/25)*25 -> 100150 | AE82: =TRUNC(AE46/25)*25 -> 178850 | AG82: excess | AH82: =TRUNC(AH46/50)*50 -> 0 | AI82: =TRUNC(AI46/50)*50 -> 2200 | AJ82: =TRUNC(AJ46/50)*50 -> 5150 | AK82: =TRUNC(AK46/50)*50 -> 7850 | AL82: =TRUNC(AL46/50)*50 -> 10700
A83: =A84+1 -> 2007 | F83: =TRUNC(F47/50)*50 -> 15650 | G83: =TRUNC(G47/100)*100 -> 63700 | H83: =TRUNC(H47/50)*50 -> 128500 | I83: =TRUNC(I47/50)*50 -> 195850 | J83: =TRUNC(J47/50)*50 -> 349700 | L83: excess | M83: =TRUNC(M47/25)*25 -> 7825 | N83: =TRUNC(N47/50)*50 -> 31850 | O83: =TRUNC(O47/50)*50 -> 77100 | P83: =TRUNC(P47/50)*50 -> 160850 | Q83: =TRUNC(Q47/50)*50 -> 349700 | S83: excess | T83: =TRUNC(T47/50)*50 -> 11200 | U83: =TRUNC(U47/50)*50 -> 42650 | V83: =TRUNC(V47/50)*50 -> 110100 | W83: =TRUNC(W47/50)*50 -> 178350 | X83: =TRUNC(X47/50)*50 -> 349700 | Z83: excess | AA83: =TRUNC(AA47/25)*25 -> 7825 | AB83: =TRUNC(AB47/50)*50 -> 31850 | AC83: =TRUNC(AC47/25)*25 -> 64250 | AD83: =TRUNC(AD47/25)*25 -> 97925 | AE83: =TRUNC(AE47/25)*25 -> 174850 | AG83: excess | AH83: =TRUNC(AH47/50)*50 -> 0 | AI83: =TRUNC(AI47/50)*50 -> 2150 | AJ83: =TRUNC(AJ47/50)*50 -> 5000 | AK83: =TRUNC(AK47/50)*50 -> 7650 | AL83: =TRUNC(AL47/50)*50 -> 10450
A84: =A85+1 -> 2006 | F84: =TRUNC(F48/50)*50 -> 15100 | G84: =TRUNC(G48/100)*100 -> 61300 | H84: =TRUNC(H48/50)*50 -> 123700 | I84: =TRUNC(I48/50)*50 -> 188450 | J84: =TRUNC(J48/50)*50 -> 336550 | L84: excess | M84: =TRUNC(M48/25)*25 -> 7550 | N84: =TRUNC(N48/50)*50 -> 30650 | O84: =TRUNC(O48/50)*50 -> 74200 | P84: =TRUNC(P48/50)*50 -> 154800 | Q84: =TRUNC(Q48/50)*50 -> 336550 | S84: excess | T84: =TRUNC(T48/50)*50 -> 10750 | U84: =TRUNC(U48/50)*50 -> 41050 | V84: =TRUNC(V48/50)*50 -> 106000 | W84: =TRUNC(W48/50)*50 -> 171650 | X84: =TRUNC(X48/50)*50 -> 336550 | Z84: excess | AA84: =TRUNC(AA48/25)*25 -> 7550 | AB84: =TRUNC(AB48/50)*50 -> 30650 | AC84: =TRUNC(AC48/25)*25 -> 61850 | AD84: =TRUNC(AD48/25)*25 -> 94225 | AE84: =TRUNC(AE48/25)*25 -> 168275 | AG84: excess | AH84: =TRUNC(AH48/50)*50 -> 0 | AI84: =TRUNC(AI48/50)*50 -> 2050 | AJ84: =TRUNC(AJ48/50)*50 -> 4850 | AK84: =TRUNC(AK48/50)*50 -> 7400 | AL84: =TRUNC(AL48/50)*50 -> 10050
A85: =A86+1 -> 2005 | F85: =TRUNC(F49/50)*50 -> 14600 | G85: =TRUNC(G49/100)*100 -> 59400 | H85: =TRUNC(H49/50)*50 -> 119950 | I85: =TRUNC(I49/50)*50 -> 182800 | J85: =TRUNC(J49/50)*50 -> 326450 | L85: excess | M85: =TRUNC(M49/25)*25 -> 7300 | N85: =TRUNC(N49/50)*50 -> 29700 | O85: =TRUNC(O49/50)*50 -> 71950 | P85: =TRUNC(P49/50)*50 -> 150150 | Q85: =TRUNC(Q49/50)*50 -> 326450 | S85: excess | T85: =TRUNC(T49/50)*50 -> 10450 | U85: =TRUNC(U49/50)*50 -> 39800 | V85: =TRUNC(V49/50)*50 -> 102800 | W85: =TRUNC(W49/50)*50 -> 166450 | X85: =TRUNC(X49/50)*50 -> 326450 | Z85: excess | AA85: =TRUNC(AA49/25)*25 -> 7300 | AB85: =TRUNC(AB49/50)*50 -> 29700 | AC85: =TRUNC(AC49/25)*25 -> 59975 | AD85: =TRUNC(AD49/25)*25 -> 91400 | AE85: =TRUNC(AE49/25)*25 -> 163225 | AG85: excess | AH85: =TRUNC(AH49/50)*50 -> 0 | AI85: =TRUNC(AI49/50)*50 -> 2000 | AJ85: =TRUNC(AJ49/50)*50 -> 4700 | AK85: =TRUNC(AK49/50)*50 -> 7150 | AL85: =TRUNC(AL49/50)*50 -> 9750
A86: =A87+1 -> 2004 | F86: =TRUNC(F50/50)*50 -> 14300 | G86: =TRUNC(G50/100)*100 -> 58100 | H86: =TRUNC(H50/50)*50 -> 117250 | I86: =TRUNC(I50/50)*50 -> 178650 | J86: =TRUNC(J50/50)*50 -> 319100 | L86: excess | M86: =TRUNC(M50/25)*25 -> 7150 | N86: =TRUNC(N50/50)*50 -> 29050 | O86: =TRUNC(O50/50)*50 -> 70350 | P86: =TRUNC(P50/50)*50 -> 146750 | Q86: =TRUNC(Q50/50)*50 -> 319100 | S86: excess | T86: =TRUNC(T50/50)*50 -> 10200 | U86: =TRUNC(U50/50)*50 -> 38900 | V86: =TRUNC(V50/50)*50 -> 100500 | W86: =TRUNC(W50/50)*50 -> 162700 | X86: =TRUNC(X50/50)*50 -> 319100 | Z86: excess | AA86: =TRUNC(AA50/25)*25 -> 7150 | AB86: =TRUNC(AB50/50)*50 -> 29050 | AC86: =TRUNC(AC50/25)*25 -> 58625 | AD86: =TRUNC(AD50/25)*25 -> 89325 | AE86: =TRUNC(AE50/25)*25 -> 159550 | AG86: excess | AH86: =TRUNC(AH50/50)*50 -> 0 | AI86: =TRUNC(AI50/50)*50 -> 1950 | AJ86: =TRUNC(AJ50/50)*50 -> 4600 | AK86: =TRUNC(AK50/50)*50 -> 7000 | AL86: =TRUNC(AL50/50)*50 -> 9550
A87: =A88+1 -> 2003 | F87: =TRUNC(F51/50)*50 -> 14000 | G87: =TRUNC(G51/100)*100 -> 56800 | H87: =TRUNC(H51/50)*50 -> 114650 | I87: =TRUNC(I51/50)*50 -> 174700 | J87: =TRUNC(J51/50)*50 -> 311950 | L87: excess | M87: =TRUNC(M51/25)*25 -> 7000 | N87: =TRUNC(N51/50)*50 -> 28400 | O87: =TRUNC(O51/50)*50 -> 68800 | P87: =TRUNC(P51/50)*50 -> 143500 | Q87: =TRUNC(Q51/50)*50 -> 311950 | S87: excess | T87: =TRUNC(T51/50)*50 -> 10000 | U87: =TRUNC(U51/50)*50 -> 38050 | V87: =TRUNC(V51/50)*50 -> 98250 | W87: =TRUNC(W51/50)*50 -> 159100 | X87: =TRUNC(X51/50)*50 -> 311950 | Z87: excess | AA87: =TRUNC(AA51/25)*25 -> 7000 | AB87: =TRUNC(AB51/50)*50 -> 28400 | AC87: =TRUNC(AC51/25)*25 -> 57325 | AD87: =TRUNC(AD51/25)*25 -> 87350 | AE87: =TRUNC(AE51/25)*25 -> 155975 | AG87: excess | AH87: =TRUNC(AH51/50)*50 -> 0 | AI87: =TRUNC(AI51/50)*50 -> 1900 | AJ87: =TRUNC(AJ51/50)*50 -> 4500 | AK87: =TRUNC(AK51/50)*50 -> 6850 | AL87: =TRUNC(AL51/50)*50 -> 9350
A88: =A89+1 -> 2002 | G88: =TRUNC(G52/100)*100 -> 55900 | H88: =TRUNC(H52/50)*50 -> 112850 | I88: =TRUNC(I52/50)*50 -> 171950 | J88: =TRUNC(J52/50)*50 -> 307050 | L88: excess | N88: =TRUNC(N52/50)*50 -> 27950 | O88: =TRUNC(O52/50)*50 -> 67700 | P88: =TRUNC(P52/50)*50 -> 141250 | Q88: =TRUNC(Q52/50)*50 -> 307050 | S88: excess | U88: =TRUNC(U52/50)*50 -> 37450 | V88: =TRUNC(V52/50)*50 -> 96700 | W88: =TRUNC(W52/50)*50 -> 156600 | X88: =TRUNC(X52/50)*50 -> 307050 | Z88: excess | AB88: =TRUNC(AB52/50)*50 -> 27950 | AC88: =TRUNC(AC52/25)*25 -> 56425 | AD88: =TRUNC(AD52/25)*25 -> 85975 | AE88: =TRUNC(AE52/25)*25 -> 153525 | AG88: excess | AI88: =TRUNC(AI52/50)*50 -> 1850 | AJ88: =TRUNC(AJ52/50)*50 -> 4400 | AK88: =TRUNC(AK52/50)*50 -> 6750 | AL88: =TRUNC(AL52/50)*50 -> 9200
A89: =A90+1 -> 2001 | G89: =TRUNC(G53/100)*100 -> 54100 | H89: =TRUNC(H53/50)*50 -> 109250 | I89: =TRUNC(I53/50)*50 -> 166450 | J89: =TRUNC(J53/50)*50 -> 297300 | L89: excess | N89: =TRUNC(N53/50)*50 -> 27050 | O89: =TRUNC(O53/50)*50 -> 65550 | P89: =TRUNC(P53/50)*50 -> 136750 | Q89: =TRUNC(Q53/50)*50 -> 297300 | S89: excess | U89: =TRUNC(U53/50)*50 -> 36250 | V89: =TRUNC(V53/50)*50 -> 93600 | W89: =TRUNC(W53/50)*50 -> 151600 | X89: =TRUNC(X53/50)*50 -> 297300 | Z89: excess | AB89: =TRUNC(AB53/50)*50 -> 27050 | AC89: =TRUNC(AC53/25)*25 -> 54625 | AD89: =TRUNC(AD53/25)*25 -> 83225 | AE89: =TRUNC(AE53/25)*25 -> 148650 | AG89: excess | AI89: =TRUNC(AI53/50)*50 -> 1800 | AJ89: =TRUNC(AJ53/50)*50 -> 4250 | AK89: =TRUNC(AK53/50)*50 -> 6500 | AL89: =TRUNC(AL53/50)*50 -> 8900
A90: =A91+1 -> 2000 | G90: =TRUNC(G54/100)*100 -> 52500 | H90: =TRUNC(H54/50)*50 -> 105950 | I90: =TRUNC(I54/50)*50 -> 161450 | J90: =TRUNC(J54/50)*50 -> 288350 | L90: excess | N90: =TRUNC(N54/50)*50 -> 26250 | O90: =TRUNC(O54/50)*50 -> 63550 | P90: =TRUNC(P54/50)*50 -> 132600 | Q90: =TRUNC(Q54/50)*50 -> 288350 | S90: excess | U90: =TRUNC(U54/50)*50 -> 35150 | V90: =TRUNC(V54/50)*50 -> 90800 | W90: =TRUNC(W54/50)*50 -> 147050 | X90: =TRUNC(X54/50)*50 -> 288350 | Z90: excess | AB90: =TRUNC(AB54/50)*50 -> 26250 | AC90: =TRUNC(AC54/25)*25 -> 52975 | AD90: =TRUNC(AD54/25)*25 -> 80725 | AE90: =TRUNC(AE54/25)*25 -> 144175 | AG90: excess | AI90: =TRUNC(AI54/50)*50 -> 1750 | AJ90: =TRUNC(AJ54/50)*50 -> 4150 | AK90: =TRUNC(AK54/50)*50 -> 6300 | AL90: =TRUNC(AL54/50)*50 -> 8650
A91: =A92+1 -> 1999 | G91: =TRUNC(G55/100)*100 -> 51500 | H91: =TRUNC(H55/50)*50 -> 104050 | I91: =TRUNC(I55/50)*50 -> 158550 | J91: =TRUNC(J55/50)*50 -> 283150 | L91: excess | N91: =TRUNC(N55/50)*50 -> 25750 | O91: =TRUNC(O55/50)*50 -> 62450 | P91: =TRUNC(P55/50)*50 -> 130250 | Q91: =TRUNC(Q55/50)*50 -> 283150 | S91: excess | U91: =TRUNC(U55/50)*50 -> 34550 | V91: =TRUNC(V55/50)*50 -> 89150 | W91: =TRUNC(W55/50)*50 -> 144400 | X91: =TRUNC(X55/50)*50 -> 283150 | Z91: excess | AB91: =TRUNC(AB55/50)*50 -> 25750 | AC91: =TRUNC(AC55/25)*25 -> 52025 | AD91: =TRUNC(AD55/25)*25 -> 79275 | AE91: =TRUNC(AE55/25)*25 -> 141575 | AG91: excess | AI91: =TRUNC(AI55/50)*50 -> 1750 | AJ91: =TRUNC(AJ55/50)*50 -> 4050 | AK91: =TRUNC(AK55/50)*50 -> 6200 | AL91: =TRUNC(AL55/50)*50 -> 8450
A92: =A93+1 -> 1998 | G92: =TRUNC(G56/100)*100 -> 50700 | H92: =TRUNC(H56/50)*50 -> 102300 | I92: =TRUNC(I56/50)*50 -> 155950 | J92: =TRUNC(J56/50)*50 -> 278450 | L92: excess | N92: =TRUNC(N56/50)*50 -> 25350 | O92: =TRUNC(O56/50)*50 -> 61400 | P92: =TRUNC(P56/50)*50 -> 128100 | Q92: =TRUNC(Q56/50)*50 -> 278450 | S92: excess | U92: =TRUNC(U56/50)*50 -> 33950 | V92: =TRUNC(V56/50)*50 -> 87700 | W92: =TRUNC(W56/50)*50 -> 142000 | X92: =TRUNC(X56/50)*50 -> 278450 | Z92: excess | AB92: =TRUNC(AB56/50)*50 -> 25350 | AC92: =TRUNC(AC56/25)*25 -> 51150 | AD92: =TRUNC(AD56/25)*25 -> 77975 | AE92: =TRUNC(AE56/25)*25 -> 139225 | AG92: excess | AI92: =TRUNC(AI56/50)*50 -> 1700 | AJ92: =TRUNC(AJ56/50)*50 -> 4000 | AK92: =TRUNC(AK56/50)*50 -> 6100 | AL92: =TRUNC(AL56/50)*50 -> 8350
A93: =A94+1 -> 1997 | G93: =TRUNC(G57/100)*100 -> 49300 | H93: =TRUNC(H57/50)*50 -> 99600 | I93: =TRUNC(I57/50)*50 -> 151750 | J93: =TRUNC(J57/50)*50 -> 271050 | L93: excess | N93: =TRUNC(N57/50)*50 -> 24650 | O93: =TRUNC(O57/50)*50 -> 59750 | P93: =TRUNC(P57/50)*50 -> 124650 | Q93: =TRUNC(Q57/50)*50 -> 271050 | S93: excess | U93: =TRUNC(U57/50)*50 -> 33050 | V93: =TRUNC(V57/50)*50 -> 85350 | W93: =TRUNC(W57/50)*50 -> 138200 | X93: =TRUNC(X57/50)*50 -> 271050 | Z93: excess | AB93: =TRUNC(AB57/50)*50 -> 24650 | AC93: =TRUNC(AC57/25)*25 -> 49800 | AD93: =TRUNC(AD57/25)*25 -> 75875 | AE93: =TRUNC(AE57/25)*25 -> 135525 | AG93: excess | AI93: =TRUNC(AI57/50)*50 -> 1650 | AJ93: =TRUNC(AJ57/50)*50 -> 3900 | AK93: =TRUNC(AK57/50)*50 -> 5950 | AL93: =TRUNC(AL57/50)*50 -> 8100
A94: =A95+1 -> 1996 | G94: =TRUNC(G58/100)*100 -> 48000 | H94: =TRUNC(H58/50)*50 -> 96900 | I94: =TRUNC(I58/50)*50 -> 147700 | J94: =TRUNC(J58/50)*50 -> 263750 | L94: excess | N94: =TRUNC(N58/50)*50 -> 24000 | O94: =TRUNC(O58/50)*50 -> 58150 | P94: =TRUNC(P58/50)*50 -> 121300 | Q94: =TRUNC(Q58/50)*50 -> 263750 | S94: excess | U94: =TRUNC(U58/50)*50 -> 32150 | V94: =TRUNC(V58/50)*50 -> 83050 | W94: =TRUNC(W58/50)*50 -> 134500 | X94: =TRUNC(X58/50)*50 -> 263750 | Z94: excess | AB94: =TRUNC(AB58/50)*50 -> 24000 | AC94: =TRUNC(AC58/25)*25 -> 48450 | AD94: =TRUNC(AD58/25)*25 -> 73850 | AE94: =TRUNC(AE58/25)*25 -> 131875 | AG94: excess | AI94: =TRUNC(AI58/50)*50 -> 1600 | AJ94: =TRUNC(AJ58/50)*50 -> 3800 | AK94: =TRUNC(AK58/50)*50 -> 5800 | AL94: =TRUNC(AL58/50)*50 -> 7900
A95: =A96+1 -> 1995 | G95: =TRUNC(G59/100)*100 -> 46700 | H95: =TRUNC(H59/50)*50 -> 94250 | I95: =TRUNC(I59/50)*50 -> 143600 | J95: =TRUNC(J59/50)*50 -> 256500 | L95: excess | N95: =TRUNC(N59/50)*50 -> 23350 | O95: =TRUNC(O59/50)*50 -> 56550 | P95: =TRUNC(P59/50)*50 -> 117950 | Q95: =TRUNC(Q59/50)*50 -> 256500 | S95: excess | U95: =TRUNC(U59/50)*50 -> 31250 | V95: =TRUNC(V59/50)*50 -> 80750 | W95: =TRUNC(W59/50)*50 -> 130800 | X95: =TRUNC(X59/50)*50 -> 256500 | Z95: excess | AB95: =TRUNC(AB59/50)*50 -> 23350 | AC95: =TRUNC(AC59/25)*25 -> 47125 | AD95: =TRUNC(AD59/25)*25 -> 71800 | AE95: =TRUNC(AE59/25)*25 -> 128250 | AG95: excess | AI95: =TRUNC(AI59/50)*50 -> 1550 | AJ95: =TRUNC(AJ59/50)*50 -> 3700 | AK95: =TRUNC(AK59/50)*50 -> 5600 | AL95: =TRUNC(AL59/50)*50 -> 7650
A96: =A97+1 -> 1994 | G96: =TRUNC(G60/100)*100 -> 45500 | H96: =TRUNC(H60/50)*50 -> 91850 | I96: =TRUNC(I60/50)*50 -> 140000 | J96: =TRUNC(J60/50)*50 -> 250000 | L96: excess | N96: =TRUNC(N60/50)*50 -> 22750 | O96: =TRUNC(O60/50)*50 -> 55100 | P96: =TRUNC(P60/50)*50 -> 115000 | Q96: =TRUNC(Q60/50)*50 -> 250000 | S96: excess | U96: =TRUNC(U60/50)*50 -> 30500 | V96: =TRUNC(V60/50)*50 -> 78700 | W96: =TRUNC(W60/50)*50 -> 127500 | X96: =TRUNC(X60/50)*50 -> 250000 | Z96: excess | AB96: =TRUNC(AB60/50)*50 -> 22750 | AC96: =TRUNC(AC60/25)*25 -> 45925 | AD96: =TRUNC(AD60/25)*25 -> 70000 | AE96: =TRUNC(AE60/25)*25 -> 125000 | AG96: excess | AI96: =TRUNC(AI60/50)*50 -> 1500 | AJ96: =TRUNC(AJ60/50)*50 -> 3600 | AK96: =TRUNC(AK60/50)*50 -> 5500 | AL96: =TRUNC(AL60/50)*50 -> 7500
A97: 1993 | G97: =TRUNC(G61/100)*100 -> 44200 | H97: =TRUNC(H61/50)*50 -> 89150 | N97: =TRUNC(N61/50)*50 -> 22100 | O97: =TRUNC(O61/50)*50 -> 53500 | U97: =TRUNC(U61/50)*50 -> 29600 | V97: =TRUNC(V61/50)*50 -> 76400 | AB97: =TRUNC(AB61/50)*50 -> 22100 | AC97: =TRUNC(AC61/25)*25 -> 44575 | AI97: =TRUNC(AI61/50)*50 -> 1500 | AJ97: =TRUNC(AJ61/50)*50 -> 3500
F98: * NOTE: The 10% and 15% bracket values are 2x the rounded Single values. | M98: * NOTE: The 10% bracket ONLY rounds to $25. | AA98: * NOTE: Actual law sets this to 50% of the rounded Joint amount.
F99: These columns calculate out to the same result.

Sheet Tax Bracket (FUTURE)
D1: Inflation | G1: 0.0264
H2: Single | O2: Married Filing Jointly
F3: starting year | G3: 2003 | H3: 1993 | I3: 1993 | J3: 1994 | K3: 1994 | L3: 2013 | N3: 2003 | O3: 1993 | P3: 1993 | Q3: 1994 | R3: 1994 | S3: 2013
A4: Tax Year | B4: CPI 2013 | C4: CPI 2003 | D4: CPI 1993 | E4: CPI 1994 | F4: CPI (base year 2018) | G4: 10% Bracket | H4: 12% Bracket | I4: 22% Bracket | J4: 24% Bracket | K4: 32% Bracket | L4: 35% Bracket | M4: 37% Bracket | N4: 10% Bracket | O4: 12% Bracket | P4: 22% Bracket | Q4: 24% Bracket | R4: 32% Bracket | S4: 35% Bracket | T4: 37% Bracket
A5: Various Years | G5: 14000 | H5: 44200 | I5: 89150 | J5: 140000 | K5: 250000 | L5: 450000 | N5: 7000 | O5: 22100 | P5: 53500 | Q5: 115000 | R5: 250000 | S5: 400000
A6: 2018 | F6: ='CPI-U & C-CPI-U Calcs'!$F6 -> 0 | G6: 19050 | H6: 77400 | I6: 165000 | J6: 315000 | K6: 400000 | L6: 600000 | M6: excess | N6: 9525 | O6: 38700 | P6: 82500 | Q6: 157500 | R6: 200000 | S6: 500000 | T6: excess
A7: 2021 | B7: ='CPI-U & C-CPI-U Calcs'!H15 -> 1.1134707 | C7: ='CPI-U & C-CPI-U Calcs'!L15 -> 1.4217864 | D7: ='CPI-U & C-CPI-U Calcs'!P15 -> 1.8285959 | E7: ='CPI-U & C-CPI-U Calcs'!O15 -> 1.7743159 | F7: ='CPI-U & C-CPI-U Calcs'!F15 -> 1.0472046 | G7: =G6*$F$7 -> 19949.248 | H7: =H6*$F$7 -> 81053.639 | I7: =I6*$F$7 -> 172788.77 | J7: =J6*$F$7 -> 329869.46 | K7: =K6*$F$7 -> 418881.86 | L7: =L6*$F$7 -> 628322.79 | M7: excess | N7: =N6*$F$7 -> 9974.6242 | O7: =O6*$F$7 -> 40526.82 | P7: =P6*$F$7 -> 86394.383 | Q7: =Q6*$F$7 -> 164934.73 | R7: =R6*$F$7 -> 209440.93 | S7: =S6*$F$7 -> 523602.32 | T7: =T6*$F$7 -> #VALUE!
A8: 2022 | B8: =B7*(1+$G$1) -> 1.1428663 | C8: =C7*(1+$G$1) -> 1.4593215 | D8: =D7*(1+$G$1) -> 1.8768708 | E8: =E7*(1+$G$1) -> 1.8211579 | F8: =F7*(1+$G$1) -> 1.0748508 | G8: =$F8*G6 -> 20475.909 | H8: =$F8*H6 -> 83193.456 | I8: =$F8*I6 -> 177350.39 | J8: =$F8*J6 -> 338578.02 | K8: =$F8*K6 -> 429940.34 | L8: =$F8*L6 -> 644910.51 | M8: excess | N8: =$F8*N6 -> 10237.954 | O8: =$F8*O6 -> 41596.728 | P8: =$F8*P6 -> 88675.195 | Q8: =$F8*Q6 -> 169289.01 | R8: =$F8*R6 -> 214970.17 | S8: =$F8*S6 -> 537425.42
A9: 2023 | B9: =B8*(1+$G$1) -> 1.173038 | C9: =C8*(1+$G$1) -> 1.4978476 | D9: =D8*(1+$G$1) -> 1.9264202 | E9: =E8*(1+$G$1) -> 1.8692364 | F9: =F8*(1+$G$1) -> 1.1032269 | G9: =$F9*G7 -> 22008.548 | H9: =$F9*H7 -> 89420.556 | I9: =$F9*I7 -> 190625.22 | J9: =$F9*J7 -> 363920.87 | K9: =$F9*K7 -> 462121.74 | L9: =$F9*L7 -> 693182.61 | M9: excess | N9: =$F9*N7 -> 11004.274 | O9: =$F9*O7 -> 44710.278 | P9: =$F9*P7 -> 95312.608 | Q9: =$F9*Q7 -> 181960.43 | R9: =$F9*R7 -> 231060.87 | S9: =$F9*S7 -> 577652.17
A10: 2024 | B10: =B9*(1+$G$1) -> 1.2040062 | C10: =C9*(1+$G$1) -> 1.5373908 | D10: =D9*(1+$G$1) -> 1.9772777 | E10: =E9*(1+$G$1) -> 1.9185843 | F10: =F9*(1+$G$1) -> 1.1323521 | G10: =$F10*G8 -> 23185.938 | H10: =$F10*H8 -> 94204.284 | I10: =$F10*I8 -> 200823.09 | J10: =$F10*J8 -> 383389.53 | K10: =$F10*K8 -> 486843.85 | L10: =$F10*L8 -> 730265.77 | M10: excess | N10: =$F10*N8 -> 11592.969 | O10: =$F10*O8 -> 47102.142 | P10: =$F10*P8 -> 100411.54 | Q10: =$F10*Q8 -> 191694.76 | R10: =$F10*R8 -> 243421.92 | S10: =$F10*S8 -> 608554.81
A11: 2025 | B11: =B10*(1+$G$1) -> 1.2357919 | C11: =C10*(1+$G$1) -> 1.5779779 | D11: =D10*(1+$G$1) -> 2.0294778 | E11: =E10*(1+$G$1) -> 1.9692349 | F11: =F10*(1+$G$1) -> 1.1622462 | G11: =$F11*G9 -> 25579.351 | H11: =$F11*H9 -> 103928.7 | I11: =$F11*I9 -> 221553.43 | J11: =$F11*J9 -> 422965.64 | K11: =$F11*K9 -> 537099.23 | L11: =$F11*L9 -> 805648.85 | M11: excess | N11: =$F11*N9 -> 12789.675 | O11: =$F11*O9 -> 51964.351 | P11: =$F11*P9 -> 110776.72 | Q11: =$F11*Q9 -> 211482.82 | R11: =$F11*R9 -> 268549.62 | S11: =$F11*S9 -> 671374.04
G12: 10% Bracket | H12: 15% Bracket | I12: 25% Bracket | J12: 28% Bracket | K12: 33% Bracket | L12: 35% Bracket | M12: 39.6% Bracket | N12: 10% Bracket | O12: 15% Bracket | P12: 25% Bracket | Q12: 28% Bracket | R12: 33% Bracket | S12: 35% Bracket | T12: 39.6% Bracket
A13: 2026 | B13: =B11*(1+$G$1) -> 1.2684168 | C13: =C11*(1+$G$1) -> 1.6196365 | D13: =D11*(1+$G$1) -> 2.083056 | E13: =E11*(1+$G$1) -> 2.0212227 | G13: =C13*G5 -> 22674.912 | H13: =D13*$H$5 -> 92071.076 | I13: =D13*$I$5 -> 185704.44 | J13: =E13*$J$5 -> 282971.18 | K13: =E13*$K$5 -> 505305.67 | L13: =B13*$L$5 -> 570787.57 | M13: excess | N13: =C13*$N$5 -> 11337.456 | O13: =D13*$O$5 -> 46035.538 | P13: =D13*$P$5 -> 111443.5 | Q13: =E13*$Q$5 -> 232440.61 | R13: =E13*$R$5 -> 505305.67 | S13: =B13*$S$5 -> 507366.73 | T13: excess
A14: 2027 | B14: =B13*(1+$G$1) -> 1.301903 | C14: =C13*(1+$G$1) -> 1.6623949 | D14: =D13*(1+$G$1) -> 2.1380487 | E14: =E13*(1+$G$1) -> 2.074583 | G14: =C14*$G$5 -> 23273.529 | H14: =D14*$H$5 -> 94501.753 | I14: =D14*$I$5 -> 190607.04 | J14: =E14*$J$5 -> 290441.62 | K14: =E14*$K$5 -> 518645.74 | L14: =B14*$L$5 -> 585856.36 | M14: excess | N14: =C14*$N$5 -> 11636.765 | O14: =D14*$O$5 -> 47250.876 | P14: =D14*$P$5 -> 114385.61 | Q14: =E14*$Q$5 -> 238577.04 | R14: =E14*$R$5 -> 518645.74 | S14: =B14*$S$5 -> 520761.21 | T14: excess
A15: 2028 | B15: =B14*(1+$G$1) -> 1.3362733 | C15: =C14*(1+$G$1) -> 1.7062822 | D15: =D14*(1+$G$1) -> 2.1944932 | E15: =E14*(1+$G$1) -> 2.129352 | G15: =C15*$G$5 -> 23887.95 | H15: =D15*$H$5 -> 96996.599 | I15: =D15*$I$5 -> 195639.07 | J15: =E15*$J$5 -> 298109.27 | K15: =E15*$K$5 -> 532337.99 | L15: =B15*$L$5 -> 601322.97 | M15: excess | N15: =C15*$N$5 -> 11943.975 | O15: =D15*$O$5 -> 48498.299 | P15: =D15*$P$5 -> 117405.39 | Q15: =E15*$Q$5 -> 244875.47 | R15: =E15*$R$5 -> 532337.99 | S15: =B15*$S$5 -> 534509.31 | T15: excess
A16: 2029 | B16: =B15*(1+$G$1) -> 1.3715509 | C16: =C15*(1+$G$1) -> 1.751328 | D16: =D15*(1+$G$1) -> 2.2524278 | E16: =E15*(1+$G$1) -> 2.1855668 | G16: =C16*$G$5 -> 24518.592 | H16: =D16*$H$5 -> 99557.309 | I16: =D16*$I$5 -> 200803.94 | J16: =E16*$J$5 -> 305979.36 | K16: =E16*$K$5 -> 546391.71 | L16: =B16*$L$5 -> 617197.9 | M16: excess | N16: =C16*$N$5 -> 12259.296 | O16: =D16*$O$5 -> 49778.655 | P16: =D16*$P$5 -> 120504.89 | Q16: =E16*$Q$5 -> 251340.19 | R16: =E16*$R$5 -> 546391.71 | S16: =B16*$S$5 -> 548620.35 | T16: excess
A17: 2030 | B17: =B16*(1+$G$1) -> 1.4077598 | C17: =C16*(1+$G$1) -> 1.7975631 | D17: =D16*(1+$G$1) -> 2.3118919 | E17: =E16*(1+$G$1) -> 2.2432658 | G17: =C17*$G$5 -> 25165.883 | H17: =D17*$H$5 -> 102185.62 | I17: =D17*$I$5 -> 206105.16 | J17: =E17*$J$5 -> 314057.21 | K17: =E17*$K$5 -> 560816.45 | L17: =B17*$L$5 -> 633491.92 | M17: excess | N17: =C17*$N$5 -> 12582.942 | O17: =D17*$O$5 -> 51092.811 | P17: =D17*$P$5 -> 123686.22 | Q17: =E17*$Q$5 -> 257975.57 | R17: =E17*$R$5 -> 560816.45 | S17: =B17*$S$5 -> 563103.93 | T17: excess
A18: 2031 | B18: =B17*(1+$G$1) -> 1.4449247 | C18: =C17*(1+$G$1) -> 1.8450187 | D18: =D17*(1+$G$1) -> 2.3729258 | E18: =E17*(1+$G$1) -> 2.302488 | G18: =C18*$G$5 -> 25830.262 | H18: =D18*$H$5 -> 104883.32 | I18: =D18*$I$5 -> 211546.34 | J18: =E18*$J$5 -> 322348.32 | K18: =E18*$K$5 -> 575622.01 | L18: =B18*$L$5 -> 650216.11 | M18: excess | N18: =C18*$N$5 -> 12915.131 | O18: =D18*$O$5 -> 52441.661 | P18: =D18*$P$5 -> 126951.53 | Q18: =E18*$Q$5 -> 264786.12 | R18: =E18*$R$5 -> 575622.01 | S18: =B18*$S$5 -> 577969.87 | T18: excess
A19: 2032 | B19: =B18*(1+$G$1) -> 1.4830707 | C19: =C18*(1+$G$1) -> 1.8937272 | D19: =D18*(1+$G$1) -> 2.4355711 | E19: =E18*(1+$G$1) -> 2.3632737 | G19: =C19*$G$5 -> 26512.181 | H19: =D19*$H$5 -> 107652.24 | I19: =D19*$I$5 -> 217131.16 | J19: =E19*$J$5 -> 330858.32 | K19: =E19*$K$5 -> 590818.43 | L19: =B19*$L$5 -> 667381.81 | M19: excess | N19: =C19*$N$5 -> 13256.091 | O19: =D19*$O$5 -> 53826.121 | P19: =D19*$P$5 -> 130303.05 | Q19: =E19*$Q$5 -> 271776.48 | R19: =E19*$R$5 -> 590818.43 | S19: =B19*$S$5 -> 593228.28 | T19: excess
A20: 2033 | B20: =B19*(1+$G$1) -> 1.5222238 | C20: =C19*(1+$G$1) -> 1.9437216 | D20: =D19*(1+$G$1) -> 2.4998702 | E20: =E19*(1+$G$1) -> 2.4256641 | G20: =C20*$G$5 -> 27212.103 | H20: =D20*$H$5 -> 110494.26 | I20: =D20*$I$5 -> 222863.43 | J20: =E20*$J$5 -> 339592.98 | K20: =E20*$K$5 -> 606416.03 | L20: =B20*$L$5 -> 685000.69 | M20: excess | N20: =C20*$N$5 -> 13606.051 | O20: =D20*$O$5 -> 55247.131 | P20: =D20*$P$5 -> 133743.05 | Q20: =E20*$Q$5 -> 278951.38 | R20: =E20*$R$5 -> 606416.03 | S20: =B20*$S$5 -> 608889.5 | T20: excess
A21: 2034 | B21: =B20*(1+$G$1) -> 1.5624105 | C21: =C20*(1+$G$1) -> 1.9950359 | D21: =D20*(1+$G$1) -> 2.5658667 | E21: =E20*(1+$G$1) -> 2.4897017 | G21: =C21*$G$5 -> 27930.502 | H21: =D21*$H$5 -> 113411.31 | I21: =D21*$I$5 -> 228747.02 | J21: =E21*$J$5 -> 348558.23 | K21: =E21*$K$5 -> 622425.42 | L21: =B21*$L$5 -> 703084.71 | M21: excess | N21: =C21*$N$5 -> 13965.251 | O21: =D21*$O$5 -> 56705.655 | P21: =D21*$P$5 -> 137273.87 | Q21: =E21*$Q$5 -> 286315.69 | R21: =E21*$R$5 -> 622425.42 | S21: =B21*$S$5 -> 624964.19 | T21: excess
A22: 2035 | B22: =B21*(1+$G$1) -> 1.6036581 | C22: =C21*(1+$G$1) -> 2.0477048 | D22: =D21*(1+$G$1) -> 2.6336056 | E22: =E21*(1+$G$1) -> 2.5554298 | G22: =C22*$G$5 -> 28667.868 | H22: =D22*$H$5 -> 116405.37 | I22: =D22*$I$5 -> 234785.94 | J22: =E22*$J$5 -> 357760.17 | K22: =E22*$K$5 -> 638857.45 | L22: =B22*$L$5 -> 721646.15 | M22: excess | N22: =C22*$N$5 -> 14333.934 | O22: =D22*$O$5 -> 58202.684 | P22: =D22*$P$5 -> 140897.9 | Q22: =E22*$Q$5 -> 293874.43 | R22: =E22*$R$5 -> 638857.45 | S22: =B22*$S$5 -> 641463.24 | T22: excess
A23: 2036 | B23: =B22*(1+$G$1) -> 1.6459947 | C23: =C22*(1+$G$1) -> 2.1017642 | D23: =D22*(1+$G$1) -> 2.7031328 | E23: =E22*(1+$G$1) -> 2.6228931 | G23: =C23*$G$5 -> 29424.699 | H23: =D23*$H$5 -> 119478.47 | I23: =D23*$I$5 -> 240984.29 | J23: =E23*$J$5 -> 367205.04 | K23: =E23*$K$5 -> 655723.29 | L23: =B23*$L$5 -> 740697.61 | M23: excess | N23: =C23*$N$5 -> 14712.35 | O23: =D23*$O$5 -> 59739.235 | P23: =D23*$P$5 -> 144617.61 | Q23: =E23*$Q$5 -> 301632.71 | R23: =E23*$R$5 -> 655723.29 | S23: =B23*$S$5 -> 658397.87 | T23: excess
A24: 2037 | B24: =B23*(1+$G$1) -> 1.6894489 | C24: =C23*(1+$G$1) -> 2.1572508 | D24: =D23*(1+$G$1) -> 2.7744955 | E24: =E23*(1+$G$1) -> 2.6921375 | G24: =C24*$G$5 -> 30201.511 | H24: =D24*$H$5 -> 122632.7 | I24: =D24*$I$5 -> 247346.28 | J24: =E24*$J$5 -> 376899.25 | K24: =E24*$K$5 -> 673034.38 | L24: =B24*$L$5 -> 760252.02 | M24: excess | N24: =C24*$N$5 -> 15100.756 | O24: =D24*$O$5 -> 61316.351 | P24: =D24*$P$5 -> 148435.51 | Q24: =E24*$Q$5 -> 309595.82 | R24: =E24*$R$5 -> 673034.38 | S24: =B24*$S$5 -> 675779.58 | T24: excess
A25: 2038 | B25: =B24*(1+$G$1) -> 1.7340504 | C25: =C24*(1+$G$1) -> 2.2142022 | D25: =D24*(1+$G$1) -> 2.8477422 | E25: =E24*(1+$G$1) -> 2.76321 | G25: =C25*$G$5 -> 30998.831 | H25: =D25*$H$5 -> 125870.21 | I25: =D25*$I$5 -> 253876.22 | J25: =E25*$J$5 -> 386849.39 | K25: =E25*$K$5 -> 690802.49 | L25: =B25*$L$5 -> 780322.68 | M25: excess | N25: =C25*$N$5 -> 15499.416 | O25: =D25*$O$5 -> 62935.103 | P25: =D25*$P$5 -> 152354.21 | Q25: =E25*$Q$5 -> 317769.14 | R25: =E25*$R$5 -> 690802.49 | S25: =B25*$S$5 -> 693620.16 | T25: excess
... A74: 2087 | B74: =B73*(1+$G$1) -> 6.2169481 | C74: =C73*(1+$G$1) -> 7.9383969 | D74: =D73*(1+$G$1) -> 10.209776 | E74: =E73*(1+$G$1) -> 9.9067091 | G74: =C74*$G$5 -> 111137.56 | H74: =D74*$H$5 -> 451272.08 | I74: =D74*$I$5 -> 910201.49 | J74: =E74*$J$5 -> 1386939.3 | K74: =E74*$K$5 -> 2476677.3 | L74: =B74*$L$5 -> 2797626.6 | M74: excess | N74: =C74*$N$5 -> 55568.779 | O74: =D74*$O$5 -> 225636.04 | P74: =D74*$P$5 -> 546222.99 | Q74: =E74*$Q$5 -> 1139271.5 | R74: =E74*$R$5 -> 2476677.3 | S74: =B74*$S$5 -> 2486779.2 | T74: excess
A75: 2088 | B75: =B74*(1+$G$1) -> 6.3810755 | C75: =C74*(1+$G$1) -> 8.1479706 | D75: =D74*(1+$G$1) -> 10.479314 | E75: =E74*(1+$G$1) -> 10.168246
A76: 2089 | B76: =B75*(1+$G$1) -> 6.5495359 | C76: =C75*(1+$G$1) -> 8.363077 | D76: =D75*(1+$G$1) -> 10.755968 | E76: =E75*(1+$G$1) -> 10.436688
A77: 2090 | B77: =B76*(1+$G$1) -> 6.7224436 | C77: =C76*(1+$G$1) -> 8.5838623 | D77: =D76*(1+$G$1) -> 11.039925 | E77: =E76*(1+$G$1) -> 10.712216
A78: 2091 | B78: =B77*(1+$G$1) -> 6.8999161 | C78: =C77*(1+$G$1) -> 8.8104762 | D78: =D77*(1+$G$1) -> 11.331379 | E78: =E77*(1+$G$1) -> 10.995019
A79: 2092 | B79: =B78*(1+$G$1) -> 7.0820739 | C79: =C78*(1+$G$1) -> 9.0430728 | D79: =D78*(1+$G$1) -> 11.630528 | E79: =E78*(1+$G$1) -> 11.285287
A80: 2093 | B80: =B79*(1+$G$1) -> 7.2690407 | C80: =C79*(1+$G$1) -> 9.2818099 | D80: =D79*(1+$G$1) -> 11.937573 | E80: =E79*(1+$G$1) -> 11.583219
A81: 2094 | B81: =B80*(1+$G$1) -> 7.4609433 | C81: =C80*(1+$G$1) -> 9.5268497 | D81: =D80*(1+$G$1) -> 12.252725 | E81: =E80*(1+$G$1) -> 11.889016
A82: 2095 | B82: =B81*(1+$G$1) -> 7.6579122 | C82: =C81*(1+$G$1) -> 9.7783585 | D82: =D81*(1+$G$1) -> 12.576197 | E82: =E81*(1+$G$1) -> 12.202886
A83: 2096 | B83: =B82*(1+$G$1) -> 7.8600811 | C83: =C82*(1+$G$1) -> 10.036507 | D83: =D82*(1+$G$1) -> 12.908209 | E83: =E82*(1+$G$1) -> 12.525042
A84: 2097 | B84: =B83*(1+$G$1) -> 8.0675873 | C84: =C83*(1+$G$1) -> 10.301471 | D84: =D83*(1+$G$1) -> 13.248986 | E84: =E83*(1+$G$1) -> 12.855703
A85: 2098 | B85: =B84*(1+$G$1) -> 8.2805716 | C85: =C84*(1+$G$1) -> 10.57343 | D85: =D84*(1+$G$1) -> 13.598759 | E85: =E84*(1+$G$1) -> 13.195094
A86: 2099 | B86: =B85*(1+$G$1) -> 8.4991787 | C86: =C85*(1+$G$1) -> 10.852568 | D86: =D85*(1+$G$1) -> 13.957766 | E86: =E85*(1+$G$1) -> 13.543444
A87: 2100 | B87: =B86*(1+$G$1) -> 8.723557 | C87: =C86*(1+$G$1) -> 11.139076 | D87: =D86*(1+$G$1) -> 14.326251 | E87: =E86*(1+$G$1) -> 13.900991

Sheet Cap Gains
A1: Capital Gains Tax Brackets
A2: These calculations are used to index IRS base numbers from the internal revenue code to future years.
A4: *** See "2022-2026 IRS Updates" sheet for complete updated 2022-2026 values from IRS Rev. Procs. 2021-45 through 2025-32 and OBBBA 2025 ***
A5: Post-2012 American Tax Payer Relief Bill
C6: Married Filing Jointly | F6: Single | I6: Head of Household | L6: Married Filing Separately | O6: Trusts & Estates
A7: Tax Year | B7: CPI (base 2018) | C7: 0% Bracket | D7: 15% Bracket | E7: 20% Bracket | F7: 0% Bracket | G7: 15% Bracket | H7: 20% Bracket | I7: 0% Bracket | J7: 15% Bracket | K7: 20% Bracket | L7: 0% Bracket | M7: 15% Bracket | N7: 20% Bracket | O7: 0% Bracket | P7: 15% Bracket | Q7: 20% Bracket
A8: =A9+1 -> 2022 | B8: ='CPI-U & C-CPI-U Calcs'!$F14 -> 1.0786208 | C8: =C$12*$B8 -> 83269.525 | D8: =D$12*$B8 -> 516659.36 | E8: excess | F8: =F$12*$B8 -> 41634.762 | G8: =G$12*$B8 -> 459276.73 | H8: excess | I8: =I$12*$B8 -> 55764.695 | J8: =J$12*$B8 -> 487968.04 | K8: excess | L8: =L$12*$B8 -> 41634.762 | M8: =M$12*$B8 -> 258329.68 | N8: excess | O8: =O$12*$B8 -> 2804.414 | P8: =P$12*$B8 -> 13698.484 | Q8: excess
A9: =A10+1 -> 2021 | B9: ='CPI-U & C-CPI-U Calcs'!$F15 -> 1.0472046 | C9: =C$12*$B9 -> 80844.199 | D9: =D$12*$B9 -> 501611.02 | E9: excess | F9: =F$12*$B9 -> 40422.099 | G9: =G$12*$B9 -> 445899.74 | H9: excess | I9: =I$12*$B9 -> 54140.48 | J9: =J$12*$B9 -> 473755.38 | K9: excess | L9: =L$12*$B9 -> 40422.099 | M9: =M$12*$B9 -> 250805.51 | N9: excess | O9: =O$12*$B9 -> 2722.7321 | P9: =P$12*$B9 -> 13299.499 | Q9: excess
A10: =A11+1 -> 2020 | B10: ='CPI-U & C-CPI-U Calcs'!$F16 -> 1.0357497 | C10: =C$12*$B10 -> 79959.874 | D10: =D$12*$B10 -> 496124.09 | E10: excess | F10: =F$12*$B10 -> 39979.937 | G10: =G$12*$B10 -> 441022.2 | H10: excess | I10: =I$12*$B10 -> 53548.257 | J10: =J$12*$B10 -> 468573.15 | K10: excess | L10: =L$12*$B10 -> 39979.937 | M10: =M$12*$B10 -> 248062.04 | N10: excess | O10: =O$12*$B10 -> 2692.9491 | P10: =P$12*$B10 -> 13154.021 | Q10: excess
A11: =A12+1 -> 2019 | B11: ='CPI-U & C-CPI-U Calcs'!$F17 -> 1.0199308 | C11: =C$12*$B11 -> 78738.656 | D11: =D$12*$B11 -> 488546.85 | E11: excess | F11: =F$12*$B11 -> 39369.328 | G11: =G$12*$B11 -> 434286.53 | H11: excess | I11: =I$12*$B11 -> 52730.421 | J11: =J$12*$B11 -> 461416.69 | K11: excess | L11: =L$12*$B11 -> 39369.328 | M11: =M$12*$B11 -> 244273.42 | N11: excess | O11: =O$12*$B11 -> 2651.82 | P11: =P$12*$B11 -> 12953.121 | Q11: excess
A12: 2018 | B12: ='CPI-U & C-CPI-U Calcs'!$F18 -> 1 | C12: 77200 | D12: 479000 | E12: excess | F12: 38600 | G12: 425800 | H12: excess | I12: 51700 | J12: 452400 | K12: excess | L12: 38600 | M12: 239500 | N12: excess | O12: 2600 | P12: 12700 | Q12: excess
A15: Capital Gains Brackets
A16: Rounded, Post-2012 American Tax Payer Relief Bill
C17: Married Filing Jointly | F17: Single | I17: Head of Household | L17: Married Filing Separately | O17: Trusts & Estates
A18: Tax Year | C18: 0% Bracket | D18: 15% Bracket | E18: 20% Bracket | F18: 0% Bracket | G18: 15% Bracket | H18: 20% Bracket | I18: 0% Bracket | J18: 15% Bracket | K18: 20% Bracket | L18: 10% Bracket | M18: 15% Bracket | N18: 20% Bracket | O18: 10% Bracket | P18: 15% Bracket | Q18: 20% Bracket
A19: =A20+1 -> 2022 | C19: =+TRUNC(C8/50)*50 -> 83250 | D19: =+TRUNC(D8/50)*50 -> 516650 | E19: =E8 -> excess | F19: =+TRUNC(F8/50)*50 -> 41600 | G19: =+TRUNC(G8/50)*50 -> 459250 | H19: =H8 -> excess | I19: =+TRUNC(I8/50)*50 -> 55750 | J19: =+TRUNC(J8/50)*50 -> 487950 | K19: =K8 -> excess | L19: =+TRUNC(L8/50)*50 -> 41600 | M19: =+TRUNC(M8/50)*50 -> 258300 | N19: =N29 -> 0 | O19: =+TRUNC(O8/50)*50 -> 2800 | P19: =+TRUNC(P8/50)*50 -> 13650 | Q19: =Q8 -> excess
A20: =A21+1 -> 2021 | C20: =+TRUNC(C9/50)*50 -> 80800 | D20: =+TRUNC(D9/50)*50 -> 501600 | E20: =E9 -> excess | F20: =+TRUNC(F9/50)*50 -> 40400 | G20: =+TRUNC(G9/50)*50 -> 445850 | H20: =H9 -> excess | I20: =+TRUNC(I9/50)*50 -> 54100 | J20: =+TRUNC(J9/50)*50 -> 473750 | K20: =K9 -> excess | L20: =+TRUNC(L9/50)*50 -> 40400 | M20: =+TRUNC(M9/50)*50 -> 250800 | N20: =N30 -> 0 | O20: =+TRUNC(O9/50)*50 -> 2700 | P20: =+TRUNC(P9/50)*50 -> 13250 | Q20: =Q9 -> excess
A21: =A22+1 -> 2020 | C21: =+TRUNC(C10/50)*50 -> 79950 | D21: =+TRUNC(D10/50)*50 -> 496100 | E21: =E10 -> excess | F21: =+TRUNC(F10/50)*50 -> 39950 | G21: =+TRUNC(G10/50)*50 -> 441000 | H21: =H10 -> excess | I21: =+TRUNC(I10/50)*50 -> 53500 | J21: =+TRUNC(J10/50)*50 -> 468550 | K21: =K10 -> excess | L21: =+TRUNC(L10/50)*50 -> 39950 | M21: =+TRUNC(M10/50)*50 -> 248050 | N21: =N31 -> 0 | O21: =+TRUNC(O10/50)*50 -> 2650 | P21: =+TRUNC(P10/50)*50 -> 13150 | Q21: =Q10 -> excess
A22: =A23+1 -> 2019 | C22: =+TRUNC(C11/50)*50 -> 78700 | D22: =+TRUNC(D11/50)*50 -> 488500 | E22: =E11 -> excess | F22: =+TRUNC(F11/25)*25 -> 39350 | G22: =+TRUNC(G11/50)*50 -> 434250 | H22: =H11 -> excess | I22: =+TRUNC(I11/50)*50 -> 52700 | J22: =+TRUNC(J11/50)*50 -> 461400 | K22: =K11 -> excess | L22: =+TRUNC(L11/50)*50 -> 39350 | M22: =+TRUNC(M11/50)*50 -> 244250 | N22: =N11 -> excess | O22: =+TRUNC(O11/50)*50 -> 2650 | P22: =+TRUNC(P11/50)*50 -> 12950 | Q22: =Q11 -> excess
A23: 2018 | C23: =+TRUNC(C12/50)*50 -> 77200 | D23: =+TRUNC(D12/50)*50 -> 479000 | E23: =E12 -> excess | F23: =+TRUNC(F12/50)*50 -> 38600 | G23: =+TRUNC(G12/50)*50 -> 425800 | H23: =H12 -> excess | I23: =+TRUNC(I12/50)*50 -> 51700 | J23: =+TRUNC(J12/50)*50 -> 452400 | K23: =K12 -> excess | L23: =+TRUNC(L12/50)*50 -> 38600 | M23: =+TRUNC(M12/50)*50 -> 239500 | N23: =N12 -> excess | O23: =+TRUNC(O12/50)*50 -> 2600 | P23: =+TRUNC(P12/50)*50 -> 12700 | Q23: =Q12 -> excess
A26: Capital Gains Tax Brackets (for 2026 Sunset)
A27: These calculations are used to index IRS base numbers from the internal revenue code to future years.
A29: Capital Gains Brackets
A30: Rounded, Post-2012 American Tax Payer Relief Bill
D31: Married Filing Jointly | G31: Single | J31: Head of Household | M31: Married Filing Separately | P31: Trusts & Estates
A32: Tax Year | D32: 0% Bracket | E32: 15% Bracket | F32: 20% Bracket | G32: 0% Bracket | H32: 15% Bracket | I32: 20% Bracket | J32: 0% Bracket | K32: 15% Bracket | L32: 20% Bracket | M32: 10% Bracket | N32: 15% Bracket | O32: 25% Bracket | P32: 10% Bracket | Q32: 15% Bracket | R32: 25% Bracket
A33: =A34+1 -> 2022 | D33: =+TRUNC(D48/50)*50 -> 83200 | E33: =+TRUNC(E48/50)*50 -> 516050 | F33: =F48 -> excess | G33: =+TRUNC(G48/50)*50 -> 41600 | H33: =+TRUNC(H48/50)*50 -> 458700 | I33: =I48 -> excess | J33: =+TRUNC(J48/50)*50 -> 55750 | K33: =+TRUNC(K48/50)*50 -> 487400 | L33: =L48 -> excess | M33: =+TRUNC(M48/50)*50 -> 41600 | N33: =+TRUNC(N48/50)*50 -> 258000 | O33: =O48 -> excess | P33: =+TRUNC(P48/50)*50 -> 2800 | Q33: =+TRUNC(Q48/50)*50 -> 13700 | R33: =R48 -> excess
A34: =A35+1 -> 2021 | D34: =+TRUNC(D49/50)*50 -> 80800 | E34: =+TRUNC(E49/50)*50 -> 501050 | F34: =F49 -> excess | G34: =+TRUNC(G49/50)*50 -> 40400 | H34: =+TRUNC(H49/50)*50 -> 445350 | I34: =I49 -> excess | J34: =+TRUNC(J49/50)*50 -> 54100 | K34: =+TRUNC(K49/50)*50 -> 473200 | L34: =L49 -> excess | M34: =+TRUNC(M49/50)*50 -> 40400 | N34: =+TRUNC(N49/50)*50 -> 250500 | O34: =O49 -> excess | P34: =+TRUNC(P49/50)*50 -> 2700 | Q34: =+TRUNC(Q49/50)*50 -> 13300 | R34: =R49 -> excess
A35: =A36+1 -> 2020 | D35: =+TRUNC(D50/50)*50 -> 79900 | E35: =+TRUNC(E50/50)*50 -> 495550 | F35: =F50 -> excess | G35: =+TRUNC(G50/50)*50 -> 39950 | H35: =+TRUNC(H50/50)*50 -> 440500 | I35: =I50 -> excess | J35: =+TRUNC(J50/50)*50 -> 53500 | K35: =+TRUNC(K50/50)*50 -> 468000 | L35: =L50 -> excess | M35: =+TRUNC(M50/50)*50 -> 39950 | N35: =+TRUNC(N50/50)*50 -> 247750 | O35: =O50 -> excess | P35: =+TRUNC(P50/50)*50 -> 2700 | Q35: =+TRUNC(Q50/50)*50 -> 13150 | R35: =R50 -> excess
A36: =A37+1 -> 2019 | D36: =+TRUNC(D51/50)*50 -> 78700 | E36: =+TRUNC(E51/50)*50 -> 488000 | F36: =F51 -> excess | G36: =+TRUNC(G51/50)*50 -> 39350 | H36: =+TRUNC(H51/50)*50 -> 433750 | I36: =I51 -> excess | J36: =+TRUNC(J51/50)*50 -> 52700 | K36: =+TRUNC(K51/50)*50 -> 460900 | L36: =L51 -> excess | M36: =+TRUNC(M51/50)*50 -> 39350 | N36: =+TRUNC(N51/50)*50 -> 244000 | O36: =O51 -> excess | P36: =+TRUNC(P51/50)*50 -> 2650 | Q36: =+TRUNC(Q51/50)*50 -> 12950 | R36: =R51 -> excess
A37: =A38+1 -> 2018 | D37: =+TRUNC(D52/50)*50 -> 77150 | E37: =+TRUNC(E52/50)*50 -> 478450 | F37: =F52 -> excess | G37: =+TRUNC(G52/50)*50 -> 38550 | H37: =+TRUNC(H52/50)*50 -> 425300 | I37: =I52 -> excess | J37: =+TRUNC(J52/50)*50 -> 51650 | K37: =+TRUNC(K52/50)*50 -> 451850 | L37: =L52 -> excess | M37: =+TRUNC(M52/50)*50 -> 38550 | N37: =+TRUNC(N52/50)*50 -> 239200 | O37: =O52 -> excess | P37: =+TRUNC(P52/50)*50 -> 2600 | Q37: =+TRUNC(Q52/50)*50 -> 12700 | R37: =R52 -> excess
A38: =A39+1 -> 2017 | D38: =+TRUNC(D53/50)*50 -> 75900 | E38: =+TRUNC(E53/50)*50 -> 470700 | F38: =F53 -> excess | G38: =+TRUNC(G53/50)*50 -> 37950 | H38: =+TRUNC(H53/50)*50 -> 418400 | I38: =I53 -> excess | J38: =+TRUNC(J53/50)*50 -> 50800 | K38: =+TRUNC(K53/50)*50 -> 444550 | L38: =L53 -> excess | M38: =+TRUNC(M53/50)*50 -> 37950 | N38: =+TRUNC(N53/50)*50 -> 235350 | O38: =O53 -> excess | P38: =+TRUNC(P53/50)*50 -> 2550 | Q38: =+TRUNC(Q53/50)*50 -> 12500 | R38: =R53 -> excess
A39: =A40+1 -> 2016 | D39: =+TRUNC(D54/50)*50 -> 75300 | E39: =+TRUNC(E54/50)*50 -> 466950 | F39: =F54 -> excess | G39: =+TRUNC(G54/50)*50 -> 37650 | H39: =+TRUNC(H54/50)*50 -> 415050 | I39: =I54 -> excess | J39: =+TRUNC(J54/50)*50 -> 50400 | K39: =+TRUNC(K54/50)*50 -> 441000 | L39: =L54 -> excess | M39: =+TRUNC(M54/50)*50 -> 37650 | N39: =+TRUNC(N54/50)*50 -> 233450 | O39: =O54 -> excess | P39: =+TRUNC(P54/50)*50 -> 2550 | Q39: =+TRUNC(Q54/50)*50 -> 12400 | R39: =R54 -> excess
A40: =A41+1 -> 2015 | D40: =+TRUNC(D55/50)*50 -> 74950 | E40: =+TRUNC(E55/50)*50 -> 464850 | F40: =F55 -> excess | G40: =+TRUNC(G55/50)*50 -> 37450 | H40: =+TRUNC(H55/50)*50 -> 413200 | I40: =I55 -> excess | J40: =+TRUNC(J55/50)*50 -> 50200 | K40: =+TRUNC(K55/50)*50 -> 439000 | L40: =L55 -> excess | M40: =+TRUNC(M55/50)*50 -> 37450 | N40: =+TRUNC(N55/50)*50 -> 232400 | O40: =O55 -> excess | P40: =+TRUNC(P55/50)*50 -> 2500 | Q40: =+TRUNC(Q55/50)*50 -> 12300 | R40: =R55 -> excess
A41: =A42+1 -> 2014 | D41: =+TRUNC(D56/50)*50 -> 73800 | E41: =+TRUNC(E56/50)*50 -> 457600 | F41: =F56 -> excess | G41: =+TRUNC(G56/50)*50 -> 36900 | H41: =+TRUNC(H56/50)*50 -> 406750 | I41: =I56 -> excess | J41: =+TRUNC(J56/50)*50 -> 49400 | K41: =+TRUNC(K56/50)*50 -> 432200 | L41: =L56 -> excess | M41: =+TRUNC(M56/50)*50 -> 36900 | N41: =+TRUNC(N56/50)*50 -> 228800 | O41: =O56 -> excess | P41: =+TRUNC(P56/50)*50 -> 2500 | Q41: =+TRUNC(Q56/50)*50 -> 12150 | R41: =R56 -> excess
A42: 2013 | D42: =+TRUNC(D57/50)*50 -> 72550 | E42: =+TRUNC(E57/50)*50 -> 450000 | F42: =F57 -> excess | G42: =+TRUNC(G57/50)*50 -> 36250 | H42: =+TRUNC(H57/50)*50 -> 400000 | I42: =I57 -> excess | J42: =+TRUNC(J57/50)*50 -> 48600 | K42: =+TRUNC(K57/50)*50 -> 425000 | L42: =L57 -> excess | M42: =+TRUNC(M57/50)*50 -> 36250 | N42: =+TRUNC(N57/50)*50 -> 225000 | O42: =O57 -> excess | P42: =+TRUNC(P57/50)*50 -> 2450 | Q42: =+TRUNC(Q57/50)*50 -> 11950 | R42: =R57 -> excess
A44: Capital Gains Brackets
A45: Post-2012 American Tax Payer Relief Bill
D46: Married Filing Jointly | G46: Single | J46: Head of Household | M46: Married Filing Separately | P46: Trusts & Estates
A47: Tax Year | B47: CPI (base 1993) | C47: CPI (base 2013) | D47: 0% Bracket | E47: 15% Bracket | F47: 20% Bracket | G47: 0% Bracket | H47: 15% Bracket | I47: 20% Bracket | J47: 0% Bracket | K47: 15% Bracket | L47: 20% Bracket | M47: 0% Bracket | N47: 15% Bracket | O47: 20% Bracket | P47: 0% Bracket | Q47: 15% Bracket * | R47: 20% Bracket
A48: =A49+1 -> 2022 | B48: ='CPI-U & C-CPI-U Calcs'!$P14 -> 1.8834537 | C48: ='CPI-U & C-CPI-U Calcs'!$H14 -> 1.1468748 | D48: =D$77*$B48 -> 83248.655 | E48: =E$57*$C48 -> 516093.65 | F48: excess | G48: =G$77*$B48 -> 41624.328 | H48: =H$57*$C48 -> 458749.91 | I48: excess | J48: =J$77*$B48 -> 55750.231 | K48: =K$57*$C48 -> 487421.78 | L48: excess | M48: =M$77*$B48 -> 41624.328 | N48: =N$57*$C48 -> 258046.82 | O48: excess | P48: =P$77*$B48 -> 2825.1806 | Q48: =Q$57*$C48 -> 13706.3 | R48: excess
A49: =A50+1 -> 2021 | B49: ='CPI-U & C-CPI-U Calcs'!$P15 -> 1.8285959 | C49: ='CPI-U & C-CPI-U Calcs'!$H15 -> 1.1134707 | D49: =D$77*$B49 -> 80823.937 | E49: =E$57*$C49 -> 501061.8 | F49: excess | G49: =G$77*$B49 -> 40411.969 | H49: =H$57*$C49 -> 445388.26 | I49: excess | J49: =J$77*$B49 -> 54126.438 | K49: =K$57*$C49 -> 473225.03 | L49: excess | M49: =M$77*$B49 -> 40411.969 | N49: =N$57*$C49 -> 250530.9 | O49: excess | P49: =P$77*$B49 -> 2742.8938 | Q49: =Q$57*$C49 -> 13307.088 | R49: excess
A50: =A51+1 -> 2020 | B50: ='CPI-U & C-CPI-U Calcs'!$P16 -> 1.8085935 | C50: ='CPI-U & C-CPI-U Calcs'!$H16 -> 1.1012908 | D50: =D$77*$B50 -> 79939.834 | E50: =E$57*$C50 -> 495580.86 | F50: excess | G50: =G$77*$B50 -> 39969.917 | H50: =H$57*$C50 -> 440516.32 | I50: excess | J50: =J$77*$B50 -> 53534.368 | K50: =K$57*$C50 -> 468048.59 | L50: excess | M50: =M$77*$B50 -> 39969.917 | N50: =N$57*$C50 -> 247790.43 | O50: excess | P50: =P$77*$B50 -> 2712.8903 | Q50: =Q$57*$C50 -> 13161.526 | R50: excess
A51: =A52+1 -> 2019 | B51: ='CPI-U & C-CPI-U Calcs'!$P17 -> 1.7809711 | C51: ='CPI-U & C-CPI-U Calcs'!$H17 -> 1.0844709 | D51: =D$77*$B51 -> 78718.923 | E51: =E$57*$C51 -> 488011.92 | F51: excess | G51: =G$77*$B51 -> 39359.461 | H51: =H$57*$C51 -> 433788.37 | I51: excess | J51: =J$77*$B51 -> 52716.745 | K51: =K$57*$C51 -> 460900.15 | L51: excess | M51: =M$77*$B51 -> 39359.461 | N51: =N$57*$C51 -> 244005.96 | O51: excess | P51: =P$77*$B51 -> 2671.4567 | Q51: =Q$57*$C51 -> 12960.512 | R51: excess
A52: =A53+1 -> 2018 | B52: ='CPI-U & C-CPI-U Calcs'!$P18 -> 1.7461686 | C52: ='CPI-U & C-CPI-U Calcs'!$H18 -> 1.063279 | D52: =D$77*$B52 -> 77180.652 | E52: =E$57*$C52 -> 478475.53 | F52: excess | G52: =G$77*$B52 -> 38590.326 | H52: =H$57*$C52 -> 425311.58 | I52: excess | J52: =J$77*$B52 -> 51686.59 | K52: =K$57*$C52 -> 451893.55 | L52: excess | M52: =M$77*$B52 -> 38590.326 | N52: =N$57*$C52 -> 239237.76 | O52: excess | P52: =P$77*$B52 -> 2619.2529 | Q52: =Q$57*$C52 -> 12707.247 | R52: excess
A53: =A54+1 -> 2017 | B53: ='CPI-U & C-CPI-U Calcs'!$P19 -> 1.7178262 | C53: ='CPI-U & C-CPI-U Calcs'!$H19 -> 1.0460206 | D53: =D$77*$B53 -> 75927.917 | E53: =E$57*$C53 -> 470709.29 | F53: excess | G53: =G$77*$B53 -> 37963.958 | H53: =H$57*$C53 -> 418408.26 | I53: excess | J53: =J$77*$B53 -> 50847.654 | K53: =K$57*$C53 -> 444558.77 | L53: excess | M53: =M$77*$B53 -> 37963.958 | N53: =N$57*$C53 -> 235354.65 | O53: excess | P53: =P$77*$B53 -> 2576.7392 | Q53: =Q$57*$C53 -> 12500.993 | R53: excess
A54: =A55+1 -> 2016 | B54: ='CPI-U & C-CPI-U Calcs'!$P20 -> 1.7041491 | C54: ='CPI-U & C-CPI-U Calcs'!$H20 -> 1.0376924 | D54: =D$77*$B54 -> 75323.391 | E54: =E$57*$C54 -> 466961.58 | F54: excess | G54: =G$77*$B54 -> 37661.696 | H54: =H$57*$C54 -> 415076.96 | I54: excess | J54: =J$77*$B54 -> 50442.814 | K54: =K$57*$C54 -> 441019.27 | L54: excess | M54: =M$77*$B54 -> 37661.696 | N54: =N$57*$C54 -> 233480.79 | O54: excess | P54: =P$77*$B54 -> 2556.2237 | Q54: =Q$57*$C54 -> 12401.462 | R54: excess
A55: =A56+1 -> 2015 | B55: ='CPI-U & C-CPI-U Calcs'!$P21 -> 1.6964909 | C55: ='CPI-U & C-CPI-U Calcs'!$H21 -> 1.0330292 | D55: =D$77*$B55 -> 74984.898 | E55: =E$57*$C55 -> 464863.12 | F55: excess | G55: =G$77*$B55 -> 37492.449 | H55: =H$57*$C55 -> 413211.66 | I55: excess | J55: =J$77*$B55 -> 50216.131 | K55: =K$57*$C55 -> 439037.39 | L55: excess | M55: =M$77*$B55 -> 37492.449 | N55: =N$57*$C55 -> 232431.56 | O55: excess | P55: =P$77*$B55 -> 2544.7364 | Q55: =Q$57*$C55 -> 12345.731 | R55: excess
A56: =A57+1 -> 2014 | B56: ='CPI-U & C-CPI-U Calcs'!$P22 -> 1.6700966 | C56: ='CPI-U & C-CPI-U Calcs'!$H22 -> 1.0169571 | D56: =D$77*$B56 -> 73818.269 | E56: =E$57*$C56 -> 457630.69 | F56: excess | G56: =G$77*$B56 -> 36909.134 | H56: =H$57*$C56 -> 406782.84 | I56: excess | J56: =J$77*$B56 -> 49434.859 | K56: =K$57*$C56 -> 432206.76 | L56: excess | M56: =M$77*$B56 -> 36909.134 | N56: =N$57*$C56 -> 228815.35 | O56: excess | P56: =P$77*$B56 -> 2505.1449 | Q56: =Q$57*$C56 -> 12153.654 | R56: excess
A57: 2013 | B57: ='CPI-U & C-CPI-U Calcs'!$P23 -> 1.6422488 | C57: ='CPI-U & C-CPI-U Calcs'!$H23 -> 1 | D57: =D$77*$B57 -> 72587.398 | E57: 450000 | F57: excess | G57: =G$77*$B57 -> 36293.699 | H57: 400000 | I57: excess | J57: =J$77*$B57 -> 48610.565 | K57: 425000 | L57: excess | M57: =M$77*$B57 -> 36293.699 | N57: 225000 | O57: excess | P57: =P$77*$B57 -> 2463.3732 | Q57: 11951 | R57: excess
A58: =A59+1 -> 2012 | B58: ='CPI-U & C-CPI-U Calcs'!$P24 -> 1.6010977 | D58: =D$77*$B58 -> 70768.519 | G58: =G$77*$B58 -> 35384.259 | J58: =J$77*$B58 -> 47392.492 | M58: =M$77*$B58 -> 35384.259 | P58: =P$77*$B58 -> 2401.6466 | Q58: * $11,951 is from 2013 33% tax bracket for trusts
A59: =A60+1 -> 2011 | B59: ='CPI-U & C-CPI-U Calcs'!$P25 -> 1.563169 | D59: =D$77*$B59 -> 69092.069 | G59: =G$77*$B59 -> 34546.034 | J59: =J$77*$B59 -> 46269.802 | M59: =M$77*$B59 -> 34546.034 | P59: =P$77*$B59 -> 2344.7535
A60: =A61+1 -> 2010 | B60: ='CPI-U & C-CPI-U Calcs'!$P26 -> 1.5404163 | D60: =D$77*$B60 -> 68086.4 | G60: =G$77*$B60 -> 34043.2 | J60: =J$77*$B60 -> 45596.322 | M60: =M$77*$B60 -> 34043.2 | P60: =P$77*$B60 -> 2310.6244
A61: =A62+1 -> 2009 | B61: ='CPI-U & C-CPI-U Calcs'!$P27 -> 1.5375562 | D61: =D$77*$B61 -> 67959.986 | G61: =G$77*$B61 -> 33979.993 | J61: =J$77*$B61 -> 45511.665 | M61: =M$77*$B61 -> 33979.993 | P61: =P$77*$B61 -> 2306.3344
A62: =A63+1 -> 2008 | B62: ='CPI-U & C-CPI-U Calcs'!$P28 -> 1.4746986 | D62: =D$77*$B62 -> 65181.677 | G62: =G$77*$B62 -> 32590.839 | J62: =J$77*$B62 -> 43651.078 | M62: =M$77*$B62 -> 32590.839 | P62: =P$77*$B62 -> 2212.0479
A63: =A64+1 -> 2007 | B63: ='CPI-U & C-CPI-U Calcs'!$P29 -> 1.4417252 | D63: =D$77*$B63 -> 63724.252 | G63: =G$77*$B63 -> 31862.126 | J63: =J$77*$B63 -> 42675.064 | M63: =M$77*$B63 -> 31862.126 | P63: =P$77*$B63 -> 2162.5877
A64: =A65+1 -> 2006 | B64: ='CPI-U & C-CPI-U Calcs'!$P30 -> 1.3875592 | D64: =D$77*$B64 -> 61330.118 | G64: =G$77*$B64 -> 30665.059 | J64: =J$77*$B64 -> 41071.753 | M64: =M$77*$B64 -> 30665.059 | P64: =P$77*$B64 -> 2081.3389
A65: =A66+1 -> 2005 | B65: ='CPI-U & C-CPI-U Calcs'!$P31 -> 1.3457501 | D65: =D$77*$B65 -> 59482.155 | G65: =G$77*$B65 -> 29741.077 | J65: =J$77*$B65 -> 39834.203 | M65: =M$77*$B65 -> 29741.077 | P65: =P$77*$B65 -> 2018.6252
A66: =A67+1 -> 2004 | B66: ='CPI-U & C-CPI-U Calcs'!$P32 -> 1.315458 | D66: =D$77*$B66 -> 58143.243 | G66: =G$77*$B66 -> 29071.621 | J66: =J$77*$B66 -> 38937.556 | M66: =M$77*$B66 -> 29071.621 | P66: =P$77*$B66 -> 1973.187
A67: =A68+1 -> 2003 | B67: ='CPI-U & C-CPI-U Calcs'!$P33 -> 1.2861256 | D67: =D$77*$B67 -> 56846.752 | G67: =G$77*$B67 -> 28423.376 | J67: =J$77*$B67 -> 38069.318 | M67: =M$77*$B67 -> 28423.376 | P67: =P$77*$B67 -> 1929.1884
A68: =A69+1 -> 2002 | B68: ='CPI-U & C-CPI-U Calcs'!$P34 -> 1.2659708 | D68: =D$77*$B68 -> 55955.911 | G68: =G$77*$B68 -> 27977.956 | J68: =J$77*$B68 -> 37472.737 | M68: =M$77*$B68 -> 27977.956 | P68: =P$77*$B68 -> 1898.9563
A69: =A70+1 -> 2001 | B69: ='CPI-U & C-CPI-U Calcs'!$P35 -> 1.2256613 | D69: =D$77*$B69 -> 54174.231 | G69: =G$77*$B69 -> 27087.115 | J69: =J$77*$B69 -> 36279.575 | M69: =M$77*$B69 -> 27087.115 | P69: =P$77*$B69 -> 1838.492
A70: =A71+1 -> 2000 | B70: ='CPI-U & C-CPI-U Calcs'!$P36 -> 1.1887109 | D70: =D$77*$B70 -> 52541.023 | G70: =G$77*$B70 -> 26270.512 | J70: =J$77*$B70 -> 35185.844 | M70: =M$77*$B70 -> 26270.512 | P70: =P$77*$B70 -> 1783.0664
... A76: =A77+1 -> 1994 | B76: ='CPI-U & C-CPI-U Calcs'!$P42 -> 1.030592 | D76: =D$77*$B76 -> 45552.168 | G76: =G$77*$B76 -> 22776.084 | J76: =J$77*$B76 -> 30505.525 | M76: =M$77*$B76 -> 22776.084 | P76: =P$77*$B76 -> 1545.8881
A77: 1993 | B77: ='CPI-U & C-CPI-U Calcs'!$P43 -> 1 | D77: 44200 | G77: 22100 | J77: 29600 | M77: 22100 | P77: 1500

Sheet Sheet2

Sheet Estate, Gifts, IRA
A1: Estate & Gifting Limits, IRA Contributions
A2: These calculations are used to index IRS base numbers from the internal revenue code to future years.
A3: This functionality is crucial for proper handling of tax provison sunsetting.
A4: *** See "2022-2026 IRS Updates" sheet for complete updated 2022-2026 values from IRS Rev. Procs. 2021-45 through 2025-32 and OBBBA 2025 ***
A5: Color Coding:
A6: Green | B6: Base value that is indexed to get subsequent year values.
A7: Red | B7: Future values based upon a CPI value (3% in the examples) picked out of the air.
A9: Estate Tax Exclusion | H9: Estate Tax Exclusion (for 2026 Sunset) | N9: Estate Tax Table
A10: Tax Year | B10: Prev Year Cum CPI | C10: Annual Gift Amount | D10: Annual Amt (rounded) * | E10: Unified Credit** | H10: Tax Year | I10: Prev Year Cum CPI | J10: Annual Gift Amount | K10: Annual Amt (rounded) * | L10: Unified Credit** | N10: Lower Limit | O10: Upper Limit | P10: Initial Tax | Q10: Further Tax
A11: =A12+1 -> 2022 | B11: ='CPI-U & C-CPI-U Calcs'!$J14 -> 1.2048945 | C11: =C$22*$B11 -> 12048945 | D11: =+ROUND(C11,-4) -> 12050000 | E11: =((D11-1000000)*0.4)+345800 -> 4765800 | H11: =H12+1 -> 2022 | I11: ='CPI-U & C-CPI-U Calcs'!$J14 -> 1.2048945 | J11: =J$22*$B11 -> 6024472.6 | K11: =+ROUND(J11,-4) -> 6020000 | L11: =((K11-1000000)*0.4)+345800 -> 2353800 | N11: 0 | O11: 10000 | P11: 0 | Q11: 18% of the amount
A12: =A13+1 -> 2021 | B12: ='CPI-U & C-CPI-U Calcs'!$J15 -> 1.1698005 | C12: =C$22*$B12 -> 11698005 | D12: =+ROUND(C12,-4) -> 11700000 | E12: =((D12-1000000)*0.4)+345800 -> 4625800 | H12: =H13+1 -> 2021 | I12: ='CPI-U & C-CPI-U Calcs'!$J15 -> 1.1698005 | J12: =J$22*$B12 -> 5849002.6 | K12: =+ROUND(J12,-4) -> 5850000 | L12: =((K12-1000000)*0.4)+345800 -> 2285800 | N12: 10000 | O12: 20000 | P12: 1800 | Q12: 20% of the excess
A13: =A14+1 -> 2020 | B13: ='CPI-U & C-CPI-U Calcs'!$J16 -> 1.1570045 | C13: =C$22*$B13 -> 11570045 | D13: =+ROUND(C13,-4) -> 11570000 | E13: =((D13-1000000)*0.4)+345800 -> 4573800 | H13: =H14+1 -> 2020 | I13: ='CPI-U & C-CPI-U Calcs'!$J16 -> 1.1570045 | J13: =J$22*$B13 -> 5785022.5 | K13: =+ROUND(J13,-4) -> 5790000 | L13: =((K13-1000000)*0.4)+345800 -> 2261800 | N13: 20000 | O13: 40000 | P13: 3800 | Q13: 22% of the excess
A14: =A15+1 -> 2019 | B14: ='CPI-U & C-CPI-U Calcs'!$J17 -> 1.1393337 | C14: =C$22*$B14 -> 11393337 | D14: =+ROUND(C14,-4) -> 11390000 | E14: =((D14-1000000)*0.4)+345800 -> 4501800 | H14: =H15+1 -> 2019 | I14: ='CPI-U & C-CPI-U Calcs'!$J17 -> 1.1393337 | J14: =J$22*$B14 -> 5696668.5 | K14: =+ROUND(J14,-4) -> 5700000 | L14: =((K14-1000000)*0.4)+345800 -> 2225800 | N14: 40000 | O14: 60000 | P14: 8200 | Q14: 24% of the excess
A15: =A16+1 -> 2018 | B15: ='CPI-U & C-CPI-U Calcs'!$J18 -> 1.1170696 | C15: =C$22*$B15 -> 11170696 | D15: =+ROUND(C15,-4) -> 11170000 | E15: =((D15-1000000)*0.4)+345800 -> 4413800 | H15: =H16+1 -> 2018 | I15: ='CPI-U & C-CPI-U Calcs'!$J18 -> 1.1170696 | J15: =J$22*$B15 -> 5585348.2 | K15: =+ROUND(J15,-4) -> 5590000 | L15: =((K15-1000000)*0.4)+345800 -> 2181800 | N15: 60000 | O15: 80000 | P15: 13000 | Q15: 26% of the excess
A16: =A17+1 -> 2017 | B16: ='CPI-U & C-CPI-U Calcs'!$J19 -> 1.0989382 | C16: =C$22*$B16 -> 10989382 | D16: =+ROUND(C16,-4) -> 10990000 | E16: =((D16-1000000)*0.4)+345800 -> 4341800 | H16: =H17+1 -> 2017 | I16: ='CPI-U & C-CPI-U Calcs'!$J19 -> 1.0989382 | J16: =J$22*$B16 -> 5494691.2 | K16: =+ROUND(J16,-4) -> 5490000 | L16: =((K16-1000000)*0.4)+345800 -> 2141800 | N16: 80000 | O16: 100000 | P16: 18200 | Q16: 28% of the excess
A17: =A18+1 -> 2016 | B17: ='CPI-U & C-CPI-U Calcs'!$J20 -> 1.0901887 | C17: =C$22*$B17 -> 10901887 | D17: =+ROUND(C17,-4) -> 10900000 | E17: =((D17-1000000)*0.4)+345800 -> 4305800 | H17: =H18+1 -> 2016 | I17: ='CPI-U & C-CPI-U Calcs'!$J20 -> 1.0901887 | J17: =J$22*$B17 -> 5450943.4 | K17: =+ROUND(J17,-4) -> 5450000 | L17: =((K17-1000000)*0.4)+345800 -> 2125800 | N17: 100000 | O17: 150000 | P17: 23800 | Q17: 30% of the excess
A18: =A19+1 -> 2015 | B18: ='CPI-U & C-CPI-U Calcs'!$J21 -> 1.0852895 | C18: =C$22*$B18 -> 10852895 | D18: =+ROUND(C18,-4) -> 10850000 | E18: =((D18-1000000)*0.4)+345800 -> 4285800 | H18: =H19+1 -> 2015 | I18: ='CPI-U & C-CPI-U Calcs'!$J21 -> 1.0852895 | J18: =J$22*$B18 -> 5426447.6 | K18: =+ROUND(J18,-4) -> 5430000 | L18: =((K18-1000000)*0.4)+345800 -> 2117800 | N18: 150000 | O18: 250000 | P18: 38800 | Q18: 32% of the excess
A19: =A20+1 -> 2014 | B19: ='CPI-U & C-CPI-U Calcs'!$J22 -> 1.0684044 | C19: =C$22*$B19 -> 10684044 | D19: =+ROUND(C19,-4) -> 10680000 | E19: =((D19-1000000)*0.4)+345800 -> 4217800 | H19: =H20+1 -> 2014 | I19: ='CPI-U & C-CPI-U Calcs'!$J22 -> 1.0684044 | J19: =J$22*$B19 -> 5342021.9 | K19: =+ROUND(J19,-4) -> 5340000 | L19: =((K19-1000000)*0.4)+345800 -> 2081800 | N19: 250000 | O19: 500000 | P19: 70800 | Q19: 34% of the excess
A20: =A21+1 -> 2013 | B20: ='CPI-U & C-CPI-U Calcs'!$J23 -> 1.0505894 | C20: =C$22*$B20 -> 10505894 | D20: =+ROUND(C20,-4) -> 10510000 | E20: =((D20-1000000)*0.4)+345800 -> 4149800 | H20: =H21+1 -> 2013 | I20: ='CPI-U & C-CPI-U Calcs'!$J23 -> 1.0505894 | J20: =J$22*$B20 -> 5252947.2 | K20: =+ROUND(J20,-4) -> 5250000 | L20: =((K20-1000000)*0.4)+345800 -> 2045800 | N20: 500000 | O20: 750000 | P20: 155800 | Q20: 37% of the excess
A21: =A22+1 -> 2012 | B21: ='CPI-U & C-CPI-U Calcs'!$J24 -> 1.024264 | C21: =C$22*$B21 -> 10242640 | D21: =+ROUND(C21,-4) -> 10240000 | E21: =((D21-1000000)*0.4)+345800 -> 4041800 | H21: =H22+1 -> 2012 | I21: ='CPI-U & C-CPI-U Calcs'!$J24 -> 1.024264 | J21: =J$22*$B21 -> 5121320 | K21: =+ROUND(J21,-4) -> 5120000 | L21: =((K21-1000000)*0.4)+345800 -> 1993800 | N21: 750000 | O21: 1000000 | P21: 248300 | Q21: 39% of the excess
A22: 2011 | B22: ='CPI-U & C-CPI-U Calcs'!$J25 -> 1 | C22: 10000000 | D22: =+TRUNC(C22/10000)*10000 -> 10000000 | E22: =((D22-1000000)*0.4)+345800 -> 3945800 | H22: 2011 | I22: ='CPI-U & C-CPI-U Calcs'!$J25 -> 1 | J22: 5000000 | K22: =+TRUNC(J22/10000)*10000 -> 5000000 | L22: =((K22-1000000)*0.4)+345800 -> 1945800 | N22: 1000000 | O22: and over | P22: 345800 | Q22: 40% of the excess
A24: * Unlike most federal tax figures, this is rounded (not rounded down) | H24: * Unlike most federal tax figures, this is rounded (not rounded down)
A25: ** Corresponding unified credit calculation (done by simulation) | H25: ** Corresponding unified credit calculation (done by simulation)
A29: Annual Gift Exclusions
C30: Annual Gift Exclusion | E30: Non-Resident Spouse
A31: Tax Year | B31: Prev Year Cum CPI | C31: Annual Gift Amount | D31: Annual Amt (rounded) | E31: Annual Gift Amount | F31: Annual Amt (rounded)
A32: =A33+1 -> 2022 | B32: ='CPI-U & C-CPI-U Calcs'!$N14 -> 1.6405798 | C32: =C$56*$B32 -> 16405.798 | D32: =+TRUNC(C32/1000)*1000 -> 16000 | E32: =E$56*$B32 -> 164057.98 | F32: =+TRUNC(E32/1000)*1000 -> 164000
A33: =A34+1 -> 2021 | B33: ='CPI-U & C-CPI-U Calcs'!$N15 -> 1.5927959 | C33: =C$56*$B33 -> 15927.959 | D33: =+TRUNC(C33/1000)*1000 -> 15000 | E33: =E$56*$B33 -> 159279.59 | F33: =+TRUNC(E33/1000)*1000 -> 159000
A34: =A35+1 -> 2020 | B34: ='CPI-U & C-CPI-U Calcs'!$N16 -> 1.5753729 | C34: =C$56*$B34 -> 15753.729 | D34: =+TRUNC(C34/1000)*1000 -> 15000 | E34: =E$56*$B34 -> 157537.29 | F34: =+TRUNC(E34/1000)*1000 -> 157000
A35: =A36+1 -> 2019 | B35: ='CPI-U & C-CPI-U Calcs'!$N17 -> 1.5513125 | C35: =C$56*$B35 -> 15513.125 | D35: =+TRUNC(C35/1000)*1000 -> 15000 | E35: =E$56*$B35 -> 155131.25 | F35: =+TRUNC(E35/1000)*1000 -> 155000
A36: =A37+1 -> 2018 | B36: ='CPI-U & C-CPI-U Calcs'!$N18 -> 1.5209978 | C36: =C$56*$B36 -> 15209.978 | D36: =+TRUNC(C36/1000)*1000 -> 15000 | E36: =E$56*$B36 -> 152099.78 | F36: =+TRUNC(E36/1000)*1000 -> 152000
A37: =A38+1 -> 2017 | B37: ='CPI-U & C-CPI-U Calcs'!$N19 -> 1.4963102 | C37: =C$56*$B37 -> 14963.102 | D37: =+TRUNC(C37/1000)*1000 -> 14000 | E37: =E$56*$B37 -> 149631.02 | F37: =+TRUNC(E37/1000)*1000 -> 149000
A38: =A39+1 -> 2016 | B38: ='CPI-U & C-CPI-U Calcs'!$N20 -> 1.4843968 | C38: =C$56*$B38 -> 14843.968 | D38: =+TRUNC(C38/1000)*1000 -> 14000 | E38: =E$56*$B38 -> 148439.68 | F38: =+TRUNC(E38/1000)*1000 -> 148000
A39: =A40+1 -> 2015 | B39: ='CPI-U & C-CPI-U Calcs'!$N21 -> 1.4777261 | C39: =C$56*$B39 -> 14777.261 | D39: =+TRUNC(C39/1000)*1000 -> 14000 | E39: =E$56*$B39 -> 147772.61 | F39: =+TRUNC(E39/1000)*1000 -> 147000
A40: =A41+1 -> 2014 | B40: ='CPI-U & C-CPI-U Calcs'!$N22 -> 1.4547354 | C40: =C$56*$B40 -> 14547.354 | D40: =+TRUNC(C40/1000)*1000 -> 14000 | E40: =E$56*$B40 -> 145473.54 | F40: =+TRUNC(E40/1000)*1000 -> 145000
A41: =A42+1 -> 2013 | B41: ='CPI-U & C-CPI-U Calcs'!$N23 -> 1.4304786 | C41: =C$56*$B41 -> 14304.786 | D41: =+TRUNC(C41/1000)*1000 -> 14000 | E41: =E$56*$B41 -> 143047.86 | F41: =+TRUNC(E41/1000)*1000 -> 143000
A42: =A43+1 -> 2012 | B42: ='CPI-U & C-CPI-U Calcs'!$N24 -> 1.394634 | C42: =C$56*$B42 -> 13946.34 | D42: =+TRUNC(C42/1000)*1000 -> 13000 | E42: =E$56*$B42 -> 139463.4 | F42: =+TRUNC(E42/1000)*1000 -> 139000
A43: =A44+1 -> 2011 | B43: ='CPI-U & C-CPI-U Calcs'!$N25 -> 1.3615962 | C43: =C$56*$B43 -> 13615.962 | D43: =+TRUNC(C43/1000)*1000 -> 13000 | E43: =E$56*$B43 -> 136159.62 | F43: =+TRUNC(E43/1000)*1000 -> 136000
... A55: =A56+1 -> 1999 | B55: ='CPI-U & C-CPI-U Calcs'!$N37 -> 1.0168765 | C55: =C$56*$B55 -> 10168.765 | D55: =+TRUNC(C55/1000)*1000 -> 10000 | E55: =E$56*$B55 -> 101687.65 | F55: =+TRUNC(E55/1000)*1000 -> 101000
A56: 1998 | B56: ='CPI-U & C-CPI-U Calcs'!$N38 -> 1 | C56: 10000 | D56: =+TRUNC(C56/1000)*1000 -> 10000 | E56: 100000 | F56: =+TRUNC(E56/1000)*1000 -> 100000
A57: NOTE: Rounding is down to the nearest $1,000
A60: Maximum Traditional & Roth IRA Contributions
A61: Tax Year | B61: Prev Year Cum CPI | C61: Maximum Contribution | D61: Max Contrib (rounded) | E61: Max Contrib (actual) | F61: Maximum Catch-up | G61: Max Catch-up (rounded) | H61: Max Catch-up (actual)
A62: =A63+1 -> 2022 | B62: ='CPI-U & C-CPI-U Calcs'!$K14 -> 1.2771788 | C62: =C$76*$B62 -> 6385.8939 | D62: =+TRUNC(C62/500)*500 -> 6000 | E62: 10000 | F62: =+F64 -> 1000 | G62: =+F62 -> 1000 | H62: =+G62 -> 1000
A63: =A64+1 -> 2021 | B63: ='CPI-U & C-CPI-U Calcs'!$K15 -> 1.2399794 | C63: =C$76*$B63 -> 6199.897 | D63: =+TRUNC(C63/500)*500 -> 6000 | E63: 6000 | F63: =+F65 -> 1000 | G63: =+F63 -> 1000 | H63: =+G63 -> 1000
A64: =A65+1 -> 2020 | B64: ='CPI-U & C-CPI-U Calcs'!$K16 -> 1.2264157 | C64: =C$76*$B64 -> 6132.0786 | D64: =+TRUNC(C64/500)*500 -> 6000 | E64: 6000 | F64: =+F66 -> 1000 | G64: =+F64 -> 1000 | H64: =+G64 -> 1000
A65: =A66+1 -> 2019 | B65: ='CPI-U & C-CPI-U Calcs'!$K17 -> 1.2076848 | C65: =C$76*$B65 -> 6038.4242 | D65: =+TRUNC(C65/500)*500 -> 6000 | E65: 6000 | F65: =+F67 -> 1000 | G65: =+F65 -> 1000 | H65: =+G65 -> 1000
A66: =A67+1 -> 2018 | B66: ='CPI-U & C-CPI-U Calcs'!$K18 -> 1.1840851 | C66: =C$76*$B66 -> 5920.4254 | D66: =+TRUNC(C66/500)*500 -> 5500 | E66: 5500 | F66: =+F68 -> 1000 | G66: =+F66 -> 1000 | H66: =+G66 -> 1000
A67: =A68+1 -> 2017 | B67: ='CPI-U & C-CPI-U Calcs'!$K19 -> 1.164866 | C67: =C$76*$B67 -> 5824.3298 | D67: =+TRUNC(C67/500)*500 -> 5500 | E67: 5500 | F67: =+F69 -> 1000 | G67: =+F67 -> 1000 | H67: =+G67 -> 1000
A68: =A69+1 -> 2016 | B68: ='CPI-U & C-CPI-U Calcs'!$K20 -> 1.1555915 | C68: =C$76*$B68 -> 5777.9574 | D68: =+TRUNC(C68/500)*500 -> 5500 | E68: 5500 | F68: =+F70 -> 1000 | G68: =+F68 -> 1000 | H68: =+G68 -> 1000
A69: =A70+1 -> 2015 | B69: ='CPI-U & C-CPI-U Calcs'!$K21 -> 1.1503984 | C69: =C$76*$B69 -> 5751.9921 | D69: =+TRUNC(C69/500)*500 -> 5500 | E69: 5500 | F69: =+F71 -> 1000 | G69: =+F69 -> 1000 | H69: =+G69 -> 1000
A70: =A71+1 -> 2014 | B70: ='CPI-U & C-CPI-U Calcs'!$K22 -> 1.1325003 | C70: =C$76*$B70 -> 5662.5015 | D70: =+TRUNC(C70/500)*500 -> 5500 | E70: 5500 | F70: =+F71 -> 1000 | G70: =+F70 -> 1000 | H70: =+G70 -> 1000
A71: =A72+1 -> 2013 | B71: ='CPI-U & C-CPI-U Calcs'!$K23 -> 1.1136166 | C71: =C$76*$B71 -> 5568.083 | D71: =+TRUNC(C71/500)*500 -> 5500 | E71: 5500 | F71: =+F72 -> 1000 | G71: =+F71 -> 1000 | H71: =+G71 -> 1000
A72: =A73+1 -> 2012 | B72: ='CPI-U & C-CPI-U Calcs'!$K24 -> 1.0857118 | C72: =C$76*$B72 -> 5428.5592 | D72: =+TRUNC(C72/500)*500 -> 5000 | E72: 5000 | F72: =+F73 -> 1000 | G72: =+F72 -> 1000 | H72: =+G72 -> 1000
A73: =A74+1 -> 2011 | B73: ='CPI-U & C-CPI-U Calcs'!$K25 -> 1.0599922 | C73: =C$76*$B73 -> 5299.961 | D73: =+TRUNC(C73/500)*500 -> 5000 | E73: 5000 | F73: =+F74 -> 1000 | G73: =+F73 -> 1000 | H73: =+G73 -> 1000
A74: =A75+1 -> 2010 | B74: ='CPI-U & C-CPI-U Calcs'!$K26 -> 1.0445635 | C74: =C$76*$B74 -> 5222.8174 | D74: =+TRUNC(C74/500)*500 -> 5000 | E74: 5000 | F74: =+F75 -> 1000 | G74: =+F74 -> 1000 | H74: =+G74 -> 1000
A75: =A76+1 -> 2009 | B75: ='CPI-U & C-CPI-U Calcs'!$K27 -> 1.0426241 | C75: =C$76*$B75 -> 5213.1204 | D75: =+TRUNC(C75/500)*500 -> 5000 | E75: 5000 | F75: =+F76 -> 1000 | G75: =+F75 -> 1000 | H75: =+G75 -> 1000
A76: 2008 | B76: ='CPI-U & C-CPI-U Calcs'!$K28 -> 1 | C76: 5000 | D76: =+TRUNC(C76/500)*500 -> 5000 | F76: 1000 | G76: =+F76 -> 1000 | H76: =+G76 -> 1000
A77: * Maximum IRA contributions rounded down to the nearest $500
A78: * Maximum catch-up contribution are not indexed for inflation

Sheet CPI-U & C-CPI-U Calcs
A1: CPI (Consumer Price Index) Historical Data
A2: - Based Upon 9/1-8/31 Fiscal Year for Income Taxes
A3: - Based Upon 9/1-8/31 Fiscal Year for Estate & Gift Taxes
A4: - Based Upon 7/1-6/30 Fiscal Year for 401(k) Contributions
A6: 2016 Base Calculation | V6: Avg2016 | W6: 42248 | X6: 42278 | Y6: 42309 | Z6: 42339 | AA6: 42370 | AB6: 42401 | AC6: 42430 | AD6: 42461 | AE6: 42491 | AF6: 42522 | AG6: 42552 | AH6: 42583
A7: Base2016 | C7: =V8*(V7/V8) -> 135.993 | U7: C-CPI-U2016 | V7: =SUM(W7:AH7)/12 -> 135.993 | W7: 135.837 | X7: 135.735 | Y7: 135.393 | Z7: 134.788 | AA7: 134.966 | AB7: 134.953 | AC7: 135.655 | AD7: 136.332 | AE7: 136.895 | AF7: 137.329 | AG7: 137.007 | AH7: 137.026
A8: * Yes, the law really does seem to be a calculation of A*(B/A) … which of course simplifies to B. W…T…F? | U8: CPI2016 | V8: =SUM(W8:AH8)/12 -> 238.649 | W8: 237.945 | X8: 237.838 | Y8: 237.336 | Z8: 236.525 | AA8: 236.916 | AB8: 237.111 | AC8: 238.132 | AD8: 239.261 | AE8: 240.229 | AF8: 241.018 | AG8: 240.628 | AH8: 240.849
A11: Annual CPI Data - Based on BoY of September 1 | F11: Tax Cuts & Jobs Act - Tax Brackets, Std Deduct, AMT Exemption, Pass-thru QBI | G11: Tax Cuts & Jobs Act - Accumulated CPI for Sunset Back to Year 2017 | H11: Income Tax - 35% Sunset Bracket, Pers Exemption & Itemized Deduct Phase-outs | I11: Alternative Minimum Tax Exemption | J11: Estate & Lifetime Gift Exclusion | K11: IRA & Roth IRA Contribution Max | L11: Income Tax Ext. - 10% Sunset Bracket | M11: Old & Obsolete Sunset Rule (for end unit tests) | N11: Annual Gift & GST Tax Exclusions | O11: Income Tax - 28% & 33% Sunset Bracket | P11: Income Tax - 15% & 25% Sunset Bracket | R11: Personal Exemption | S11: Standard Deduction | T11: Monthly CPI Data
A12: Tax Year | B12: Avg Annual CPI | C12: Annual CPI Change (%) | D12: Annual CPI Change (num) | F12: Accum Adj Base Year 2018 | H12: Accum Adj Base Year 2013 | I12: Accum Adj Base Year 2012 | J12: Accum Adj Base Year 2011 | K12: Accum Adj Base Year 2008 | L12: Accum Adj Base Year 2003 | M12: Accum Adj Base Year 2000 | N12: Accum Adj Base Year 1998 | O12: Accum Adj Base Year 1994 | P12: Accum Adj Base Year 1993 | Q12: Accum Adj Base Year 1992 | R12: Accum Adj Base Year 1989 | S12: Accum Adj Base Year 1988 | T12: Tax Year | U12: COLA Adj | V12: Data Year | W12: Jan | X12: Feb | Y12: Mar | Z12: Apr | AA12: May | AB12: Jun | AC12: Jul | AD12: Aug | AE12: Sep | AF12: Oct | AG12: Nov | AH12: Dec | AI12: Tax Year Avg
A13: 2023 (est.) | B13: =SUM(AE14, AF14,AG14,AH14,W13,X13,Y13,Z13,AA13,AB13,AC13,AD13)/12 -> 200 | C13: 0.03 | D13: =C13 -> 0.03 | F13: =F14*(1+$D13) -> 1.1109794 | G13: =G14*(1+$D13) -> 1.1293095 | H13: =H14*(1+$D13) -> 1.181281 | I13: =I14*(1+$D13) -> 1.2116421 | J13: =J14*(1+$D13) -> 1.2410414 | K13: =K14*(1+$D13) -> 1.3154942 | L13: =L14*(1+$D13) -> 1.5083732 | M13: =M14*(1+$D13) -> 1.6319841 | ... S13: =S14*(1+$D13) -> 2.4066847 | T13: =T14+1 -> 2023 | U13: =(AI13-AI14)/AI14 -> 0.022986507 | V13: =V14+1 -> 2022 | W13: 200 | X13: 200 | Y13: 200 | Z13: 200 | AA13: 200 | AB13: 200 | AC13: 200 | AD13: 200 | AE13: 200 | AF13: 200 | AG13: 200 | AH13: 200 | AI13: =(SUM(AE14:AH14)+SUM(W13:AD13))/12 -> 200
A14: 2022 (est.) | B14: =SUM(AE15, AF15,AG15,AH15,W14,X14,Y14,Z14,AA14,AB14,AC14,AD14)/12 -> 195.506 | C14: 0.03 | D14: =C14 -> 0.03 | F14: =F15*(1+$D14) -> 1.0786208 | G14: =G15*(1+$D14) -> 1.096417 | H14: =H15*(1+$D14) -> 1.1468748 | I14: =I15*(1+$D14) -> 1.1763515 | J14: =J15*(1+$D14) -> 1.2048945 | K14: =K15*(1+$D14) -> 1.2771788 | L14: =L15*(1+$D14) -> 1.46444 | M14: =M15*(1+$D14) -> 1.5844506 | ... S14: =S15*(1+$D14) -> 2.3365871 | T14: =T15+1 -> 2022 | U14: =(AI14-AI15)/AI15 -> 0.35053243 | V14: =V15+1 -> 2021 | W14: 200 | X14: 200 | Y14: 200 | Z14: 200 | AA14: 200 | AB14: 200 | AC14: 200 | AD14: 200 | AE14: 200 | AF14: 200 | AG14: 200 | AH14: 200 | AI14: =(SUM(AE15:AH15)+SUM(W14:AD14))/12 -> 195.506
A15: =A16+1 -> 2021 | B15: =SUM(AE16, AF16,AG16,AH16,W15,X15,Y15,Z15,AA15,AB15,AC15,AD15)/12 -> 144.76217 | C15: =U15 -> 0.011059609 | D15: =C15 -> 0.011059609 | F15: =F16*(1+$D15) -> 1.0472046 | G15: =G16*(1+$D15) -> 1.0644825 | H15: =H16*(1+$D15) -> 1.1134707 | I15: =I16*(1+$D15) -> 1.1420889 | J15: =J16*(1+$D15) -> 1.1698005 | K15: =K16*(1+$D15) -> 1.2399794 | L15: =L16*(1+$D15) -> 1.4217864 | M15: =M16*(1+$D15) -> 1.5383015 | ... S15: =S16*(1+$D15) -> 2.2685312 | T15: =T16+1 -> 2021 | U15: =(AI15-AI16)/AI16 -> 0.011059609 | V15: =V16+1 -> 2020 | W15: 144.995 | X15: 145.39 | Y15: 145.005 | Z15: 143.847 | AA15: 143.8 | AB15: 144.651 | AC15: 145.405 | AD15: 145.853 | AE15: 146.072 | AF15: 200 | AG15: 200 | AH15: 200 | AI15: =(SUM(AE16:AH16)+SUM(W15:AD15))/12 -> 144.76217
A16: =A17+1 -> 2020 | B16: =SUM(AE17, AF17,AG17,AH17,W16,X16,Y16,Z16,AA16,AB16,AC16,AD16)/12 -> 143.17867 | C16: =U16 -> 0.015509754 | D16: =C16 -> 0.015509754 | F16: =F17*(1+$D16) -> 1.0357497 | G16: =G17*(1+$D16) -> 1.0528385 | H16: =H17*(1+$D16) -> 1.1012908 | I16: =I17*(1+$D16) -> 1.129596 | J16: =J17*(1+$D16) -> 1.1570045 | K16: =K17*(1+$D16) -> 1.2264157 | L16: =L17*(1+$D16) -> 1.406234 | M16: =M17*(1+$D16) -> 1.5214746 | ... S16: =S17*(1+$D16) -> 2.2437165 | T16: =T17+1 -> 2020 | U16: =(AI16-AI17)/AI17 -> 0.015509754 | V16: =V17+1 -> 2019 | W16: 142.001 | X16: 142.571 | Y16: 143.297 | Z16: 143.926 | AA16: 144.183 | AB16: 144.243 | AC16: 144.409 | AD16: 144.388 | AE16: 144.428 | AF16: 144.722 | AG16: 144.613 | AH16: 144.437 | AI16: =(SUM(AE17:AH17)+SUM(W16:AD16))/12 -> 143.17867
A17: =A18+1 -> 2019 | B17: =SUM(AE18, AF18,AG18,AH18,W17,X17,Y17,Z17,AA17,AB17,AC17,AD17)/12 -> 140.99192 | C17: =U17 -> 0.019930783 | D17: =C17 -> 0.019930783 | F17: =F18*(1+$D17) -> 1.0199308 | G17: =G18*(1+$D17) -> 1.0367586 | H17: =H18*(1+$D17) -> 1.0844709 | I17: =I18*(1+$D17) -> 1.1123438 | J17: =J18*(1+$D17) -> 1.1393337 | K17: =K18*(1+$D17) -> 1.2076848 | L17: =L18*(1+$D17) -> 1.3847567 | M17: =M18*(1+$D17) -> 1.4982373 | ... S17: =S18*(1+$D17) -> 2.2094485 | T17: 2019 | U17: =(AI17-AI18)/AI18 -> 0.019930783 | V17: =V18+1 -> 2018 | W17: 140.239 | X17: 140.805 | Y17: 141.142 | Z17: 141.662 | AA17: 142.146 | AB17: 142.349 | AC17: 142.317 | AD17: 142.317 | AE17: 142.489 | AF17: 142.7 | AG17: 142.238 | AH17: 141.699 | AI17: =(SUM(AE18:AH18)+SUM(W17:AD17))/12 -> 140.99192
A18: =A19+1 -> 2018 | B18: =SUM(AE19, AF19,AG19,AH19,W18,X18,Y18,Z18,AA18,AB18,AC18,AD18)/12 -> 138.23675 | C18: =U18 -> 0.016499011 | D18: =C18 -> 0.016499011 | F18: 1 | G18: =G19*(1+$D18) -> 1.016499 | H18: =H19*(1+$D18) -> 1.063279 | I18: =I19*(1+$D18) -> 1.0906071 | J18: =J19*(1+$D18) -> 1.1170696 | K18: =K19*(1+$D18) -> 1.1840851 | L18: =L19*(1+$D18) -> 1.3576968 | M18: =M19*(1+$D18) -> 1.4689598 | N18: =N19*(1+$D18) -> 1.5209978 | ... S18: =S19*(1+$D18) -> 2.166273 | T18: *2018 | U18: =(AI18-$C$7)/$C$7 -> 0.016499011 | V18: =V19+1 -> 2017 | W18: 138.035 | X18: 138.403 | Y18: 138.461 | Z18: 138.81 | AA18: 138.922 | AB18: 138.989 | AC18: 138.755 | AD18: 139.128 | AE18: 139.878 | AF18: 139.782 | AG18: 139.72 | AH18: 139.546 | AI18: =(SUM(AE19:AH19)+SUM(W18:AD18))/12 -> 138.23675
A19: =A20+1 -> 2017 | B19: =SUM(AE20, AF20,AG20,AH20,W19,X19,Y19,Z19,AA19,AB19,AC19,AD19)/12 -> 238.649 | C19: =U19 -> 0.0080257319 | D19: =C19 -> 0.0080257319 | G19: 1 | H19: =H20*(1+$D19) -> 1.0460206 | I19: =I20*(1+$D19) -> 1.0729053 | J19: =J20*(1+$D19) -> 1.0989382 | K19: =K20*(1+$D19) -> 1.164866 | L19: =L20*(1+$D19) -> 1.3356597 | M19: =M20*(1+$D19) -> 1.4451168 | N19: =N20*(1+$D19) -> 1.4963102 | O19: =O20*(1+$D19) -> 1.6668343 | ... S19: =S20*(1+$D19) -> 2.1311118 | T19: =T20+1 -> 2017 | U19: =(AI19-AI20)/AI20 -> 0.0080257319 | V19: =V20+1 -> 2016 | W19: 236.916 | X19: 237.111 | Y19: 238.132 | Z19: 239.261 | AA19: 240.229 | AB19: 241.018 | AC19: 240.628 | AD19: 240.849 | AE19: 137.328 | AF19: 137.536 | AG19: 137.253 | AH19: 137.221 | AI19: =(SUM(AE20:AH20)+SUM(W19:AD19))/12 -> 238.649
A20: =A21+1 -> 2016 | B20: =SUM(AE21, AF21,AG21,AH21,W20,X20,Y20,Z20,AA20,AB20,AC20,AD20)/12 -> 236.74892 | C20: =U20 -> 0.0045141467 | D20: =C20 -> 0.0045141467 | H20: =H21*(1+$D20) -> 1.0376924 | I20: =I21*(1+$D20) -> 1.064363 | J20: =J21*(1+$D20) -> 1.0901887 | K20: =K21*(1+$D20) -> 1.1555915 | L20: =L21*(1+$D20) -> 1.3250254 | M20: =M21*(1+$D20) -> 1.433611 | N20: =N21*(1+$D20) -> 1.4843968 | O20: =O21*(1+$D20) -> 1.6535632 | ... S20: =S21*(1+$D20) -> 2.1141442 | T20: =T21+1 -> 2016 | U20: =(AI20-AI21)/AI21 -> 0.0045141467 | V20: =V21+1 -> 2015 | W20: 233.707 | X20: 234.722 | Y20: 236.119 | Z20: 236.599 | AA20: 237.805 | AB20: 238.638 | AC20: 238.654 | AD20: 238.316 | AE20: 237.945 | AF20: 237.838 | AG20: 237.336 | AH20: 236.525 | AI20: =(SUM(AE21:AH21)+SUM(W20:AD20))/12 -> 236.74892
A21: =A22+1 -> 2015 | B21: =SUM(AE22, AF22,AG22,AH22,W21,X21,Y21,Z21,AA21,AB21,AC21,AD21)/12 -> 235.685 | C21: =U21 -> 0.015804079 | D21: =C21 -> 0.015804079 | H21: =H22*(1+$D21) -> 1.0330292 | I21: =I22*(1+$D21) -> 1.0595799 | J21: =J22*(1+$D21) -> 1.0852895 | K21: =K22*(1+$D21) -> 1.1503984 | L21: =L22*(1+$D21) -> 1.3190709 | M21: =M22*(1+$D21) -> 1.4271686 | N21: =N22*(1+$D21) -> 1.4777261 | O21: =O22*(1+$D21) -> 1.6461324 | ... S21: =S22*(1+$D21) -> 2.1046435 | T21: =T22+1 -> 2015 | U21: =(AI21-AI22)/AI22 -> 0.015804079 | V21: =V22+1 -> 2014 | W21: 233.916 | X21: 234.781 | Y21: 236.293 | Z21: 237.072 | AA21: 237.9 | AB21: 238.343 | AC21: 238.25 | AD21: 237.852 | AE21: 238.031 | AF21: 237.433 | AG21: 236.151 | AH21: 234.812 | AI21: =(SUM(AE22:AH22)+SUM(W21:AD21))/12 -> 235.685
A22: =A23+1 -> 2014 | B22: =SUM(AE23, AF23,AG23,AH23,W22,X22,Y22,Z22,AA22,AB22,AC22,AD22)/12 -> 232.01817 | C22: =U22 -> 0.016957089 | D22: =C22 -> 0.016957089 | H22: =H23*(1+$D22) -> 1.0169571 | I22: =I23*(1+$D22) -> 1.0430947 | J22: =J23*(1+$D22) -> 1.0684044 | K22: =K23*(1+$D22) -> 1.1325003 | L22: =L23*(1+$D22) -> 1.2985486 | M22: =M23*(1+$D22) -> 1.4049644 | N22: =N23*(1+$D22) -> 1.4547354 | O22: =O23*(1+$D22) -> 1.6205215 | ... S22: =S23*(1+$D22) -> 2.0718991 | T22: =T23+1 -> 2014 | U22: =(AI22-AI23)/AI23 -> 0.016957089 | V22: =V23+1 -> 2013 | W22: 230.28 | X22: 232.166 | Y22: 232.773 | Z22: 232.531 | AA22: 232.945 | AB22: 233.504 | AC22: 233.596 | AD22: 233.877 | AE22: 234.149 | AF22: 233.546 | AG22: 233.069 | AH22: 233.049 | AI22: =(SUM(AE23:AH23)+SUM(W22:AD22))/12 -> 232.01817
A23: =A24+1 -> 2013 | B23: =SUM(AE24, AF24,AG24,AH24,W23,X23,Y23,Z23,AA23,AB23,AC23,AD23)/12 -> 228.14942 | C23: =U23 -> 0.025701805 | D23: =C23 -> 0.025701805 | H23: 1 | I23: =I24*(1+$D23) -> 1.0257018 | J23: =J24*(1+$D23) -> 1.0505894 | K23: =K24*(1+$D23) -> 1.1136166 | L23: =L24*(1+$D23) -> 1.2768961 | M23: =M24*(1+$D23) -> 1.3815376 | N23: =N24*(1+$D23) -> 1.4304786 | O23: =O24*(1+$D23) -> 1.5935004 | P23: =P24*(1+$D23) -> 1.6422488 | ... S23: =S24*(1+$D23) -> 2.0373515 | T23: =T24+1 -> 2013 | U23: =(AI23-AI24)/AI24 -> 0.025701805 | V23: =V24+1 -> 2012 | W23: 226.665 | X23: 227.663 | Y23: 229.392 | Z23: 230.085 | AA23: 229.815 | AB23: 229.478 | AC23: 229.104 | AD23: 230.379 | AE23: 231.407 | AF23: 231.317 | AG23: 230.221 | AH23: 229.601 | AI23: =(SUM(AE24:AH24)+SUM(W23:AD23))/12 -> 228.14942
